Workbook

Sheet Setembro
A1: Planejamento Mensal Káic e Gabi | I1: Mês: | J1: Abril
A2: Data hoje formula | B2: Data formula | C2: Formula pgto ok | G2: Saldo Prévio | H2: Descrição Conta | I2: Valor | J2: Data vencimento | K2: Pago?
A3: =TODAY() -> 45567 | B3: 45017 | C3: =A3-B3 -> 550 | D3: =C3+K3 -> #VALUE! | E3: =IF(10,K3="ok",0) -> TRUE | F3: Dia 1 | G3: =I3 -> 0 | K3: ok | L3: =IF(A3=B3,"➜ Hoje","")
A4: =TODAY() -> 45567 | B4: 45018 | C4: =A4-B4 -> 549 | D4: =C4+K4 -> #VALUE! | E4: =IF(10,K4="ok",0) -> TRUE | F4: Dia 2 | G4: =G3+I4 -> 0 | K4: ok | L4: =IF(A4=B4,"➜ Hoje","")
A5: =TODAY() -> 45567 | B5: 45019 | C5: =A5-B5 -> 548 | D5: =C5+K5 -> #VALUE! | E5: =IF(10,K5="ok",0) -> TRUE | F5: Dia 3 | G5: =G4+I5 -> 0 | K5: ok | L5: =IF(A5=B5,"➜ Hoje","")
A6: =TODAY() -> 45567 | B6: 45020 | C6: =A6-B6 -> 547 | D6: =C6+K6 -> #VALUE! | E6: =IF(10,K6="ok",0) -> TRUE | F6: Dia 4 | G6: =G5+I6 -> 0 | K6: ok | L6: =IF(A6=B6,"➜ Hoje","")
A7: =TODAY() -> 45567 | B7: 45021 | C7: =A7-B7 -> 546 | D7: =C7+K7 -> #VALUE! | E7: =IF(10,K7="ok",0) -> TRUE | F7: Dia 5 | G7: =G6+I7 -> 1000 | H7: Pagamento Recebido Bellocopo | I7: 1000 | J7: Dia 5 | K7: ok | L7: =IF(A7=B7,"➜ Hoje","")
A8: =TODAY() -> 45567 | B8: 45022 | C8: =A8-B8 -> 545 | D8: =C8+K8 -> #VALUE! | E8: =IF(10,K8="ok",0) -> TRUE | F8: Dia 6 | G8: =G7+I8 -> 2700 | H8: Pagamento Recebido CD Medical Care | I8: 1700 | J8: Dia 6 | K8: ok | L8: =IF(A8=B8,"➜ Hoje","")
A9: =TODAY() -> 45567 | B9: 45023 | C9: =A9-B9 -> 544 | D9: =C9+K9 -> #VALUE! | E9: =IF(10,K9="ok",0) -> TRUE | F9: Dia 7 | G9: =G8+I9 -> 2640.4 | H9: Areia Gatíssimo (x4 Unidades) | I9: -59.6 | J9: Dia 6 | K9: ok | L9: =IF(A9=B9,"➜ Hoje","")
A10: =TODAY() -> 45567 | B10: 45024 | C10: =A10-B10 -> 543 | D10: =C10+K10 -> #VALUE! | E10: =IF(10,K10="ok",0) -> TRUE | F10: Dia 8 | G10: =G9+I10 -> 2601.4 | H10: Microsoft | I10: -39 | J10: Dia 6 | K10: ok | L10: =IF(A10=B10,"➜ Hoje","")
A11: =TODAY() -> 45567 | B11: 45025 | C11: =A11-B11 -> 542 | D11: =C11+K11 -> #VALUE! | E11: =IF(10,K11="ok",0) -> TRUE | F11: Dia 9 | G11: =G10+I11 -> 2501.4 | H11: Unhas | I11: -100 | J11: Dia 6 | K11: ok | L11: =IF(A11=B11,"➜ Hoje","")
A12: =TODAY() -> 45567 | B12: 45026 | C12: =A12-B12 -> 541 | D12: =C12+K12 -> #VALUE! | E12: =IF(10,K12="ok",0) -> TRUE | F12: Dia 10 | G12: =G11+I12 -> 2101.4 | H12: Psicóloga | I12: -400 | J12: Dia 7 | K12: ok | L12: =IF(A12=B12,"➜ Hoje","")
A13: =TODAY() -> 45567 | B13: 45027 | C13: =A13-B13 -> 540 | D13: =C13+K13 -> #VALUE! | E13: =IF(10,K13="ok",0) -> TRUE | F13: Dia 11 | G13: =G12+I13 -> 1991.4 | H13: Energia Elétrica (1/4 pagamento) | I13: -110 | J13: Dia 8 | K13: ok | L13: =IF(A13=B13,"➜ Hoje","")
A14: =TODAY() -> 45567 | B14: 45028 | C14: =A14-B14 -> 539 | D14: =C14+K14 -> #VALUE! | E14: =IF(10,K14="ok",0) -> TRUE | F14: Dia 12 | G14: =G13+I14 -> 1991.4 | K14: ok | L14: =IF(A14=B14,"➜ Hoje","")
A15: =TODAY() -> 45567 | B15: 45029 | C15: =A15-B15 -> 538 | D15: =C15+K15 -> #VALUE! | E15: =IF(10,K15="ok",0) -> TRUE | F15: Dia 13 | G15: =G14+I15 -> 1991.4 | K15: ok | L15: =IF(A15=B15,"➜ Hoje","")
A16: =TODAY() -> 45567 | B16: 45030 | C16: =A16-B16 -> 537 | D16: =C16+K16 -> #VALUE! | E16: =IF(10,K16="ok",0) -> TRUE | F16: Dia 14 | G16: =G15+I16 -> 1991.4 | K16: ok | L16: =IF(A16=B16,"➜ Hoje","")
A17: =TODAY() -> 45567 | B17: 45031 | C17: =A17-B17 -> 536 | D17: =C17+K17 -> #VALUE! | E17: =IF(10,K17="ok",0) -> TRUE | F17: Dia 15 | G17: =G16+I17 -> 2131.4 | H17: Pagamento Recebido VA Bellocopo | I17: 140 | J17: Dia 15 | K17: ok | L17: =IF(A17=B17,"➜ Hoje","")
A18: =TODAY() -> 45567 | B18: 45032 | C18: =A18-B18 -> 535 | D18: =C18+K18 -> #VALUE! | E18: =IF(10,K18="ok",0) -> TRUE | F18: Dia 16 | G18: =G17+I18 -> 1991.4 | H18: Alimentação Misturas (Compras Mercado) | I18: -140 | J18: Dia 16 | K18: ok | L18: =IF(A18=B18,"➜ Hoje","")
A19: =TODAY() -> 45567 | B19: 45033 | C19: =A19-B19 -> 534 | D19: =C19+K19 -> #VALUE! | E19: =IF(10,K19="ok",0) -> TRUE | F19: Dia 17 | G19: =G18+I19 -> 1991.4 | K19: ok | L19: =IF(A19=B19,"➜ Hoje","")
A20: =TODAY() -> 45567 | B20: 45034 | C20: =A20-B20 -> 533 | D20: =C20+K20 -> #VALUE! | E20: =IF(10,K20="ok",0) -> TRUE | F20: Dia 18 | G20: =G19+I20 -> 1991.4 | K20: ok | L20: =IF(A20=B20,"➜ Hoje","")
A21: =TODAY() -> 45567 | B21: 45035 | C21: =A21-B21 -> 532 | D21: =C21+K21 -> #VALUE! | E21: =IF(10,K21="ok",0) -> TRUE | F21: Dia 19 | G21: =G20+I21 -> 1631.4 | H21: Geladeira (1/11 Parcelas) | I21: -360 | K21: ok | L21: =IF(A21=B21,"➜ Hoje","")
A22: =TODAY() -> 45567 | B22: 45036 | C22: =A22-B22 -> 531 | D22: =C22+K22 -> #VALUE! | E22: =IF(10,K22="ok",0) -> TRUE | F22: Dia 20 | G22: =G21+I22 -> 2631.4 | H22: Pagamento Recebido Bellocopo | I22: 1000 | J22: Dia 20 | K22: ok | L22: =IF(A22=B22,"➜ Hoje","")
A23: =TODAY() -> 45567 | B23: 45037 | C23: =A23-B23 -> 530 | D23: =C23+K23 -> #VALUE! | E23: =IF(10,K23="ok",0) -> TRUE | F23: Dia 21 | G23: =G22+I23 -> 2631.4 | K23: ok | L23: =IF(A23=B23,"➜ Hoje","")
A24: =TODAY() -> 45567 | B24: 45038 | C24: =A24-B24 -> 529 | D24: =C24+K24 -> #VALUE! | E24: =IF(10,K24="ok",0) -> TRUE | F24: Dia 22 | G24: =G23+I24 -> 2631.4 | K24: ok | L24: =IF(A24=B24,"➜ Hoje","")
A25: =TODAY() -> 45567 | B25: 45039 | C25: =A25-B25 -> 528 | D25: =C25+K25 -> #VALUE! | E25: =IF(10,K25="ok",0) -> TRUE | F25: Dia 23 | G25: 0 | K25: ok | L25: =IF(A25=B25,"➜ Hoje","")
A26: =TODAY() -> 45567 | B26: 45040 | C26: =A26-B26 -> 527 | D26: =C26+K26 -> #VALUE! | E26: =IF(10,K26="ok",0) -> TRUE | F26: Dia 24 | G26: =G25+I26 -> 0 | K26: ok | L26: =IF(A26=B26,"➜ Hoje","")
A27: =TODAY() -> 45567 | B27: 45041 | C27: =A27-B27 -> 526 | D27: =C27+K27 -> #VALUE! | E27: =IF(10,K27="ok",0) -> TRUE | F27: Dia 25 | G27: =G26+I27 -> 0 | K27: ok | L27: =IF(A27=B27,"➜ Hoje","")
A28: =TODAY() -> 45567 | B28: 45042 | C28: =A28-B28 -> 525 | D28: =C28+K28 -> #VALUE! | E28: =IF(10,K28="ok",0) -> TRUE | F28: Dia 26 | G28: =G27+I28 -> -21 | H28: Cartão Bradesco (Cheque especial) | I28: -21 | K28: ok | L28: =IF(A28=B28,"➜ Hoje","")
A29: =TODAY() -> 45567 | B29: 45043 | C29: =A29-B29 -> 524 | D29: =C29+K29 -> #VALUE! | E29: =IF(10,K29="ok",0) -> TRUE | F29: Dia 27 | G29: =G28+I29 -> -66 | H29: Internet Celular Vivo | I29: -45 | J29: Dia 27 | K29: ok | L29: =IF(A29=B29,"➜ Hoje","")
A30: =TODAY() -> 45567 | B30: 45044 | C30: =A30-B30 -> 523 | D30: =C30+K30 -> #VALUE! | E30: =IF(10,K30="ok",0) -> TRUE | F30: Dia 28 | G30: =G29+I30 -> -146 | H30: Cílios | I30: -80 | J30: Dia 28 | K30: ok | L30: =IF(A30=B30,"➜ Hoje","")
A31: =TODAY() -> 45567 | B31: 45045 | C31: =A31-B31 -> 522 | D31: =C31+K31 -> 522 | E31: =IF(10,K31="ok",0) -> FALSE | F31: Dia 29 | G31: =G30+I31 -> -163.45 | H31: HBO | I31: -17.45 | L31: =IF(A31=B31,"➜ Hoje","")
A32: =TODAY() -> 45567 | B32: 45046 | C32: =A32-B32 -> 521 | D32: =C32+K32 -> #VALUE! | E32: =IF(10,K32="ok",0) -> TRUE | F32: Dia 30 | G32: =G31+I32 -> -163.45 | K32: ok | L32: =IF(A32=B32,"➜ Hoje","")
A33: =TODAY() -> 45567 | B33: 45077 | C33: =A33-B33 -> 490 | D33: =C33+K33 -> 490 | E33: =IF(10,K33="ok",0) -> FALSE | F33: Dia 31 | G33: 0 | L33: =IF(A33=B33,"➜ Hoje","")

Sheet Maio
A1: Planejamento Mensal Káic e Gabi | I1: Mês: | J1: Maio | M1: Resumo Finalização do Mês | S1: 0
A2: Data hoje formula | B2: Data formula | C2: Formula pgto ok | G2: Saldo Prévio | H2: Descrição Conta | I2: Valor | J2: Data vencimento | K2: Pago? | M2: =F33 -> Dia 31 | N2: =G33 -> 294.55 | O2: Valor sobra dia 31 - Final do mês
A3: =TODAY() -> 45567 | B3: 45047 | C3: =A3-B3 -> 520 | D3: =C3+K3 -> #VALUE! | E3: =IF(10,K3="ok",0) -> TRUE | F3: Dia 1 | G3: =Setembro!G33+I3 -> -260 | H3: Cartão Transporte | I3: -260 | J3: Dia 1 | K3: ok | L3: =IF(A3=B3,"➜ Hoje","")
A4: =TODAY() -> 45567 | B4: 45048 | C4: =A4-B4 -> 519 | D4: =C4+K4 -> #VALUE! | E4: =IF(10,K4="ok",0) -> TRUE | F4: Dia 2 | G4: =G3+I4 -> -260 | K4: ok | L4: =IF(A4=B4,"➜ Hoje","") | M4: 0.2 | N4: =N2*M4 -> 58.91 | O4: Comemoraçao dia 20
A5: =TODAY() -> 45567 | B5: 45049 | C5: =A5-B5 -> 518 | D5: =C5+K5 -> #VALUE! | E5: =IF(10,K5="ok",0) -> TRUE | F5: Dia 3 | G5: =G4+I5 -> -260 | K5: ok | L5: =IF(A5=B5,"➜ Hoje","") | M5: 0.1 | N5: =N2*M5 -> 29.455 | O5: Reforma/Construção Gatódromo
A6: =TODAY() -> 45567 | B6: 45050 | C6: =A6-B6 -> 517 | D6: =C6+K6 -> #VALUE! | E6: =IF(10,K6="ok",0) -> TRUE | F6: Dia 4 | G6: =G5+I6 -> -440 | H6: Manutenção Guitarra Cort X6 | I6: -180 | J6: Dia 5 | K6: ok | L6: =IF(A6=B6,"➜ Hoje","") | M6: 0.4 | N6: =N2*M6 -> 117.82 | O6: Reforma Cozinha
A7: =TODAY() -> 45567 | B7: 45051 | C7: =A7-B7 -> 516 | D7: =C7+K7 -> #VALUE! | E7: =IF(10,K7="ok",0) -> TRUE | F7: Dia 5 | G7: =G6+I7 -> 700 | H7: Pagamento Recebido Bellocopo | I7: 1140 | J7: Dia 5 | K7: ok | L7: =IF(A7=B7,"➜ Hoje","") | M7: 0.3 | N7: =N2*M7 -> 88.365 | O7: Tirar Carta pra comprar Moto
A8: =TODAY() -> 45567 | B8: 45052 | C8: =A8-B8 -> 515 | D8: =C8+K8 -> #VALUE! | E8: =IF(10,K8="ok",0) -> TRUE | F8: Dia 6 | G8: =G7+I8 -> 2950 | H8: Pagamento Recebido CD Medical Care | I8: 2250 | J8: Dia 6 | K8: ok | L8: =IF(A8=B8,"➜ Hoje","")
A9: =TODAY() -> 45567 | B9: 45053 | C9: =A9-B9 -> 514 | D9: =C9+K9 -> #VALUE! | E9: =IF(10,K9="ok",0) -> TRUE | F9: Dia 7 | G9: =G8+I9 -> 2780 | H9: Ração Gatos Castrados Ultralife | I9: -170 | J9: Dia 6 | K9: ok | L9: =IF(A9=B9,"➜ Hoje","") | M9: Planejamento Aquisições / Projetos
A10: =TODAY() -> 45567 | B10: 45054 | C10: =A10-B10 -> 513 | D10: =C10+K10 -> #VALUE! | E10: =IF(10,K10="ok",0) -> TRUE | F10: Dia 8 | G10: =G9+I10 -> 2741 | H10: Microsoft | I10: -39 | J10: Dia 6 | K10: ok | L10: =IF(A10=B10,"➜ Hoje","")
A11: =TODAY() -> 45567 | B11: 45055 | C11: =A11-B11 -> 512 | D11: =C11+K11 -> #VALUE! | E11: =IF(10,K11="ok",0) -> TRUE | F11: Dia 9 | G11: =G10+I11 -> 2641 | H11: Unhas | I11: -100 | J11: Dia 6 | K11: ok | L11: =IF(A11=B11,"➜ Hoje","") | M11: Data | N11: Valor média | O11: Descrição
A12: =TODAY() -> 45567 | B12: 45056 | C12: =A12-B12 -> 511 | D12: =C12+K12 -> #VALUE! | E12: =IF(10,K12="ok",0) -> TRUE | F12: Dia 10 | G12: =G11+I12 -> 2241 | H12: Psicóloga | I12: -400 | J12: Dia 7 | K12: ok | L12: =IF(A12=B12,"➜ Hoje","") | M12: 45046 | N12: 400 | O12: Depurador de ar (Reforma Cozinha)
A13: =TODAY() -> 45567 | B13: 45057 | C13: =A13-B13 -> 510 | D13: =C13+K13 -> #VALUE! | E13: =IF(10,K13="ok",0) -> TRUE | F13: Dia 11 | G13: =G12+I13 -> 2121 | H13: Energia Elétrica (1/4 pagamento) | I13: -120 | J13: Dia 8 | K13: ok | L13: =IF(A13=B13,"➜ Hoje","") | M13: 44540 | N13: 300 | O13: Revestimento Lume 45x90 Botanico Branco Retif.Azulejo (Reforma Cozinha)
A14: =TODAY() -> 45567 | B14: 45058 | C14: =A14-B14 -> 509 | D14: =C14+K14 -> 509 | E14: =IF(10,K14="ok",0) -> FALSE | F14: Dia 12 | G14: =G13+I14 -> 2011 | H14: Dízimo (1/2 parte) | I14: -110 | J14: Dia 9 | L14: =IF(A14=B14,"➜ Hoje","") | M14: 45041 | N14: 400 | O14: Mesa de Cabeceira Armario modulado Amendola Grafito (Reforma Cozinha)
A15: =TODAY() -> 45567 | B15: 45059 | C15: =A15-B15 -> 508 | D15: =C15+K15 -> #VALUE! | E15: =IF(10,K15="ok",0) -> TRUE | F15: Dia 13 | G15: =G14+I15 -> 1241 | H15: Fatura Cartão Nubank | I15: -770 | J15: Dia 12 | K15: ok | L15: =IF(A15=B15,"➜ Hoje","") | M15: 45046 | N15: 350 | O15: Balcao Madesa Glamy 35cm 1porta (Reforma Cozinha)
A16: =TODAY() -> 45567 | B16: 45060 | C16: =A16-B16 -> 507 | D16: =C16+K16 -> #VALUE! | E16: =IF(10,K16="ok",0) -> TRUE | F16: Dia 14 | G16: =G15+I16 -> 881 | H16: Geladeira (1/11 Parcelas) | I16: -360 | J16: Dia 13 | K16: ok | L16: =IF(A16=B16,"➜ Hoje","")
A17: =TODAY() -> 45567 | B17: 45061 | C17: =A17-B17 -> 506 | D17: =C17+K17 -> #VALUE! | E17: =IF(10,K17="ok",0) -> TRUE | F17: Dia 15 | G17: =G16+I17 -> 801 | H17: Curso Administração | I17: -80 | J17: Dia 13 | K17: ok | L17: =IF(A17=B17,"➜ Hoje","")
A18: =TODAY() -> 45567 | B18: 45062 | C18: =A18-B18 -> 505 | D18: =C18+K18 -> #VALUE! | E18: =IF(10,K18="ok",0) -> TRUE | F18: Dia 16 | G18: =G17+I18 -> 771.9 | H18: Granulado MimiCat (1/2 unidades) | I18: -29.1 | J18: Dia 5 | K18: ok | L18: =IF(A18=B18,"➜ Hoje","") | M18: Planejamento Reposição Dispensa / Compras Mercado
A19: =TODAY() -> 45567 | B19: 45063 | C19: =A19-B19 -> 504 | D19: =C19+K19 -> #VALUE! | E19: =IF(10,K19="ok",0) -> TRUE | F19: Dia 17 | G19: =G18+I19 -> 731.9 | H19: Netflix - Automatico | I19: -40 | J19: Dia 17 | K19: ok | L19: =IF(A19=B19,"➜ Hoje","")
A20: =TODAY() -> 45567 | B20: 45064 | C20: =A20-B20 -> 503 | D20: =C20+K20 -> #VALUE! | E20: =IF(10,K20="ok",0) -> TRUE | F20: Dia 18 | G20: =G19+I20 -> 581.9 | H20: Madeirite plastificado 2200x1100 (1/2) | I20: -150 | J20: Dia 18 | K20: ok | L20: =IF(A20=B20,"➜ Hoje","") | M20: Dia 10 | N20: 500 | O20: Pagamento recebido VA + VR CD Medical Care
A21: =TODAY() -> 45567 | B21: 45065 | C21: =A21-B21 -> 502 | D21: =C21+K21 -> #VALUE! | E21: =IF(10,K21="ok",0) -> TRUE | F21: Dia 19 | G21: =G20+I21 -> 531.9 | H21: Cartão de todos - Automatico | I21: -50 | J21: Dia 19 | K21: ok | L21: =IF(A21=B21,"➜ Hoje","") | M21: Dia 15 | N21: 140 | O21: Pagamento Recebido VA Bellocopo
A22: =TODAY() -> 45567 | B22: 45066 | C22: =A22-B22 -> 501 | D22: =C22+K22 -> #VALUE! | E22: =IF(10,K22="ok",0) -> TRUE | F22: Dia 20 | G22: =G21+I22 -> 1531.9 | H22: Pagamento Recebido Bellocopo | I22: 1000 | J22: Dia 20 | K22: ok | L22: =IF(A22=B22,"➜ Hoje","")
A23: =TODAY() -> 45567 | B23: 45067 | C23: =A23-B23 -> 500 | D23: =C23+K23 -> #VALUE! | E23: =IF(10,K23="ok",0) -> TRUE | F23: Dia 21 | G23: =G22+I23 -> 1516.9 | H23: Nível 6 Mercado Livre - Automatico | I23: -15 | J23: Dia 20 | K23: ok | L23: =IF(A23=B23,"➜ Hoje","")
A24: =TODAY() -> 45567 | B24: 45068 | C24: =A24-B24 -> 499 | D24: =C24+K24 -> #VALUE! | E24: =IF(10,K24="ok",0) -> TRUE | F24: Dia 22 | G24: =G23+I24 -> 1412 | H24: Internet Atranet | I24: -104.9 | J24: Dia 20 | K24: ok | L24: =IF(A24=B24,"➜ Hoje","")
A25: =TODAY() -> 45567 | B25: 45069 | C25: =A25-B25 -> 498 | D25: =C25+K25 -> #VALUE! | E25: =IF(10,K25="ok",0) -> TRUE | F25: Dia 23 | G25: =G24+I25 -> 547 | H25: Fatura Cartão Mercado Livre | I25: -865 | J25: Dia 22 | K25: ok | L25: =IF(A25=B25,"➜ Hoje","")
A26: =TODAY() -> 45567 | B26: 45070 | C26: =A26-B26 -> 497 | D26: =C26+K26 -> 497 | E26: =IF(10,K26="ok",0) -> FALSE | F26: Dia 24 | G26: =G25+I26 -> 437 | H26: Dízimo (2/2 parte) | I26: -110 | J26: Dia 24 | L26: =IF(A26=B26,"➜ Hoje","")
A27: =TODAY() -> 45567 | B27: 45071 | C27: =A27-B27 -> 496 | D27: =C27+K27 -> 496 | E27: =IF(10,K27="ok",0) -> FALSE | F27: Dia 25 | G27: =G26+I27 -> 437 | L27: =IF(A27=B27,"➜ Hoje","") | O27: Areia Gatíssimo (x4 unidades) | P27: -59.6 | Q27: Dia 6
A28: =TODAY() -> 45567 | B28: 45072 | C28: =A28-B28 -> 495 | D28: =C28+K28 -> 495 | E28: =IF(10,K28="ok",0) -> FALSE | F28: Dia 26 | G28: =G27+I28 -> 437 | L28: =IF(A28=B28,"➜ Hoje","") | O28: Alterado para
A29: =TODAY() -> 45567 | B29: 45073 | C29: =A29-B29 -> 494 | D29: =C29+K29 -> 494 | E29: =IF(10,K29="ok",0) -> FALSE | F29: Dia 27 | G29: =G28+I29 -> 392 | H29: Internet Celular Vivo | I29: -45 | J29: Dia 27 | L29: =IF(A29=B29,"➜ Hoje","") | O29: Granulado MimiCat (x3 unidades) | P29: -29.1 | Q29: Dia 5
A30: =TODAY() -> 45567 | B30: 45074 | C30: =A30-B30 -> 493 | D30: =C30+K30 -> #VALUE! | E30: =IF(10,K30="ok",0) -> TRUE | F30: Dia 28 | G30: =G29+I30 -> 312 | H30: Cílios | I30: -80 | J30: Dia 28 | K30: ok | L30: =IF(A30=B30,"➜ Hoje","")
A31: =TODAY() -> 45567 | B31: 45075 | C31: =A31-B31 -> 492 | D31: =C31+K31 -> 492 | E31: =IF(10,K31="ok",0) -> FALSE | F31: Dia 29 | G31: =G30+I31 -> 294.55 | H31: HBO | I31: -17.45 | J31: Dia 29 | L31: =IF(A31=B31,"➜ Hoje","")
A32: =TODAY() -> 45567 | B32: 45076 | C32: =A32-B32 -> 491 | D32: =C32+K32 -> 491 | E32: =IF(10,K32="ok",0) -> FALSE | F32: Dia 30 | G32: =G31+I32 -> 294.55 | L32: =IF(A32=B32,"➜ Hoje","")
A33: =TODAY() -> 45567 | B33: 45077 | C33: =A33-B33 -> 490 | D33: =C33+K33 -> 490 | E33: =IF(10,K33="ok",0) -> FALSE | F33: Dia 31 | G33: =G32+I33 -> 294.55 | L33: =IF(A33=B33,"➜ Hoje","")
M34: Pendencias para pagar
M36: {=F2:K33} -> 0 | N36: Saldo Prévio | O36: Descrição Conta | P36: Valor | Q36: Data vencimento | R36: Pago?
M37: Dia 1 | N37: -260 | O37: Cartão Transporte | P37: -260 | Q37: Dia 1 | R37: ok
M38: Dia 2 | N38: -260 | O38: 0 | P38: 0 | Q38: 0 | R38: ok
M39: Dia 3 | N39: -260 | O39: 0 | P39: 0 | Q39: 0 | R39: ok
M40: Dia 4 | N40: -440 | O40: Manutenção Guitarra Cort X6 | P40: -180 | Q40: Dia 5 | R40: ok
M41: Dia 5 | N41: 700 | O41: Pagamento Recebido Bellocopo | P41: 1140 | Q41: Dia 5 | R41: ok
M42: Dia 6 | N42: 2950 | O42: Pagamento Recebido CD Medical Care | P42: 2250 | Q42: Dia 6 | R42: ok
M43: Dia 7 | N43: 2780 | O43: Ração Gatos Castrados Ultralife | P43: -170 | Q43: Dia 6 | R43: ok
M44: Dia 8 | N44: 2741 | O44: Microsoft | P44: -39 | Q44: Dia 6 | R44: ok
M45: Dia 9 | N45: 2641 | O45: Unhas | P45: -100 | Q45: Dia 6 | R45: ok
M46: Dia 10 | N46: 2241 | O46: Psicóloga | P46: -400 | Q46: Dia 7 | R46: ok
M47: Dia 11 | N47: 2121 | O47: Energia Elétrica (1/4 pagamento) | P47: -120 | Q47: Dia 8 | R47: ok
M48: Dia 12 | N48: 2011 | O48: Dízimo (1/2 parte) | P48: -110 | Q48: Dia 9 | R48: 0
M49: Dia 13 | N49: 1241 | O49: Fatura Cartão Nubank | P49: -770 | Q49: Dia 12 | R49: ok
M50: Dia 14 | N50: 881 | O50: Geladeira (1/11 Parcelas) | P50: -360 | Q50: Dia 13 | R50: ok
M51: Dia 15 | N51: 801 | O51: Curso Administração | P51: -80 | Q51: Dia 13 | R51: ok
M52: Dia 16 | N52: 771.9 | O52: Granulado MimiCat (1/2 unidades) | P52: -29.1 | Q52: Dia 5 | R52: ok
M53: Dia 17 | N53: 731.9 | O53: Netflix - Automatico | P53: -40 | Q53: Dia 17 | R53: ok
M54: Dia 18 | N54: 581.9 | O54: Madeirite plastificado 2200x1100 (1/2) | P54: -150 | Q54: Dia 18 | R54: ok
M55: Dia 19 | N55: 531.9 | O55: Cartão de todos - Automatico | P55: -50 | Q55: Dia 19 | R55: ok
M56: Dia 20 | N56: 1531.9 | O56: Pagamento Recebido Bellocopo | P56: 1000 | Q56: Dia 20 | R56: ok
M57: Dia 21 | N57: 1516.9 | O57: Nível 6 Mercado Livre - Automatico | P57: -15 | Q57: Dia 20 | R57: ok
M58: Dia 22 | N58: 1412 | O58: Internet Atranet | P58: -104.9 | Q58: Dia 20 | R58: ok
M59: Dia 23 | N59: 547 | O59: Fatura Cartão Mercado Livre | P59: -865 | Q59: Dia 22 | R59: ok
M60: Dia 24 | N60: 437 | O60: Dízimo (2/2 parte) | P60: -110 | Q60: Dia 24 | R60: 0
M61: Dia 25 | N61: 437 | O61: 0 | P61: 0 | Q61: 0 | R61: 0
M62: Dia 26 | N62: 437 | O62: 0 | P62: 0 | Q62: 0 | R62: 0
M63: Dia 27 | N63: 392 | O63: Internet Celular Vivo | P63: -45 | Q63: Dia 27 | R63: 0
M64: Dia 28 | N64: 312 | O64: Cílios | P64: -80 | Q64: Dia 28 | R64: ok
M65: Dia 29 | N65: 294.55 | O65: HBO | P65: -17.45 | Q65: Dia 29 | R65: 0
M66: Dia 30 | N66: 294.55 | O66: 0 | P66: 0 | Q66: 0 | R66: 0
M67: Dia 31 | N67: 294.55 | O67: 0 | P67: 0 | Q67: 0 | R67: 0

Sheet Junho
A1: Planejamento Mensal Káic e Gabi | I1: Mês: | J1: Junho | M1: Resumo Finalização do Mês | S1: 0
A2: Data hoje formula | B2: Data formula | C2: Formula pgto ok | G2: Saldo Prévio | H2: Descrição Conta | I2: Valor | J2: Data vencimento | K2: Pago? | M2: =F33 -> Dia 31 | N2: =G33 -> 423.55 | O2: Valor sobra dia 31 - Final do mês
A3: =TODAY() -> 45567 | B3: 45078 | C3: =A3-B3 -> 489 | D3: =C3+K3 -> #VALUE! | E3: =IF(10,K3="ok",0) -> TRUE | F3: Dia 1 | G3: =Setembro!G33+I3 -> -260 | H3: Cartão Transporte | I3: -260 | J3: Dia 1 | K3: ok | L3: =IF(A3=B3,"➜ Hoje","")
A4: =TODAY() -> 45567 | B4: 45079 | C4: =A4-B4 -> 488 | D4: =C4+K4 -> #VALUE! | E4: =IF(10,K4="ok",0) -> TRUE | F4: Dia 2 | G4: =G3+I4 -> -260 | K4: ok | L4: =IF(A4=B4,"➜ Hoje","") | M4: 0.2 | N4: =N2*M4 -> 84.71 | O4: Comemoraçao dia 20
A5: =TODAY() -> 45567 | B5: 45080 | C5: =A5-B5 -> 487 | D5: =C5+K5 -> #VALUE! | E5: =IF(10,K5="ok",0) -> TRUE | F5: Dia 3 | G5: =G4+I5 -> -260 | K5: ok | L5: =IF(A5=B5,"➜ Hoje","") | M5: 0.1 | N5: =N2*M5 -> 42.355 | O5: Reforma/Construção Gatódromo
A6: =TODAY() -> 45567 | B6: 45081 | C6: =A6-B6 -> 486 | D6: =C6+K6 -> #VALUE! | E6: =IF(10,K6="ok",0) -> TRUE | F6: Dia 4 | G6: =G5+I6 -> -289.1 | H6: Granulado MimiCat (3 unidades) | I6: -29.1 | J6: Dia 5 | K6: ok | L6: =IF(A6=B6,"➜ Hoje","") | M6: 0.4 | N6: =N2*M6 -> 169.42 | O6: Reforma Cozinha
A7: =TODAY() -> 45567 | B7: 45082 | C7: =A7-B7 -> 485 | D7: =C7+K7 -> #VALUE! | E7: =IF(10,K7="ok",0) -> TRUE | F7: Dia 5 | G7: =G6+I7 -> 850.9 | H7: Pagamento Recebido Bellocopo | I7: 1140 | J7: Dia 5 | K7: ok | L7: =IF(A7=B7,"➜ Hoje","") | M7: 0.3 | N7: =N2*M7 -> 127.065 | O7: Tirar Carta pra comprar Moto
A8: =TODAY() -> 45567 | B8: 45083 | C8: =A8-B8 -> 484 | D8: =C8+K8 -> #VALUE! | E8: =IF(10,K8="ok",0) -> TRUE | F8: Dia 6 | G8: =G7+I8 -> 2750.9 | H8: Pagamento Recebido CD Medical Care | I8: 1900 | J8: Dia 6 | K8: ok | L8: =IF(A8=B8,"➜ Hoje","")
A9: =TODAY() -> 45567 | B9: 45084 | C9: =A9-B9 -> 483 | D9: =C9+K9 -> #VALUE! | E9: =IF(10,K9="ok",0) -> TRUE | F9: Dia 7 | G9: =G8+I9 -> 2580.9 | H9: Ração Gatos Castrados Ultralife | I9: -170 | J9: Dia 6 | K9: ok | L9: =IF(A9=B9,"➜ Hoje","") | M9: Planejamento Aquisições / Projetos
A10: =TODAY() -> 45567 | B10: 45085 | C10: =A10-B10 -> 482 | D10: =C10+K10 -> #VALUE! | E10: =IF(10,K10="ok",0) -> TRUE | F10: Dia 8 | G10: =G9+I10 -> 2541.9 | H10: Microsoft | I10: -39 | J10: Dia 6 | K10: ok | L10: =IF(A10=B10,"➜ Hoje","")
A11: =TODAY() -> 45567 | B11: 45086 | C11: =A11-B11 -> 481 | D11: =C11+K11 -> #VALUE! | E11: =IF(10,K11="ok",0) -> TRUE | F11: Dia 9 | G11: =G10+I11 -> 2441.9 | H11: Unhas | I11: -100 | J11: Dia 6 | K11: ok | L11: =IF(A11=B11,"➜ Hoje","") | M11: Data | N11: Valor média | O11: Descrição
A12: =TODAY() -> 45567 | B12: 45087 | C12: =A12-B12 -> 480 | D12: =C12+K12 -> #VALUE! | E12: =IF(10,K12="ok",0) -> TRUE | F12: Dia 10 | G12: =G11+I12 -> 2041.9 | H12: Psicóloga | I12: -400 | J12: Dia 7 | K12: ok | L12: =IF(A12=B12,"➜ Hoje","") | M12: 45046 | N12: 400 | O12: Depurador de ar (Reforma Cozinha)
A13: =TODAY() -> 45567 | B13: 45088 | C13: =A13-B13 -> 479 | D13: =C13+K13 -> #VALUE! | E13: =IF(10,K13="ok",0) -> TRUE | F13: Dia 11 | G13: =G12+I13 -> 1921.9 | H13: Energia Elétrica (1/4 pagamento) | I13: -120 | J13: Dia 8 | K13: ok | L13: =IF(A13=B13,"➜ Hoje","") | M13: 44540 | N13: 300 | O13: Revestimento Lume 45x90 Botanico Branco Retif.Azulejo (Reforma Cozinha)
A14: =TODAY() -> 45567 | B14: 45089 | C14: =A14-B14 -> 478 | D14: =C14+K14 -> #VALUE! | E14: =IF(10,K14="ok",0) -> TRUE | F14: Dia 12 | G14: =G13+I14 -> 1811.9 | H14: Dízimo (1/2 parte) | I14: -110 | J14: Dia 9 | K14: ok | L14: =IF(A14=B14,"➜ Hoje","") | M14: 45041 | N14: 400 | O14: Mesa de Cabeceira Armario modulado Amendola Grafito (Reforma Cozinha)
A15: =TODAY() -> 45567 | B15: 45090 | C15: =A15-B15 -> 477 | D15: =C15+K15 -> #VALUE! | E15: =IF(10,K15="ok",0) -> TRUE | F15: Dia 13 | G15: =G14+I15 -> 1341.9 | H15: Fatura Cartão Nubank | I15: -470 | J15: Dia 12 | K15: ok | L15: =IF(A15=B15,"➜ Hoje","") | M15: 45046 | N15: 350 | O15: Balcao Madesa Glamy 35cm 1porta (Reforma Cozinha)
A16: =TODAY() -> 45567 | B16: 45091 | C16: =A16-B16 -> 476 | D16: =C16+K16 -> #VALUE! | E16: =IF(10,K16="ok",0) -> TRUE | F16: Dia 14 | G16: =G15+I16 -> 981.9 | H16: Geladeira (2/11 Parcelas) | I16: -360 | J16: Dia 13 | K16: ok | L16: =IF(A16=B16,"➜ Hoje","")
A17: =TODAY() -> 45567 | B17: 45092 | C17: =A17-B17 -> 475 | D17: =C17+K17 -> #VALUE! | E17: =IF(10,K17="ok",0) -> TRUE | F17: Dia 15 | G17: =G16+I17 -> 901.9 | H17: Curso Administração | I17: -80 | J17: Dia 13 | K17: ok | L17: =IF(A17=B17,"➜ Hoje","")
A18: =TODAY() -> 45567 | B18: 45093 | C18: =A18-B18 -> 474 | D18: =C18+K18 -> #VALUE! | E18: =IF(10,K18="ok",0) -> TRUE | F18: Dia 16 | G18: =G17+I18 -> 901.9 | K18: ok | L18: =IF(A18=B18,"➜ Hoje","") | M18: Planejamento Reposição Dispensa / Compras Mercado
A19: =TODAY() -> 45567 | B19: 45094 | C19: =A19-B19 -> 473 | D19: =C19+K19 -> #VALUE! | E19: =IF(10,K19="ok",0) -> TRUE | F19: Dia 17 | G19: =G18+I19 -> 861.9 | H19: Netflix - Automatico | I19: -40 | J19: Dia 17 | K19: ok | L19: =IF(A19=B19,"➜ Hoje","")
A20: =TODAY() -> 45567 | B20: 45095 | C20: =A20-B20 -> 472 | D20: =C20+K20 -> #VALUE! | E20: =IF(10,K20="ok",0) -> TRUE | F20: Dia 18 | G20: =G19+I20 -> 711.9 | H20: Madeirite plastificado 2200x1100 (2/2) | I20: -150 | J20: Dia 18 | K20: ok | L20: =IF(A20=B20,"➜ Hoje","") | M20: Dia 10 | N20: 500 | O20: Pagamento recebido VA + VR CD Medical Care
A21: =TODAY() -> 45567 | B21: 45096 | C21: =A21-B21 -> 471 | D21: =C21+K21 -> #VALUE! | E21: =IF(10,K21="ok",0) -> TRUE | F21: Dia 19 | G21: =G20+I21 -> 661.9 | H21: Cartão de todos - Automatico | I21: -50 | J21: Dia 19 | K21: ok | L21: =IF(A21=B21,"➜ Hoje","") | M21: Dia 15 | N21: 140 | O21: Pagamento Recebido VA Bellocopo
A22: =TODAY() -> 45567 | B22: 45097 | C22: =A22-B22 -> 470 | D22: =C22+K22 -> #VALUE! | E22: =IF(10,K22="ok",0) -> TRUE | F22: Dia 20 | G22: =G21+I22 -> 1661.9 | H22: Pagamento Recebido Bellocopo | I22: 1000 | J22: Dia 20 | K22: ok | L22: =IF(A22=B22,"➜ Hoje","")
A23: =TODAY() -> 45567 | B23: 45098 | C23: =A23-B23 -> 469 | D23: =C23+K23 -> #VALUE! | E23: =IF(10,K23="ok",0) -> TRUE | F23: Dia 21 | G23: =G22+I23 -> 1646.9 | H23: Nível 6 Mercado Livre - Automatico | I23: -15 | J23: Dia 20 | K23: ok | L23: =IF(A23=B23,"➜ Hoje","")
A24: =TODAY() -> 45567 | B24: 45099 | C24: =A24-B24 -> 468 | D24: =C24+K24 -> #VALUE! | E24: =IF(10,K24="ok",0) -> TRUE | F24: Dia 22 | G24: =G23+I24 -> 1542 | H24: Internet Atranet | I24: -104.9 | J24: Dia 20 | K24: ok | L24: =IF(A24=B24,"➜ Hoje","")
A25: =TODAY() -> 45567 | B25: 45100 | C25: =A25-B25 -> 467 | D25: =C25+K25 -> #VALUE! | E25: =IF(10,K25="ok",0) -> TRUE | F25: Dia 23 | G25: =G24+I25 -> 676 | H25: Fatura Cartão Mercado Livre | I25: -866 | J25: Dia 22 | K25: ok | L25: =IF(A25=B25,"➜ Hoje","")
A26: =TODAY() -> 45567 | B26: 45101 | C26: =A26-B26 -> 466 | D26: =C26+K26 -> #VALUE! | E26: =IF(10,K26="ok",0) -> TRUE | F26: Dia 24 | G26: =G25+I26 -> 566 | H26: Dízimo (2/2 parte) | I26: -110 | J26: Dia 24 | K26: ok | L26: =IF(A26=B26,"➜ Hoje","")
A27: =TODAY() -> 45567 | B27: 45102 | C27: =A27-B27 -> 465 | D27: =C27+K27 -> #VALUE! | E27: =IF(10,K27="ok",0) -> TRUE | F27: Dia 25 | G27: =G26+I27 -> 566 | K27: ok | L27: =IF(A27=B27,"➜ Hoje","")
A28: =TODAY() -> 45567 | B28: 45103 | C28: =A28-B28 -> 464 | D28: =C28+K28 -> #VALUE! | E28: =IF(10,K28="ok",0) -> TRUE | F28: Dia 26 | G28: =G27+I28 -> 566 | K28: ok | L28: =IF(A28=B28,"➜ Hoje","")
A29: =TODAY() -> 45567 | B29: 45104 | C29: =A29-B29 -> 463 | D29: =C29+K29 -> #VALUE! | E29: =IF(10,K29="ok",0) -> TRUE | F29: Dia 27 | G29: =G28+I29 -> 521 | H29: Internet Celular Vivo | I29: -45 | J29: Dia 27 | K29: ok | L29: =IF(A29=B29,"➜ Hoje","")
A30: =TODAY() -> 45567 | B30: 45105 | C30: =A30-B30 -> 462 | D30: =C30+K30 -> #VALUE! | E30: =IF(10,K30="ok",0) -> TRUE | F30: Dia 28 | G30: =G29+I30 -> 441 | H30: Cílios | I30: -80 | J30: Dia 28 | K30: ok | L30: =IF(A30=B30,"➜ Hoje","")
A31: =TODAY() -> 45567 | B31: 45106 | C31: =A31-B31 -> 461 | D31: =C31+K31 -> #VALUE! | E31: =IF(10,K31="ok",0) -> TRUE | F31: Dia 29 | G31: =G30+I31 -> 423.55 | H31: HBO | I31: -17.45 | J31: Dia 29 | K31: ok | L31: =IF(A31=B31,"➜ Hoje","")
A32: =TODAY() -> 45567 | B32: 45107 | C32: =A32-B32 -> 460 | D32: =C32+K32 -> #VALUE! | E32: =IF(10,K32="ok",0) -> TRUE | F32: Dia 30 | G32: =G31+I32 -> 423.55 | K32: ok | L32: =IF(A32=B32,"➜ Hoje","")
A33: =TODAY() -> 45567 | B33: 45107 | C33: =A33-B33 -> 460 | D33: =C33+K33 -> #VALUE! | E33: =IF(10,K33="ok",0) -> TRUE | F33: Dia 31 | G33: =G32+I33 -> 423.55 | K33: ok | L33: =IF(A33=B33,"➜ Hoje","")
M34: Pendencias para pagar
M36: {=F2:K33} -> 0 | N36: Saldo Prévio | O36: Descrição Conta | P36: Valor | Q36: Data vencimento | R36: Pago?
M37: Dia 1 | N37: -260 | O37: Cartão Transporte | P37: -260 | Q37: Dia 1 | R37: ok
M38: Dia 2 | N38: -260 | O38: 0 | P38: 0 | Q38: 0 | R38: ok
M39: Dia 3 | N39: -260 | O39: 0 | P39: 0 | Q39: 0 | R39: ok
M40: Dia 4 | N40: -289.1 | O40: Granulado MimiCat (3 unidades) | P40: -29.1 | Q40: Dia 5 | R40: ok
M41: Dia 5 | N41: 850.9 | O41: Pagamento Recebido Bellocopo | P41: 1140 | Q41: Dia 5 | R41: ok
M42: Dia 6 | N42: 2750.9 | O42: Pagamento Recebido CD Medical Care | P42: 1900 | Q42: Dia 6 | R42: ok
M43: Dia 7 | N43: 2580.9 | O43: Ração Gatos Castrados Ultralife | P43: -170 | Q43: Dia 6 | R43: ok
M44: Dia 8 | N44: 2541.9 | O44: Microsoft | P44: -39 | Q44: Dia 6 | R44: ok
M45: Dia 9 | N45: 2441.9 | O45: Unhas | P45: -100 | Q45: Dia 6 | R45: ok
M46: Dia 10 | N46: 2041.9 | O46: Psicóloga | P46: -400 | Q46: Dia 7 | R46: ok
M47: Dia 11 | N47: 1921.9 | O47: Energia Elétrica (1/4 pagamento) | P47: -120 | Q47: Dia 8 | R47: ok
M48: Dia 12 | N48: 1811.9 | O48: Dízimo (1/2 parte) | P48: -110 | Q48: Dia 9 | R48: ok
M49: Dia 13 | N49: 1341.9 | O49: Fatura Cartão Nubank | P49: -470 | Q49: Dia 12 | R49: ok
M50: Dia 14 | N50: 981.9 | O50: Geladeira (2/11 Parcelas) | P50: -360 | Q50: Dia 13 | R50: ok
M51: Dia 15 | N51: 901.9 | O51: Curso Administração | P51: -80 | Q51: Dia 13 | R51: ok
M52: Dia 16 | N52: 901.9 | O52: 0 | P52: 0 | Q52: 0 | R52: ok
M53: Dia 17 | N53: 861.9 | O53: Netflix - Automatico | P53: -40 | Q53: Dia 17 | R53: ok
M54: Dia 18 | N54: 711.9 | O54: Madeirite plastificado 2200x1100 (2/2) | P54: -150 | Q54: Dia 18 | R54: ok
M55: Dia 19 | N55: 661.9 | O55: Cartão de todos - Automatico | P55: -50 | Q55: Dia 19 | R55: ok
M56: Dia 20 | N56: 1661.9 | O56: Pagamento Recebido Bellocopo | P56: 1000 | Q56: Dia 20 | R56: ok
M57: Dia 21 | N57: 1646.9 | O57: Nível 6 Mercado Livre - Automatico | P57: -15 | Q57: Dia 20 | R57: ok
M58: Dia 22 | N58: 1542 | O58: Internet Atranet | P58: -104.9 | Q58: Dia 20 | R58: ok
M59: Dia 23 | N59: 676 | O59: Fatura Cartão Mercado Livre | P59: -866 | Q59: Dia 22 | R59: ok
M60: Dia 24 | N60: 566 | O60: Dízimo (2/2 parte) | P60: -110 | Q60: Dia 24 | R60: ok
M61: Dia 25 | N61: 566 | O61: 0 | P61: 0 | Q61: 0 | R61: ok
M62: Dia 26 | N62: 566 | O62: 0 | P62: 0 | Q62: 0 | R62: ok
M63: Dia 27 | N63: 521 | O63: Internet Celular Vivo | P63: -45 | Q63: Dia 27 | R63: ok
M64: Dia 28 | N64: 441 | O64: Cílios | P64: -80 | Q64: Dia 28 | R64: ok
M65: Dia 29 | N65: 423.55 | O65: HBO | P65: -17.45 | Q65: Dia 29 | R65: ok
M66: Dia 30 | N66: 423.55 | O66: 0 | P66: 0 | Q66: 0 | R66: ok
M67: Dia 31 | N67: 423.55 | O67: 0 | P67: 0 | Q67: 0 | R67: ok

Sheet Julho
A1: Planejamento Mensal Káic e Gabi | I1: Mês: | J1: Julho | M1: Resumo Finalização do Mês | S1: 0
A2: Data hoje formula | B2: Data formula | C2: Formula pgto ok | G2: Saldo Prévio | H2: Descrição Conta | I2: Valor | J2: Data vencimento | K2: Pago? | M2: =F33 -> Dia 31 | N2: =G33 -> -63.35 | O2: Valor sobra dia 31 - Final do mês
A3: =TODAY() -> 45567 | B3: 45108 | C3: =A3-B3 -> 459 | D3: =C3+K3 -> #VALUE! | E3: =IF(10,K3="ok",0) -> TRUE | F3: Dia 1 | G3: 0 | H3: Cartão Transporte | I3: 0 | J3: Dia 1 | K3: ok | L3: =IF(A3=B3,"➜ Hoje","")
A4: =TODAY() -> 45567 | B4: 45109 | C4: =A4-B4 -> 458 | D4: =C4+K4 -> #VALUE! | E4: =IF(10,K4="ok",0) -> TRUE | F4: Dia 2 | G4: =G3+I4 -> 0 | K4: ok | L4: =IF(A4=B4,"➜ Hoje","") | M4: 0.2 | N4: =N2*M4 -> -12.67 | O4: Comemoraçao dia 20
A5: =TODAY() -> 45567 | B5: 45110 | C5: =A5-B5 -> 457 | D5: =C5+K5 -> #VALUE! | E5: =IF(10,K5="ok",0) -> TRUE | F5: Dia 3 | G5: =G4+I5 -> 0 | K5: ok | L5: =IF(A5=B5,"➜ Hoje","") | M5: 0.1 | N5: =N2*M5 -> -6.335 | O5: Reforma/Construção Gatódromo
A6: =TODAY() -> 45567 | B6: 45111 | C6: =A6-B6 -> 456 | D6: =C6+K6 -> #VALUE! | E6: =IF(10,K6="ok",0) -> TRUE | F6: Dia 4 | G6: =G5+I6 -> 0 | I6: 0 | J6: Dia 5 | K6: ok | L6: =IF(A6=B6,"➜ Hoje","") | M6: 0.4 | N6: =N2*M6 -> -25.34 | O6: Reforma Cozinha
A7: =TODAY() -> 45567 | B7: 45112 | C7: =A7-B7 -> 455 | D7: =C7+K7 -> #VALUE! | E7: =IF(10,K7="ok",0) -> TRUE | F7: Dia 5 | G7: =G6+I7 -> 1140 | H7: Pagamento Recebido Bellocopo | I7: 1140 | J7: Dia 5 | K7: ok | L7: =IF(A7=B7,"➜ Hoje","") | M7: 0.3 | N7: =N2*M7 -> -19.005 | O7: Tirar Carta pra comprar Moto
A8: =TODAY() -> 45567 | B8: 45113 | C8: =A8-B8 -> 454 | D8: =C8+K8 -> #VALUE! | E8: =IF(10,K8="ok",0) -> TRUE | F8: Dia 6 | G8: =G7+I8 -> 1140 | I8: 0 | J8: Dia 6 | K8: ok | L8: =IF(A8=B8,"➜ Hoje","")
A9: =TODAY() -> 45567 | B9: 45114 | C9: =A9-B9 -> 453 | D9: =C9+K9 -> #VALUE! | E9: =IF(10,K9="ok",0) -> TRUE | F9: Dia 7 | G9: =G8+I9 -> 970 | H9: Ração Gatos Castrados Ultralife | I9: -170 | J9: Dia 6 | K9: ok | L9: =IF(A9=B9,"➜ Hoje","") | M9: Planejamento Aquisições / Projetos
A10: =TODAY() -> 45567 | B10: 45115 | C10: =A10-B10 -> 452 | D10: =C10+K10 -> #VALUE! | E10: =IF(10,K10="ok",0) -> TRUE | F10: Dia 8 | G10: =G9+I10 -> 931 | H10: Microsoft | I10: -39 | J10: Dia 6 | K10: ok | L10: =IF(A10=B10,"➜ Hoje","")
A11: =TODAY() -> 45567 | B11: 45116 | C11: =A11-B11 -> 451 | D11: =C11+K11 -> #VALUE! | E11: =IF(10,K11="ok",0) -> TRUE | F11: Dia 9 | G11: =G10+I11 -> 831 | H11: Unhas | I11: -100 | J11: Dia 6 | K11: ok | L11: =IF(A11=B11,"➜ Hoje","") | M11: Data | N11: Valor média | O11: Descrição
A12: =TODAY() -> 45567 | B12: 45117 | C12: =A12-B12 -> 450 | D12: =C12+K12 -> #VALUE! | E12: =IF(10,K12="ok",0) -> TRUE | F12: Dia 10 | G12: =G11+I12 -> 691 | H12: Psicóloga (Quinzenal) | I12: -140 | J12: Dia 7 | K12: ok | L12: =IF(A12=B12,"➜ Hoje","") | M12: 45046 | N12: 400 | O12: Depurador de ar (Reforma Cozinha)
A13: =TODAY() -> 45567 | B13: 45118 | C13: =A13-B13 -> 449 | D13: =C13+K13 -> #VALUE! | E13: =IF(10,K13="ok",0) -> TRUE | F13: Dia 11 | G13: =G12+I13 -> 571 | H13: Energia Elétrica (1/4 pagamento) | I13: -120 | J13: Dia 8 | K13: ok | L13: =IF(A13=B13,"➜ Hoje","") | M13: 44540 | N13: 300 | O13: Revestimento Lume 45x90 Botanico Branco Retif.Azulejo (Reforma Cozinha)
A14: =TODAY() -> 45567 | B14: 45119 | C14: =A14-B14 -> 448 | D14: =C14+K14 -> #VALUE! | E14: =IF(10,K14="ok",0) -> TRUE | F14: Dia 12 | G14: =G13+I14 -> 461 | H14: Dízimo (1/2 parte) | I14: -110 | J14: Dia 9 | K14: ok | L14: =IF(A14=B14,"➜ Hoje","") | M14: 45041 | N14: 400 | O14: Mesa de Cabeceira Armario modulado Amendola Grafito (Reforma Cozinha)
A15: =TODAY() -> 45567 | B15: 45120 | C15: =A15-B15 -> 447 | D15: =C15+K15 -> #VALUE! | E15: =IF(10,K15="ok",0) -> TRUE | F15: Dia 13 | G15: =G14+I15 -> 461 | H15: Fatura Cartão Nubank | I15: 0 | J15: Dia 12 | K15: ok | L15: =IF(A15=B15,"➜ Hoje","") | M15: 45046 | N15: 350 | O15: Balcao Madesa Glamy 35cm 1porta (Reforma Cozinha)
A16: =TODAY() -> 45567 | B16: 45121 | C16: =A16-B16 -> 446 | D16: =C16+K16 -> #VALUE! | E16: =IF(10,K16="ok",0) -> TRUE | F16: Dia 14 | G16: =G15+I16 -> 101 | H16: Geladeira (3/11 Parcelas) | I16: -360 | J16: Dia 13 | K16: ok | L16: =IF(A16=B16,"➜ Hoje","")
A17: =TODAY() -> 45567 | B17: 45122 | C17: =A17-B17 -> 445 | D17: =C17+K17 -> #VALUE! | E17: =IF(10,K17="ok",0) -> TRUE | F17: Dia 15 | G17: =G16+I17 -> 21 | H17: Curso Administração | I17: -80 | J17: Dia 13 | K17: ok | L17: =IF(A17=B17,"➜ Hoje","")
A18: =TODAY() -> 45567 | B18: 45123 | C18: =A18-B18 -> 444 | D18: =C18+K18 -> #VALUE! | E18: =IF(10,K18="ok",0) -> TRUE | F18: Dia 16 | G18: =G17+I18 -> 21 | K18: ok | L18: =IF(A18=B18,"➜ Hoje","") | M18: Planejamento Reposição Dispensa / Compras Mercado
A19: =TODAY() -> 45567 | B19: 45124 | C19: =A19-B19 -> 443 | D19: =C19+K19 -> #VALUE! | E19: =IF(10,K19="ok",0) -> TRUE | F19: Dia 17 | G19: =G18+I19 -> -19 | H19: Netflix - Automatico | I19: -40 | J19: Dia 17 | K19: ok | L19: =IF(A19=B19,"➜ Hoje","")
A20: =TODAY() -> 45567 | B20: 45125 | C20: =A20-B20 -> 442 | D20: =C20+K20 -> #VALUE! | E20: =IF(10,K20="ok",0) -> TRUE | F20: Dia 18 | G20: =G19+I20 -> -19 | I20: 0 | J20: Dia 18 | K20: ok | L20: =IF(A20=B20,"➜ Hoje","")
A21: =TODAY() -> 45567 | B21: 45126 | C21: =A21-B21 -> 441 | D21: =C21+K21 -> #VALUE! | E21: =IF(10,K21="ok",0) -> TRUE | F21: Dia 19 | G21: =G20+I21 -> -69 | H21: Cartão de todos - Automatico | I21: -50 | J21: Dia 19 | K21: ok | L21: =IF(A21=B21,"➜ Hoje","") | M21: Dia 15 | N21: 140 | O21: Pagamento Recebido VA Bellocopo
A22: =TODAY() -> 45567 | B22: 45127 | C22: =A22-B22 -> 440 | D22: =C22+K22 -> #VALUE! | E22: =IF(10,K22="ok",0) -> TRUE | F22: Dia 20 | G22: =G21+I22 -> 931 | H22: Pagamento Recebido Bellocopo | I22: 1000 | J22: Dia 20 | K22: ok | L22: =IF(A22=B22,"➜ Hoje","")
A23: =TODAY() -> 45567 | B23: 45128 | C23: =A23-B23 -> 439 | D23: =C23+K23 -> #VALUE! | E23: =IF(10,K23="ok",0) -> TRUE | F23: Dia 21 | G23: =G22+I23 -> 916 | H23: Nível 6 Mercado Livre - Automatico | I23: -15 | J23: Dia 20 | K23: ok | L23: =IF(A23=B23,"➜ Hoje","")
A24: =TODAY() -> 45567 | B24: 45129 | C24: =A24-B24 -> 438 | D24: =C24+K24 -> #VALUE! | E24: =IF(10,K24="ok",0) -> TRUE | F24: Dia 22 | G24: =G23+I24 -> 811.1 | H24: Internet Atranet | I24: -104.9 | J24: Dia 20 | K24: ok | L24: =IF(A24=B24,"➜ Hoje","")
A25: =TODAY() -> 45567 | B25: 45130 | C25: =A25-B25 -> 437 | D25: =C25+K25 -> #VALUE! | E25: =IF(10,K25="ok",0) -> TRUE | F25: Dia 23 | G25: =G24+I25 -> 189.1 | H25: Fatura Cartão Mercado Livre | I25: -622 | J25: Dia 22 | K25: ok | L25: =IF(A25=B25,"➜ Hoje","")
A26: =TODAY() -> 45567 | B26: 45131 | C26: =A26-B26 -> 436 | D26: =C26+K26 -> #VALUE! | E26: =IF(10,K26="ok",0) -> TRUE | F26: Dia 24 | G26: =G25+I26 -> 79.1 | H26: Dízimo (2/2 parte) | I26: -110 | J26: Dia 24 | K26: ok | L26: =IF(A26=B26,"➜ Hoje","")
A27: =TODAY() -> 45567 | B27: 45132 | C27: =A27-B27 -> 435 | D27: =C27+K27 -> #VALUE! | E27: =IF(10,K27="ok",0) -> TRUE | F27: Dia 25 | G27: =G26+I27 -> 79.1 | K27: ok | L27: =IF(A27=B27,"➜ Hoje","")
A28: =TODAY() -> 45567 | B28: 45133 | C28: =A28-B28 -> 434 | D28: =C28+K28 -> #VALUE! | E28: =IF(10,K28="ok",0) -> TRUE | F28: Dia 26 | G28: =G27+I28 -> 79.1 | K28: ok | L28: =IF(A28=B28,"➜ Hoje","")
A29: =TODAY() -> 45567 | B29: 45134 | C29: =A29-B29 -> 433 | D29: =C29+K29 -> #VALUE! | E29: =IF(10,K29="ok",0) -> TRUE | F29: Dia 27 | G29: =G28+I29 -> 34.1 | H29: Internet Celular Vivo | I29: -45 | J29: Dia 27 | K29: ok | L29: =IF(A29=B29,"➜ Hoje","")
A30: =TODAY() -> 45567 | B30: 45135 | C30: =A30-B30 -> 432 | D30: =C30+K30 -> #VALUE! | E30: =IF(10,K30="ok",0) -> TRUE | F30: Dia 28 | G30: =G29+I30 -> -45.9 | H30: Cílios | I30: -80 | J30: Dia 28 | K30: ok | L30: =IF(A30=B30,"➜ Hoje","")
A31: =TODAY() -> 45567 | B31: 45136 | C31: =A31-B31 -> 431 | D31: =C31+K31 -> #VALUE! | E31: =IF(10,K31="ok",0) -> TRUE | F31: Dia 29 | G31: =G30+I31 -> -63.35 | H31: HBO | I31: -17.45 | J31: Dia 29 | K31: ok | L31: =IF(A31=B31,"➜ Hoje","")
A32: =TODAY() -> 45567 | B32: 45137 | C32: =A32-B32 -> 430 | D32: =C32+K32 -> #VALUE! | E32: =IF(10,K32="ok",0) -> TRUE | F32: Dia 30 | G32: =G31+I32 -> -63.35 | K32: ok | L32: =IF(A32=B32,"➜ Hoje","")
A33: =TODAY() -> 45567 | B33: 45138 | C33: =A33-B33 -> 429 | D33: =C33+K33 -> #VALUE! | E33: =IF(10,K33="ok",0) -> TRUE | F33: Dia 31 | G33: =G32+I33 -> -63.35 | K33: ok | L33: =IF(A33=B33,"➜ Hoje","")
M34: Pendencias para pagar
M36: {=F2:K33} -> 0 | N36: Saldo Prévio | O36: Descrição Conta | P36: Valor | Q36: Data vencimento | R36: Pago?
M37: Dia 1 | N37: 0 | O37: Cartão Transporte | P37: 0 | Q37: Dia 1 | R37: ok
M38: Dia 2 | N38: 0 | O38: 0 | P38: 0 | Q38: 0 | R38: ok
M39: Dia 3 | N39: 0 | O39: 0 | P39: 0 | Q39: 0 | R39: ok
M40: Dia 4 | N40: 0 | O40: 0 | P40: 0 | Q40: Dia 5 | R40: ok
M41: Dia 5 | N41: 1140 | O41: Pagamento Recebido Bellocopo | P41: 1140 | Q41: Dia 5 | R41: ok
M42: Dia 6 | N42: 1140 | O42: 0 | P42: 0 | Q42: Dia 6 | R42: ok
M43: Dia 7 | N43: 970 | O43: Ração Gatos Castrados Ultralife | P43: -170 | Q43: Dia 6 | R43: ok
M44: Dia 8 | N44: 931 | O44: Microsoft | P44: -39 | Q44: Dia 6 | R44: ok
M45: Dia 9 | N45: 831 | O45: Unhas | P45: -100 | Q45: Dia 6 | R45: ok
M46: Dia 10 | N46: 691 | O46: Psicóloga (Quinzenal) | P46: -140 | Q46: Dia 7 | R46: ok
M47: Dia 11 | N47: 571 | O47: Energia Elétrica (1/4 pagamento) | P47: -120 | Q47: Dia 8 | R47: ok
M48: Dia 12 | N48: 461 | O48: Dízimo (1/2 parte) | P48: -110 | Q48: Dia 9 | R48: ok
M49: Dia 13 | N49: 461 | O49: Fatura Cartão Nubank | P49: 0 | Q49: Dia 12 | R49: ok
M50: Dia 14 | N50: 101 | O50: Geladeira (3/11 Parcelas) | P50: -360 | Q50: Dia 13 | R50: ok
M51: Dia 15 | N51: 21 | O51: Curso Administração | P51: -80 | Q51: Dia 13 | R51: ok
M52: Dia 16 | N52: 21 | O52: 0 | P52: 0 | Q52: 0 | R52: ok
M53: Dia 17 | N53: -19 | O53: Netflix - Automatico | P53: -40 | Q53: Dia 17 | R53: ok
M54: Dia 18 | N54: -19 | O54: 0 | P54: 0 | Q54: Dia 18 | R54: ok
M55: Dia 19 | N55: -69 | O55: Cartão de todos - Automatico | P55: -50 | Q55: Dia 19 | R55: ok
M56: Dia 20 | N56: 931 | O56: Pagamento Recebido Bellocopo | P56: 1000 | Q56: Dia 20 | R56: ok
M57: Dia 21 | N57: 916 | O57: Nível 6 Mercado Livre - Automatico | P57: -15 | Q57: Dia 20 | R57: ok
M58: Dia 22 | N58: 811.1 | O58: Internet Atranet | P58: -104.9 | Q58: Dia 20 | R58: ok
M59: Dia 23 | N59: 189.1 | O59: Fatura Cartão Mercado Livre | P59: -622 | Q59: Dia 22 | R59: ok
M60: Dia 24 | N60: 79.1 | O60: Dízimo (2/2 parte) | P60: -110 | Q60: Dia 24 | R60: ok
M61: Dia 25 | N61: 79.1 | O61: 0 | P61: 0 | Q61: 0 | R61: ok
M62: Dia 26 | N62: 79.1 | O62: 0 | P62: 0 | Q62: 0 | R62: ok
M63: Dia 27 | N63: 34.1 | O63: Internet Celular Vivo | P63: -45 | Q63: Dia 27 | R63: ok
M64: Dia 28 | N64: -45.9 | O64: Cílios | P64: -80 | Q64: Dia 28 | R64: ok
M65: Dia 29 | N65: -63.35 | O65: HBO | P65: -17.45 | Q65: Dia 29 | R65: ok
M66: Dia 30 | N66: -63.35 | O66: 0 | P66: 0 | Q66: 0 | R66: ok
M67: Dia 31 | N67: -63.35 | O67: 0 | P67: 0 | Q67: 0 | R67: ok

Sheet Outubro 2024
A1: Planejamento Mensal Káic e Gabi | I1: Mês: | J1: Outubro | M1: Resumo Finalização do Mês | S1: 0
A2: Data hoje formula | B2: Data formula | C2: Formula pgto ok | G2: Saldo Prévio | H2: Descrição Conta | I2: Valor | J2: Data vencimento | K2: Pago? | M2: =F33 -> Dia 31 | N2: =G33 -> -701.32 | O2: Valor sobra dia 31 - Final do mês
A3: =TODAY() -> 45567 | B3: 45566 | C3: =A3-B3 -> 1 | D3: =C3+K3 -> #VALUE! | E3: =IF(10,K3="ok",0) -> TRUE | F3: Dia 1 | G3: =Setembro!G33+I3-13 -> -40.99 | H3: Nível 6 Mercado Livre - Automatico | I3: -27.99 | J3: Dia 1 | K3: OK | L3: =IF(A3=B3,"➜ Hoje","")
A4: =TODAY() -> 45567 | B4: =B3+1 -> 45567 | C4: =A4-B4 -> 0 | D4: =C4+K4 -> #VALUE! | E4: =IF(10,K4="ok",0) -> TRUE | F4: Dia 2 | G4: =G3+I4 -> 537.92 | H4: Pagamento PLR | I4: 578.91 | J4: Dia 1 | K4: OK | L4: =IF(A4=B4,"➜ Hoje","") -> ➜ Hoje | M4: 0.2 | N4: =IF($N$2*M4<=0,"Em vermelho",$N$2*M4) -> Em vermelho | O4: Comemoraçao dia 20
A5: =TODAY() -> 45567 | B5: =B4+1 -> 45568 | C5: =A5-B5 -> -1 | D5: =C5+K5 -> -1 | E5: =IF(10,K5="ok",0) -> FALSE | F5: Dia 3 | G5: =G4+I5 -> 537.92 | L5: =IF(A5=B5,"➜ Hoje","") | M5: 0.1 | N5: =IF($N$2*M5<=0,"Em vermelho",$N$2*M5) -> Em vermelho | O5: Reforma Casa
A6: =TODAY() -> 45567 | B6: =B5+1 -> 45569 | C6: =A6-B6 -> -2 | D6: =C6+K6 -> -2 | E6: =IF(10,K6="ok",0) -> FALSE | F6: Dia 4 | G6: =G5+I6 -> 515.92 | H6: Granulado Madeira (10kg) | I6: -22 | J6: Dia 5 | L6: =IF(A6=B6,"➜ Hoje","") | M6: 0.4 | N6: =IF($N$2*M6<=0,"Em vermelho",$N$2*M6) -> Em vermelho | O6: Tirar Carta A+B
A7: =TODAY() -> 45567 | B7: =B6+1 -> 45570 | C7: =A7-B7 -> -3 | D7: =C7+K7 -> -3 | E7: =IF(10,K7="ok",0) -> FALSE | F7: Dia 5 | G7: =G6+I7 -> 1915.92 | H7: Pagamento Recebido Bellocopo | I7: 1400 | J7: Dia 5 | L7: =IF(A7=B7,"➜ Hoje","") | M7: 0.3 | N7: =IF($N$2*M7<=0,"Em vermelho",$N$2*M7) -> Em vermelho | O7: Novas Alianças
A8: =TODAY() -> 45567 | B8: =B7+1 -> 45571 | C8: =A8-B8 -> -4 | D8: =C8+K8 -> -4 | E8: =IF(10,K8="ok",0) -> FALSE | F8: Dia 6 | G8: =G7+I8 -> 748.69 | H8: Fatura Cartão Mercado Livre | I8: =-1206.93+39.7 -> -1167.23 | J8: Dia 5 | L8: =IF(A8=B8,"➜ Hoje","")
A9: =TODAY() -> 45567 | B9: =B8+1 -> 45572 | C9: =A9-B9 -> -5 | D9: =C9+K9 -> -5 | E9: =IF(10,K9="ok",0) -> FALSE | F9: Dia 7 | G9: =G8+I9 -> 148.09 | H9: Parcela Moto | I9: -600.6 | J9: Dia 6 | L9: =IF(A9=B9,"➜ Hoje","") | M9: Planejamento Aquisições / Projetos
A10: =TODAY() -> 45567 | B10: =B9+1 -> 45573 | C10: =A10-B10 -> -6 | D10: =C10+K10 -> -6 | E10: =IF(10,K10="ok",0) -> FALSE | F10: Dia 8 | G10: =G9+I10 -> -9.91 | H10: Ração Gatos Golden Castrados | I10: -158 | J10: Dia 6 | L10: =IF(A10=B10,"➜ Hoje","")
A11: =TODAY() -> 45567 | B11: =B10+1 -> 45574 | C11: =A11-B11 -> -7 | D11: =C11+K11 -> -7 | E11: =IF(10,K11="ok",0) -> FALSE | F11: Dia 9 | G11: =G10+I11 -> -48.91 | H11: Microsoft | I11: -39 | J11: Dia 6 | L11: =IF(A11=B11,"➜ Hoje","") | M11: Data | N11: Valor média | O11: Descrição
A12: =TODAY() -> 45567 | B12: =B11+1 -> 45575 | C12: =A12-B12 -> -8 | D12: =C12+K12 -> -8 | E12: =IF(10,K12="ok",0) -> FALSE | F12: Dia 10 | G12: =G11+I12 -> -79.81 | H12: Netflix - Automatico | I12: -30.9 | J12: Dia 9 | L12: =IF(A12=B12,"➜ Hoje","") | M12: 45046 | N12: 400 | O12: Depurador de ar (Reforma Cozinha)
A13: =TODAY() -> 45567 | B13: =B12+1 -> 45576 | C13: =A13-B13 -> -9 | D13: =C13+K13 -> -9 | E13: =IF(10,K13="ok",0) -> FALSE | F13: Dia 11 | G13: =G12+I13 -> -219.81 | H13: Dízimo (1/2 parte) | I13: -140 | J13: Dia 9 | L13: =IF(A13=B13,"➜ Hoje","") | M13: 44540 | N13: 300 | O13: Revestimento Lume 45x90 Botanico Branco Retif.Azulejo (Reforma Cozinha)
A14: =TODAY() -> 45567 | B14: =B13+1 -> 45577 | C14: =A14-B14 -> -10 | D14: =C14+K14 -> -10 | E14: =IF(10,K14="ok",0) -> FALSE | F14: Dia 12 | G14: =G13+I14 -> -247.59 | H14: Anticoncepcional | I14: -27.78 | J14: Dia 10 | L14: =IF(A14=B14,"➜ Hoje","")
A15: =TODAY() -> 45567 | B15: =B14+1 -> 45578 | C15: =A15-B15 -> -11 | D15: =C15+K15 -> -11 | E15: =IF(10,K15="ok",0) -> FALSE | F15: Dia 13 | G15: =G14+I15 -> -264.08 | H15: SimplyPiano | I15: -16.49 | J15: Dia 12 | L15: =IF(A15=B15,"➜ Hoje","")
A16: =TODAY() -> 45567 | B16: =B15+1 -> 45579 | C16: =A16-B16 -> -12 | D16: =C16+K16 -> -12 | E16: =IF(10,K16="ok",0) -> FALSE | F16: Dia 14 | G16: =G15+I16 -> -264.08 | L16: =IF(A16=B16,"➜ Hoje","")
A17: =TODAY() -> 45567 | B17: =B16+1 -> 45580 | C17: =A17-B17 -> -13 | D17: =C17+K17 -> -13 | E17: =IF(10,K17="ok",0) -> FALSE | F17: Dia 15 | G17: =G16+I17 -> -354.08 | H17: Gasolina Moto | I17: -90 | J17: Dia 15 | L17: =IF(A17=B17,"➜ Hoje","")
A18: =TODAY() -> 45567 | B18: =B17+1 -> 45581 | C18: =A18-B18 -> -14 | D18: =C18+K18 -> -14 | E18: =IF(10,K18="ok",0) -> FALSE | F18: Dia 16 | G18: =G17+I18 -> -393.78 | H18: Curso Aryanne Ativando a Libido | I18: -39.7 | J18: Dia 15 | L18: =IF(A18=B18,"➜ Hoje","") | M18: Planejamento Reposição Dispensa / Compras Mercado
A19: =TODAY() -> 45567 | B19: =B18+1 -> 45582 | C19: =A19-B19 -> -15 | D19: =C19+K19 -> -15 | E19: =IF(10,K19="ok",0) -> FALSE | F19: Dia 17 | G19: =G18+I19 -> -393.78 | L19: =IF(A19=B19,"➜ Hoje","")
A20: =TODAY() -> 45567 | B20: =B19+1 -> 45583 | C20: =A20-B20 -> -16 | D20: =C20+K20 -> -16 | E20: =IF(10,K20="ok",0) -> FALSE | F20: Dia 18 | G20: =G19+I20 -> 806.22 | H20: Pagamento Recebido Bellocopo | I20: 1200 | J20: Dia 20 | L20: =IF(A20=B20,"➜ Hoje","") | M20: Dia 15 | N20: 210 | O20: Pagamento Recebido VA Bellocopo
A21: =TODAY() -> 45567 | B21: =B20+1 -> 45584 | C21: =A21-B21 -> -17 | D21: =C21+K21 -> -17 | E21: =IF(10,K21="ok",0) -> FALSE | F21: Dia 19 | G21: =G20+I21 -> -148.78 | H21: Fatura Cartão Nubank | I21: -955 | J21: Dia 20 | L21: =IF(A21=B21,"➜ Hoje","")
A22: =TODAY() -> 45567 | B22: =B21+1 -> 45585 | C22: =A22-B22 -> -18 | D22: =C22+K22 -> -18 | E22: =IF(10,K22="ok",0) -> FALSE | F22: Dia 20 | G22: =G21+I22 -> -160.48 | H22: Spotify | I22: -11.7 | J22: Dia 20 | L22: =IF(A22=B22,"➜ Hoje","") | M22: Planejamento Acerto de dividas - prorrogando para mês seguinte
A23: =TODAY() -> 45567 | B23: =B22+1 -> 45586 | C23: =A23-B23 -> -19 | D23: =C23+K23 -> -19 | E23: =IF(10,K23="ok",0) -> FALSE | F23: Dia 21 | G23: =G22+I23 -> -160.48 | L23: =IF(A23=B23,"➜ Hoje","")
A24: =TODAY() -> 45567 | B24: =B23+1 -> 45587 | C24: =A24-B24 -> -20 | D24: =C24+K24 -> -20 | E24: =IF(10,K24="ok",0) -> FALSE | F24: Dia 22 | G24: =G23+I24 -> -260.38 | H24: Internet Atranet | I24: -99.9 | J24: Dia 20 | L24: =IF(A24=B24,"➜ Hoje","") | N24: 35 | O24: Granulado Madeira (10kg)
A25: =TODAY() -> 45567 | B25: =B24+1 -> 45588 | C25: =A25-B25 -> -21 | D25: =C25+K25 -> -21 | E25: =IF(10,K25="ok",0) -> FALSE | F25: Dia 23 | G25: =G24+I25 -> -271.37 | H25: PicsArt Photo | I25: -10.99 | J25: Dia 21 | L25: =IF(A25=B25,"➜ Hoje","") | N25: 158 | O25: Ração Gatos Golden Castrados
A26: =TODAY() -> 45567 | B26: =B25+1 -> 45589 | C26: =A26-B26 -> -22 | D26: =C26+K26 -> -22 | E26: =IF(10,K26="ok",0) -> FALSE | F26: Dia 24 | G26: =G25+I26 -> -271.37 | L26: =IF(A26=B26,"➜ Hoje","") | N26: 99.9 | O26: Internet Atranet
A27: =TODAY() -> 45567 | B27: =B26+1 -> 45590 | C27: =A27-B27 -> -23 | D27: =C27+K27 -> -23 | E27: =IF(10,K27="ok",0) -> FALSE | F27: Dia 25 | G27: =G26+I27 -> -391.37 | H27: Dízimo (2/2 parte) | I27: -120 | J27: Dia 24 | L27: =IF(A27=B27,"➜ Hoje","") | N27: 127.5 | O27: Cílios
A28: =TODAY() -> 45567 | B28: =B27+1 -> 45591 | C28: =A28-B28 -> -24 | D28: =C28+K28 -> -24 | E28: =IF(10,K28="ok",0) -> FALSE | F28: Dia 26 | G28: =G27+I28 -> -511.37 | H28: Energia Elétrica (1/4 pagamento) | I28: -120 | J28: Dia 20 | L28: =IF(A28=B28,"➜ Hoje","") | N28: 27.78 | O28: Anticoncepcional
A29: =TODAY() -> 45567 | B29: =B28+1 -> 45592 | C29: =A29-B29 -> -25 | D29: =C29+K29 -> -25 | E29: =IF(10,K29="ok",0) -> FALSE | F29: Dia 27 | G29: =G28+I29 -> -556.37 | H29: Internet Celular Vivo | I29: -45 | J29: Dia 27 | L29: =IF(A29=B29,"➜ Hoje","")
A30: =TODAY() -> 45567 | B30: =B29+1 -> 45593 | C30: =A30-B30 -> -26 | D30: =C30+K30 -> -26 | E30: =IF(10,K30="ok",0) -> FALSE | F30: Dia 28 | G30: =G29+I30 -> -683.87 | H30: Cílios | I30: -127.5 | J30: Dia 28 | L30: =IF(A30=B30,"➜ Hoje","") | M30: Prorrogar: | N30: =SUM(N24:N29) -> 448.18
A31: =TODAY() -> 45567 | B31: =B30+1 -> 45594 | C31: =A31-B31 -> -27 | D31: =C31+K31 -> -27 | E31: =IF(10,K31="ok",0) -> FALSE | F31: Dia 29 | G31: =G30+I31 -> -701.32 | H31: HBO | I31: -17.45 | J31: Dia 29 | L31: =IF(A31=B31,"➜ Hoje","") | M31: =M2 -> Dia 31 | N31: =N2+N30 -> -253.14 | O31: Valor sobra dia 31 - Final do mês
A32: =TODAY() -> 45567 | B32: =B31+1 -> 45595 | C32: =A32-B32 -> -28 | D32: =C32+K32 -> -28 | E32: =IF(10,K32="ok",0) -> FALSE | F32: Dia 30 | G32: =G31+I32 -> -701.32 | L32: =IF(A32=B32,"➜ Hoje","") | N32: =N30*2 -> 896.36
A33: =TODAY() -> 45567 | B33: 45596 | C33: =A33-B33 -> -29 | D33: =C33+K33 -> -29 | E33: =IF(10,K33="ok",0) -> FALSE | F33: Dia 31 | G33: =G32+I33 -> -701.32 | L33: =IF(A33=B33,"➜ Hoje","") | N33: =N30-N32 -> -448.18
M34: Pendencias para pagar
M36: {=F2:K33} -> 0 | N36: Saldo Prévio | O36: Descrição Conta | P36: Valor | Q36: Data vencimento | R36: Pago?
M37: Dia 1 | N37: -40.99 | O37: Nível 6 Mercado Livre - Automatico | P37: -27.99 | Q37: Dia 1 | R37: OK
M38: Dia 2 | N38: 537.92 | O38: Pagamento PLR | P38: 578.91 | Q38: Dia 1 | R38: OK
M39: Dia 3 | N39: 537.92 | O39: 0 | P39: 0 | Q39: 0 | R39: 0
M40: Dia 4 | N40: 515.92 | O40: Granulado Madeira (10kg) | P40: -22 | Q40: Dia 5 | R40: 0
M41: Dia 5 | N41: 1915.92 | O41: Pagamento Recebido Bellocopo | P41: 1400 | Q41: Dia 5 | R41: 0
M42: Dia 6 | N42: 748.69 | O42: Fatura Cartão Mercado Livre | P42: -1167.23 | Q42: Dia 5 | R42: 0
M43: Dia 7 | N43: 148.09 | O43: Parcela Moto | P43: -600.6 | Q43: Dia 6 | R43: 0
M44: Dia 8 | N44: -9.91 | O44: Ração Gatos Golden Castrados | P44: -158 | Q44: Dia 6 | R44: 0
M45: Dia 9 | N45: -48.91 | O45: Microsoft | P45: -39 | Q45: Dia 6 | R45: 0
M46: Dia 10 | N46: -79.81 | O46: Netflix - Automatico | P46: -30.9 | Q46: Dia 9 | R46: 0
M47: Dia 11 | N47: -219.81 | O47: Dízimo (1/2 parte) | P47: -140 | Q47: Dia 9 | R47: 0
M48: Dia 12 | N48: -247.59 | O48: Anticoncepcional | P48: -27.78 | Q48: Dia 10 | R48: 0
M49: Dia 13 | N49: -264.08 | O49: SimplyPiano | P49: -16.49 | Q49: Dia 12 | R49: 0
M50: Dia 14 | N50: -264.08 | O50: 0 | P50: 0 | Q50: 0 | R50: 0
M51: Dia 15 | N51: -354.08 | O51: Gasolina Moto | P51: -90 | Q51: Dia 15 | R51: 0
M52: Dia 16 | N52: -393.78 | O52: Curso Aryanne Ativando a Libido | P52: -39.7 | Q52: Dia 15 | R52: 0
M53: Dia 17 | N53: -393.78 | O53: 0 | P53: 0 | Q53: 0 | R53: 0
M54: Dia 18 | N54: 806.22 | O54: Pagamento Recebido Bellocopo | P54: 1200 | Q54: Dia 20 | R54: 0
M55: Dia 19 | N55: -148.78 | O55: Fatura Cartão Nubank | P55: -955 | Q55: Dia 20 | R55: 0
M56: Dia 20 | N56: -160.48 | O56: Spotify | P56: -11.7 | Q56: Dia 20 | R56: 0
M57: Dia 21 | N57: -160.48 | O57: 0 | P57: 0 | Q57: 0 | R57: 0
M58: Dia 22 | N58: -260.38 | O58: Internet Atranet | P58: -99.9 | Q58: Dia 20 | R58: 0
M59: Dia 23 | N59: -271.37 | O59: PicsArt Photo | P59: -10.99 | Q59: Dia 21 | R59: 0
M60: Dia 24 | N60: -271.37 | O60: 0 | P60: 0 | Q60: 0 | R60: 0
M61: Dia 25 | N61: -391.37 | O61: Dízimo (2/2 parte) | P61: -120 | Q61: Dia 24 | R61: 0
M62: Dia 26 | N62: -511.37 | O62: Energia Elétrica (1/4 pagamento) | P62: -120 | Q62: Dia 20 | R62: 0
M63: Dia 27 | N63: -556.37 | O63: Internet Celular Vivo | P63: -45 | Q63: Dia 27 | R63: 0
M64: Dia 28 | N64: -683.87 | O64: Cílios | P64: -127.5 | Q64: Dia 28 | R64: 0
M65: Dia 29 | N65: -701.32 | O65: HBO | P65: -17.45 | Q65: Dia 29 | R65: 0
M66: Dia 30 | N66: -701.32 | O66: 0 | P66: 0 | Q66: 0 | R66: 0
M67: Dia 31 | N67: -701.32 | O67: 0 | P67: 0 | Q67: 0 | R67: 0

Sheet Novembro 2024
A1: Planejamento Mensal Káic e Gabi | I1: Mês: | J1: Novembro | M1: Resumo Finalização do Mês | S1: 0
A2: Data hoje formula | B2: Data formula | C2: Formula pgto ok | G2: Saldo Prévio | H2: Descrição Conta | I2: Valor | J2: Data vencimento | K2: Pago? | M2: =F33 -> Dia 31 | N2: =G33 -> 25.05 | O2: Valor sobra dia 31 - Final do mês
A3: =TODAY() -> 45567 | B3: 45597 | C3: =A3-B3 -> -30 | D3: =C3+K3 -> -30 | E3: =IF(10,K3="ok",0) -> FALSE | F3: Dia 1 | G3: ='Outubro 2024'!G33+I3 -> -701.32 | L3: =IF(A3=B3,"➜ Hoje","")
A4: =TODAY() -> 45567 | B4: =B3+1 -> 45598 | C4: =A4-B4 -> -31 | D4: =C4+K4 -> -31 | E4: =IF(10,K4="ok",0) -> FALSE | F4: Dia 2 | G4: =G3+I4 -> -729.31 | H4: Nível 6 Mercado Livre - Automatico | I4: -27.99 | J4: Dia 1 | L4: =IF(A4=B4,"➜ Hoje","") | M4: 0.2 | N4: =IF($N$2*M4<=0,"Em vermelho",$N$2*M4) -> 5.01 | O4: Comemoraçao dia 20
A5: =TODAY() -> 45567 | B5: =B4+1 -> 45599 | C5: =A5-B5 -> -32 | D5: =C5+K5 -> -32 | E5: =IF(10,K5="ok",0) -> FALSE | F5: Dia 3 | G5: =G4+I5 -> -729.31 | L5: =IF(A5=B5,"➜ Hoje","") | M5: 0.1 | N5: =IF($N$2*M5<=0,"Em vermelho",$N$2*M5) -> 2.505 | O5: Reforma Casa
A6: =TODAY() -> 45567 | B6: =B5+1 -> 45600 | C6: =A6-B6 -> -33 | D6: =C6+K6 -> -33 | E6: =IF(10,K6="ok",0) -> FALSE | F6: Dia 4 | G6: =G5+I6 -> -764.31 | H6: Granulado Madeira (10kg) | I6: -35 | J6: Dia 5 | L6: =IF(A6=B6,"➜ Hoje","") | M6: 0.4 | N6: =IF($N$2*M6<=0,"Em vermelho",$N$2*M6) -> 10.02 | O6: Tirar Carta A+B
A7: =TODAY() -> 45567 | B7: =B6+1 -> 45601 | C7: =A7-B7 -> -34 | D7: =C7+K7 -> -34 | E7: =IF(10,K7="ok",0) -> FALSE | F7: Dia 5 | G7: =G6+I7 -> 635.69 | H7: Pagamento Recebido Bellocopo | I7: 1400 | J7: Dia 5 | L7: =IF(A7=B7,"➜ Hoje","") | M7: 0.3 | N7: =IF($N$2*M7<=0,"Em vermelho",$N$2*M7) -> 7.515 | O7: Novas Alianças
A8: =TODAY() -> 45567 | B8: =B7+1 -> 45602 | C8: =A8-B8 -> -35 | D8: =C8+K8 -> -35 | E8: =IF(10,K8="ok",0) -> FALSE | F8: Dia 6 | G8: =G7+I8 -> 555.36 | H8: Fatura Cartão Mercado Pago | I8: =-120.03+39.7 -> -80.33 | J8: Dia 5 | L8: =IF(A8=B8,"➜ Hoje","")
A9: =TODAY() -> 45567 | B9: =B8+1 -> 45603 | C9: =A9-B9 -> -36 | D9: =C9+K9 -> -36 | E9: =IF(10,K9="ok",0) -> FALSE | F9: Dia 7 | G9: =G8+I9 -> -45.24 | H9: Parcela Moto | I9: -600.6 | J9: Dia 6 | L9: =IF(A9=B9,"➜ Hoje","") | M9: Planejamento Aquisições / Projetos
A10: =TODAY() -> 45567 | B10: =B9+1 -> 45604 | C10: =A10-B10 -> -37 | D10: =C10+K10 -> -37 | E10: =IF(10,K10="ok",0) -> FALSE | F10: Dia 8 | G10: =G9+I10 -> -203.24 | H10: Ração Gatos Golden Castrados | I10: -158 | J10: Dia 6 | L10: =IF(A10=B10,"➜ Hoje","")
A11: =TODAY() -> 45567 | B11: =B10+1 -> 45605 | C11: =A11-B11 -> -38 | D11: =C11+K11 -> -38 | E11: =IF(10,K11="ok",0) -> FALSE | F11: Dia 9 | G11: =G10+I11 -> -242.24 | H11: Microsoft | I11: -39 | J11: Dia 6 | L11: =IF(A11=B11,"➜ Hoje","") | M11: Data | N11: Valor média | O11: Descrição
A12: =TODAY() -> 45567 | B12: =B11+1 -> 45606 | C12: =A12-B12 -> -39 | D12: =C12+K12 -> -39 | E12: =IF(10,K12="ok",0) -> FALSE | F12: Dia 10 | G12: =G11+I12 -> -242.24 | L12: =IF(A12=B12,"➜ Hoje","") | M12: 45046 | N12: 400 | O12: Depurador de ar (Reforma Cozinha)
A13: =TODAY() -> 45567 | B13: =B12+1 -> 45607 | C13: =A13-B13 -> -40 | D13: =C13+K13 -> -40 | E13: =IF(10,K13="ok",0) -> FALSE | F13: Dia 11 | G13: =G12+I13 -> -242.24 | L13: =IF(A13=B13,"➜ Hoje","") | M13: 44540 | N13: 300 | O13: Revestimento Lume 45x90 Botanico Branco Retif.Azulejo (Reforma Cozinha)
A14: =TODAY() -> 45567 | B14: =B13+1 -> 45608 | C14: =A14-B14 -> -41 | D14: =C14+K14 -> -41 | E14: =IF(10,K14="ok",0) -> FALSE | F14: Dia 12 | G14: =G13+I14 -> -273.14 | H14: Netflix - Automatico | I14: -30.9 | J14: Dia 9 | L14: =IF(A14=B14,"➜ Hoje","")
A15: =TODAY() -> 45567 | B15: =B14+1 -> 45609 | C15: =A15-B15 -> -42 | D15: =C15+K15 -> -42 | E15: =IF(10,K15="ok",0) -> FALSE | F15: Dia 13 | G15: =G14+I15 -> -413.14 | H15: Dízimo (1/2 parte) | I15: -140 | J15: Dia 9 | L15: =IF(A15=B15,"➜ Hoje","")
A16: =TODAY() -> 45567 | B16: =B15+1 -> 45610 | C16: =A16-B16 -> -43 | D16: =C16+K16 -> -43 | E16: =IF(10,K16="ok",0) -> FALSE | F16: Dia 14 | G16: =G15+I16 -> -440.92 | H16: Anticoncepcional | I16: -27.78 | J16: Dia 10 | L16: =IF(A16=B16,"➜ Hoje","")
A17: =TODAY() -> 45567 | B17: =B16+1 -> 45611 | C17: =A17-B17 -> -44 | D17: =C17+K17 -> -44 | E17: =IF(10,K17="ok",0) -> FALSE | F17: Dia 15 | G17: =G16+I17 -> -457.41 | H17: SimplyPiano | I17: -16.49 | J17: Dia 12 | L17: =IF(A17=B17,"➜ Hoje","")
A18: =TODAY() -> 45567 | B18: =B17+1 -> 45612 | C18: =A18-B18 -> -45 | D18: =C18+K18 -> -45 | E18: =IF(10,K18="ok",0) -> FALSE | F18: Dia 16 | G18: =G17+I18 -> -594.41 | H18: Fatura Cartão Nubank | I18: -137 | J18: Dia 12 | L18: =IF(A18=B18,"➜ Hoje","") | M18: Planejamento Reposição Dispensa / Compras Mercado
A19: =TODAY() -> 45567 | B19: =B18+1 -> 45613 | C19: =A19-B19 -> -46 | D19: =C19+K19 -> -46 | E19: =IF(10,K19="ok",0) -> FALSE | F19: Dia 17 | G19: =G18+I19 -> -634.11 | H19: Curso Aryanne Ativando a Libido | I19: -39.7 | J19: Dia 15 | L19: =IF(A19=B19,"➜ Hoje","")
A20: =TODAY() -> 45567 | B20: =B19+1 -> 45614 | C20: =A20-B20 -> -47 | D20: =C20+K20 -> -47 | E20: =IF(10,K20="ok",0) -> FALSE | F20: Dia 18 | G20: =G19+I20 -> -634.11 | L20: =IF(A20=B20,"➜ Hoje","") | M20: Dia 15 | N20: 210 | O20: Pagamento Recebido VA Bellocopo
A21: =TODAY() -> 45567 | B21: =B20+1 -> 45615 | C21: =A21-B21 -> -48 | D21: =C21+K21 -> -48 | E21: =IF(10,K21="ok",0) -> FALSE | F21: Dia 19 | G21: =G20+I21 -> -634.11 | L21: =IF(A21=B21,"➜ Hoje","")
A22: =TODAY() -> 45567 | B22: =B21+1 -> 45616 | C22: =A22-B22 -> -49 | D22: =C22+K22 -> -49 | E22: =IF(10,K22="ok",0) -> FALSE | F22: Dia 20 | G22: =G21+I22 -> 565.89 | H22: Pagamento Recebido Bellocopo | I22: 1200 | J22: Dia 20 | L22: =IF(A22=B22,"➜ Hoje","") | M22: Planejamento Acerto de dividas - prorrogando para mês seguinte
A23: =TODAY() -> 45567 | B23: =B22+1 -> 45617 | C23: =A23-B23 -> -50 | D23: =C23+K23 -> -50 | E23: =IF(10,K23="ok",0) -> FALSE | F23: Dia 21 | G23: =G22+I23 -> 565.89 | L23: =IF(A23=B23,"➜ Hoje","")
A24: =TODAY() -> 45567 | B24: =B23+1 -> 45618 | C24: =A24-B24 -> -51 | D24: =C24+K24 -> -51 | E24: =IF(10,K24="ok",0) -> FALSE | F24: Dia 22 | G24: =G23+I24 -> 465.99 | H24: Internet Atranet | I24: -99.9 | J24: Dia 20 | L24: =IF(A24=B24,"➜ Hoje","")
A25: =TODAY() -> 45567 | B25: =B24+1 -> 45619 | C25: =A25-B25 -> -52 | D25: =C25+K25 -> -52 | E25: =IF(10,K25="ok",0) -> FALSE | F25: Dia 23 | G25: =G24+I25 -> 455 | H25: PicsArt Photo | I25: -10.99 | J25: Dia 21 | L25: =IF(A25=B25,"➜ Hoje","")
A26: =TODAY() -> 45567 | B26: =B25+1 -> 45620 | C26: =A26-B26 -> -53 | D26: =C26+K26 -> -53 | E26: =IF(10,K26="ok",0) -> FALSE | F26: Dia 24 | G26: =G25+I26 -> 455 | L26: =IF(A26=B26,"➜ Hoje","")
A27: =TODAY() -> 45567 | B27: =B26+1 -> 45621 | C27: =A27-B27 -> -54 | D27: =C27+K27 -> -54 | E27: =IF(10,K27="ok",0) -> FALSE | F27: Dia 25 | G27: =G26+I27 -> 335 | H27: Dízimo (2/2 parte) | I27: -120 | J27: Dia 24 | L27: =IF(A27=B27,"➜ Hoje","")
A28: =TODAY() -> 45567 | B28: =B27+1 -> 45622 | C28: =A28-B28 -> -55 | D28: =C28+K28 -> -55 | E28: =IF(10,K28="ok",0) -> FALSE | F28: Dia 26 | G28: =G27+I28 -> 215 | H28: Energia Elétrica (1/4 pagamento) | I28: -120 | J28: Dia 20 | L28: =IF(A28=B28,"➜ Hoje","")
A29: =TODAY() -> 45567 | B29: =B28+1 -> 45623 | C29: =A29-B29 -> -56 | D29: =C29+K29 -> -56 | E29: =IF(10,K29="ok",0) -> FALSE | F29: Dia 27 | G29: =G28+I29 -> 170 | H29: Internet Celular Vivo | I29: -45 | J29: Dia 27 | L29: =IF(A29=B29,"➜ Hoje","")
A30: =TODAY() -> 45567 | B30: =B29+1 -> 45624 | C30: =A30-B30 -> -57 | D30: =C30+K30 -> -57 | E30: =IF(10,K30="ok",0) -> FALSE | F30: Dia 28 | G30: =G29+I30 -> 42.5 | H30: Cílios | I30: -127.5 | J30: Dia 28 | L30: =IF(A30=B30,"➜ Hoje","") | M30: Prorrogar: | N30: =SUM(N24:N29) -> 0
A31: =TODAY() -> 45567 | B31: =B30+1 -> 45625 | C31: =A31-B31 -> -58 | D31: =C31+K31 -> -58 | E31: =IF(10,K31="ok",0) -> FALSE | F31: Dia 29 | G31: =G30+I31 -> 25.05 | H31: HBO | I31: -17.45 | J31: Dia 29 | L31: =IF(A31=B31,"➜ Hoje","") | M31: =M2 -> Dia 31 | N31: =N2+N30 -> 25.05 | O31: Valor sobra dia 31 - Final do mês
A32: =TODAY() -> 45567 | B32: =B31+1 -> 45626 | C32: =A32-B32 -> -59 | D32: =C32+K32 -> -59 | E32: =IF(10,K32="ok",0) -> FALSE | F32: Dia 30 | G32: =G31+I32 -> 25.05 | L32: =IF(A32=B32,"➜ Hoje","") | N32: =N30*2 -> 0
A33: =TODAY() -> 45567 | B33: 45596 | C33: =A33-B33 -> -29 | D33: =C33+K33 -> -29 | E33: =IF(10,K33="ok",0) -> FALSE | F33: Dia 31 | G33: =G32+I33 -> 25.05 | L33: =IF(A33=B33,"➜ Hoje","") | N33: =N30-N32 -> 0
M34: Pendencias para pagar
M36: {=F2:K33} -> 0 | N36: Saldo Prévio | O36: Descrição Conta | P36: Valor | Q36: Data vencimento | R36: Pago?
M37: Dia 1 | N37: -701.32 | O37: 0 | P37: 0 | Q37: 0 | R37: 0
M38: Dia 2 | N38: -729.31 | O38: Nível 6 Mercado Livre - Automatico | P38: -27.99 | Q38: Dia 1 | R38: 0
M39: Dia 3 | N39: -729.31 | O39: 0 | P39: 0 | Q39: 0 | R39: 0
M40: Dia 4 | N40: -764.31 | O40: Granulado Madeira (10kg) | P40: -35 | Q40: Dia 5 | R40: 0
M41: Dia 5 | N41: 635.69 | O41: Pagamento Recebido Bellocopo | P41: 1400 | Q41: Dia 5 | R41: 0
M42: Dia 6 | N42: 555.36 | O42: Fatura Cartão Mercado Pago | P42: -80.33 | Q42: Dia 5 | R42: 0
M43: Dia 7 | N43: -45.24 | O43: Parcela Moto | P43: -600.6 | Q43: Dia 6 | R43: 0
M44: Dia 8 | N44: -203.24 | O44: Ração Gatos Golden Castrados | P44: -158 | Q44: Dia 6 | R44: 0
M45: Dia 9 | N45: -242.24 | O45: Microsoft | P45: -39 | Q45: Dia 6 | R45: 0
M46: Dia 10 | N46: -242.24 | O46: 0 | P46: 0 | Q46: 0 | R46: 0
M47: Dia 11 | N47: -242.24 | O47: 0 | P47: 0 | Q47: 0 | R47: 0
M48: Dia 12 | N48: -273.14 | O48: Netflix - Automatico | P48: -30.9 | Q48: Dia 9 | R48: 0
M49: Dia 13 | N49: -413.14 | O49: Dízimo (1/2 parte) | P49: -140 | Q49: Dia 9 | R49: 0
M50: Dia 14 | N50: -440.92 | O50: Anticoncepcional | P50: -27.78 | Q50: Dia 10 | R50: 0
M51: Dia 15 | N51: -457.41 | O51: SimplyPiano | P51: -16.49 | Q51: Dia 12 | R51: 0
M52: Dia 16 | N52: -594.41 | O52: Fatura Cartão Nubank | P52: -137 | Q52: Dia 12 | R52: 0
M53: Dia 17 | N53: -634.11 | O53: Curso Aryanne Ativando a Libido | P53: -39.7 | Q53: Dia 15 | R53: 0
M54: Dia 18 | N54: -634.11 | O54: 0 | P54: 0 | Q54: 0 | R54: 0
M55: Dia 19 | N55: -634.11 | O55: 0 | P55: 0 | Q55: 0 | R55: 0
M56: Dia 20 | N56: 565.89 | O56: Pagamento Recebido Bellocopo | P56: 1200 | Q56: Dia 20 | R56: 0
M57: Dia 21 | N57: 565.89 | O57: 0 | P57: 0 | Q57: 0 | R57: 0
M58: Dia 22 | N58: 465.99 | O58: Internet Atranet | P58: -99.9 | Q58: Dia 20 | R58: 0
M59: Dia 23 | N59: 455 | O59: PicsArt Photo | P59: -10.99 | Q59: Dia 21 | R59: 0
M60: Dia 24 | N60: 455 | O60: 0 | P60: 0 | Q60: 0 | R60: 0
M61: Dia 25 | N61: 335 | O61: Dízimo (2/2 parte) | P61: -120 | Q61: Dia 24 | R61: 0
M62: Dia 26 | N62: 215 | O62: Energia Elétrica (1/4 pagamento) | P62: -120 | Q62: Dia 20 | R62: 0
M63: Dia 27 | N63: 170 | O63: Internet Celular Vivo | P63: -45 | Q63: Dia 27 | R63: 0
M64: Dia 28 | N64: 42.5 | O64: Cílios | P64: -127.5 | Q64: Dia 28 | R64: 0
M65: Dia 29 | N65: 25.05 | O65: HBO | P65: -17.45 | Q65: Dia 29 | R65: 0
M66: Dia 30 | N66: 25.05 | O66: 0 | P66: 0 | Q66: 0 | R66: 0
M67: Dia 31 | N67: 25.05 | O67: 0 | P67: 0 | Q67: 0 | R67: 0

Sheet Dezembro 2024
A1: Planejamento Mensal Káic e Gabi | I1: Mês: | J1: Dezembro | M1: Resumo Finalização do Mês | S1: 0
A2: Data hoje formula | B2: Data formula | C2: Formula pgto ok | G2: Saldo Prévio | H2: Descrição Conta | I2: Valor | J2: Data vencimento | K2: Pago? | M2: =F33 -> Dia 31 | N2: =G33 -> 2899.64 | O2: Valor sobra dia 31 - Final do mês
A3: =TODAY() -> 45567 | B3: 45627 | C3: =A3-B3 -> -60 | D3: =C3+K3 -> -60 | E3: =IF(10,K3="ok",0) -> FALSE | F3: Dia 1 | G3: ='Novembro 2024'!G33+'Novembro 2024'!I3 -> 25.05 | L3: =IF(A3=B3,"➜ Hoje","")
A4: =TODAY() -> 45567 | B4: =B3+1 -> 45628 | C4: =A4-B4 -> -61 | D4: =C4+K4 -> -61 | E4: =IF(10,K4="ok",0) -> FALSE | F4: Dia 2 | G4: =G3+I4 -> -2.94 | H4: Nível 6 Mercado Livre - Automatico | I4: -27.99 | J4: Dia 1 | L4: =IF(A4=B4,"➜ Hoje","") | M4: 0.2 | N4: =IF($N$2*M4<=0,"Em vermelho",$N$2*M4) -> 579.928 | O4: Comemoraçao dia 20
A5: =TODAY() -> 45567 | B5: =B4+1 -> 45629 | C5: =A5-B5 -> -62 | D5: =C5+K5 -> -62 | E5: =IF(10,K5="ok",0) -> FALSE | F5: Dia 3 | G5: =G4+I5 -> -2.94 | L5: =IF(A5=B5,"➜ Hoje","") | M5: 0.1 | N5: =IF($N$2*M5<=0,"Em vermelho",$N$2*M5) -> 289.964 | O5: Reforma Casa
A6: =TODAY() -> 45567 | B6: =B5+1 -> 45630 | C6: =A6-B6 -> -63 | D6: =C6+K6 -> -63 | E6: =IF(10,K6="ok",0) -> FALSE | F6: Dia 4 | G6: =G5+I6 -> -37.94 | H6: Granulado Madeira (10kg) | I6: -35 | J6: Dia 5 | L6: =IF(A6=B6,"➜ Hoje","") | M6: 0.4 | N6: =IF($N$2*M6<=0,"Em vermelho",$N$2*M6) -> 1159.856 | O6: Tirar Carta A+B
A7: =TODAY() -> 45567 | B7: =B6+1 -> 45631 | C7: =A7-B7 -> -64 | D7: =C7+K7 -> -64 | E7: =IF(10,K7="ok",0) -> FALSE | F7: Dia 5 | G7: =G6+I7 -> 1362.06 | H7: Pagamento Recebido Bellocopo | I7: 1400 | J7: Dia 5 | L7: =IF(A7=B7,"➜ Hoje","") | M7: 0.3 | N7: =IF($N$2*M7<=0,"Em vermelho",$N$2*M7) -> 869.892 | O7: Novas Alianças
A8: =TODAY() -> 45567 | B8: =B7+1 -> 45632 | C8: =A8-B8 -> -65 | D8: =C8+K8 -> -65 | E8: =IF(10,K8="ok",0) -> FALSE | F8: Dia 6 | G8: =G7+I8 -> 1351.59 | H8: Fatura Cartão Mercado Livre | I8: =-50.17+39.7 -> -10.47 | J8: Dia 5 | L8: =IF(A8=B8,"➜ Hoje","")
A9: =TODAY() -> 45567 | B9: =B8+1 -> 45633 | C9: =A9-B9 -> -66 | D9: =C9+K9 -> -66 | E9: =IF(10,K9="ok",0) -> FALSE | F9: Dia 7 | G9: =G8+I9 -> 750.99 | H9: Parcela Moto | I9: -600.6 | J9: Dia 6 | L9: =IF(A9=B9,"➜ Hoje","") | M9: Planejamento Aquisições / Projetos
A10: =TODAY() -> 45567 | B10: =B9+1 -> 45634 | C10: =A10-B10 -> -67 | D10: =C10+K10 -> -67 | E10: =IF(10,K10="ok",0) -> FALSE | F10: Dia 8 | G10: =G9+I10 -> 592.99 | H10: Ração Gatos Golden Castrados | I10: -158 | J10: Dia 6 | L10: =IF(A10=B10,"➜ Hoje","")
A11: =TODAY() -> 45567 | B11: =B10+1 -> 45635 | C11: =A11-B11 -> -68 | D11: =C11+K11 -> -68 | E11: =IF(10,K11="ok",0) -> FALSE | F11: Dia 9 | G11: =G10+I11 -> 553.99 | H11: Microsoft | I11: -39 | J11: Dia 6 | L11: =IF(A11=B11,"➜ Hoje","") | M11: Data | N11: Valor média | O11: Descrição
A12: =TODAY() -> 45567 | B12: =B11+1 -> 45636 | C12: =A12-B12 -> -69 | D12: =C12+K12 -> -69 | E12: =IF(10,K12="ok",0) -> FALSE | F12: Dia 10 | G12: =G11+I12 -> 553.99 | L12: =IF(A12=B12,"➜ Hoje","") | M12: 45046 | N12: 400 | O12: Depurador de ar (Reforma Cozinha)
A13: =TODAY() -> 45567 | B13: =B12+1 -> 45637 | C13: =A13-B13 -> -70 | D13: =C13+K13 -> -70 | E13: =IF(10,K13="ok",0) -> FALSE | F13: Dia 11 | G13: =G12+I13 -> 553.99 | L13: =IF(A13=B13,"➜ Hoje","") | M13: 44540 | N13: 300 | O13: Revestimento Lume 45x90 Botanico Branco Retif.Azulejo (Reforma Cozinha)
A14: =TODAY() -> 45567 | B14: =B13+1 -> 45638 | C14: =A14-B14 -> -71 | D14: =C14+K14 -> -71 | E14: =IF(10,K14="ok",0) -> FALSE | F14: Dia 12 | G14: =G13+I14 -> 523.09 | H14: Netflix - Automatico | I14: -30.9 | J14: Dia 9 | L14: =IF(A14=B14,"➜ Hoje","")
A15: =TODAY() -> 45567 | B15: =B14+1 -> 45639 | C15: =A15-B15 -> -72 | D15: =C15+K15 -> -72 | E15: =IF(10,K15="ok",0) -> FALSE | F15: Dia 13 | G15: =G14+I15 -> 383.09 | H15: Dízimo (1/2 parte) | I15: -140 | J15: Dia 9 | L15: =IF(A15=B15,"➜ Hoje","")
A16: =TODAY() -> 45567 | B16: =B15+1 -> 45640 | C16: =A16-B16 -> -73 | D16: =C16+K16 -> -73 | E16: =IF(10,K16="ok",0) -> FALSE | F16: Dia 14 | G16: =G15+I16 -> 355.31 | H16: Anticoncepcional | I16: -27.78 | J16: Dia 10 | L16: =IF(A16=B16,"➜ Hoje","")
A17: =TODAY() -> 45567 | B17: =B16+1 -> 45641 | C17: =A17-B17 -> -74 | D17: =C17+K17 -> -74 | E17: =IF(10,K17="ok",0) -> FALSE | F17: Dia 15 | G17: =G16+I17 -> 338.82 | H17: SimplyPiano | I17: -16.49 | J17: Dia 12 | L17: =IF(A17=B17,"➜ Hoje","")
A18: =TODAY() -> 45567 | B18: =B17+1 -> 45642 | C18: =A18-B18 -> -75 | D18: =C18+K18 -> -75 | E18: =IF(10,K18="ok",0) -> FALSE | F18: Dia 16 | G18: =G17+I18 -> 299.12 | H18: Curso Aryanne Ativando a Libido | I18: -39.7 | J18: Dia 15 | L18: =IF(A18=B18,"➜ Hoje","") | M18: Planejamento Reposição Dispensa / Compras Mercado
A19: =TODAY() -> 45567 | B19: =B18+1 -> 45643 | C19: =A19-B19 -> -76 | D19: =C19+K19 -> -76 | E19: =IF(10,K19="ok",0) -> FALSE | F19: Dia 17 | G19: =G18+I19 -> 299.12 | L19: =IF(A19=B19,"➜ Hoje","")
A20: =TODAY() -> 45567 | B20: =B19+1 -> 45644 | C20: =A20-B20 -> -77 | D20: =C20+K20 -> -77 | E20: =IF(10,K20="ok",0) -> FALSE | F20: Dia 18 | G20: =G19+I20 -> 2299.12 | H20: Acréscimo 13 Salario | I20: 2000 | L20: =IF(A20=B20,"➜ Hoje","") | M20: Dia 15 | N20: 210 | O20: Pagamento Recebido VA Bellocopo
A21: =TODAY() -> 45567 | B21: =B20+1 -> 45645 | C21: =A21-B21 -> -78 | D21: =C21+K21 -> -78 | E21: =IF(10,K21="ok",0) -> FALSE | F21: Dia 19 | G21: =G20+I21 -> 2240.48 | H21: Fatura Cartão Nubank | I21: -58.64 | J21: Dia 12 | L21: =IF(A21=B21,"➜ Hoje","")
A22: =TODAY() -> 45567 | B22: =B21+1 -> 45646 | C22: =A22-B22 -> -79 | D22: =C22+K22 -> -79 | E22: =IF(10,K22="ok",0) -> FALSE | F22: Dia 20 | G22: =G21+I22 -> 3440.48 | H22: Pagamento Recebido Bellocopo | I22: 1200 | J22: Dia 20 | L22: =IF(A22=B22,"➜ Hoje","") | M22: Planejamento Acerto de dividas - prorrogando para mês seguinte
A23: =TODAY() -> 45567 | B23: =B22+1 -> 45647 | C23: =A23-B23 -> -80 | D23: =C23+K23 -> -80 | E23: =IF(10,K23="ok",0) -> FALSE | F23: Dia 21 | G23: =G22+I23 -> 3440.48 | L23: =IF(A23=B23,"➜ Hoje","")
A24: =TODAY() -> 45567 | B24: =B23+1 -> 45648 | C24: =A24-B24 -> -81 | D24: =C24+K24 -> -81 | E24: =IF(10,K24="ok",0) -> FALSE | F24: Dia 22 | G24: =G23+I24 -> 3340.58 | H24: Internet Atranet | I24: -99.9 | J24: Dia 20 | L24: =IF(A24=B24,"➜ Hoje","")
A25: =TODAY() -> 45567 | B25: =B24+1 -> 45649 | C25: =A25-B25 -> -82 | D25: =C25+K25 -> -82 | E25: =IF(10,K25="ok",0) -> FALSE | F25: Dia 23 | G25: =G24+I25 -> 3329.59 | H25: PicsArt Photo | I25: -10.99 | J25: Dia 21 | L25: =IF(A25=B25,"➜ Hoje","")
A26: =TODAY() -> 45567 | B26: =B25+1 -> 45650 | C26: =A26-B26 -> -83 | D26: =C26+K26 -> -83 | E26: =IF(10,K26="ok",0) -> FALSE | F26: Dia 24 | G26: =G25+I26 -> 3329.59 | L26: =IF(A26=B26,"➜ Hoje","")
A27: =TODAY() -> 45567 | B27: =B26+1 -> 45651 | C27: =A27-B27 -> -84 | D27: =C27+K27 -> -84 | E27: =IF(10,K27="ok",0) -> FALSE | F27: Dia 25 | G27: =G26+I27 -> 3209.59 | H27: Dízimo (2/2 parte) | I27: -120 | J27: Dia 24 | L27: =IF(A27=B27,"➜ Hoje","")
A28: =TODAY() -> 45567 | B28: =B27+1 -> 45652 | C28: =A28-B28 -> -85 | D28: =C28+K28 -> -85 | E28: =IF(10,K28="ok",0) -> FALSE | F28: Dia 26 | G28: =G27+I28 -> 3089.59 | H28: Energia Elétrica (1/4 pagamento) | I28: -120 | J28: Dia 20 | L28: =IF(A28=B28,"➜ Hoje","")
A29: =TODAY() -> 45567 | B29: =B28+1 -> 45653 | C29: =A29-B29 -> -86 | D29: =C29+K29 -> -86 | E29: =IF(10,K29="ok",0) -> FALSE | F29: Dia 27 | G29: =G28+I29 -> 3044.59 | H29: Internet Celular Vivo | I29: -45 | J29: Dia 27 | L29: =IF(A29=B29,"➜ Hoje","")
A30: =TODAY() -> 45567 | B30: =B29+1 -> 45654 | C30: =A30-B30 -> -87 | D30: =C30+K30 -> -87 | E30: =IF(10,K30="ok",0) -> FALSE | F30: Dia 28 | G30: =G29+I30 -> 2917.09 | H30: Cílios | I30: -127.5 | J30: Dia 28 | L30: =IF(A30=B30,"➜ Hoje","") | M30: Prorrogar: | N30: =SUM(N24:N29) -> 0
A31: =TODAY() -> 45567 | B31: =B30+1 -> 45655 | C31: =A31-B31 -> -88 | D31: =C31+K31 -> -88 | E31: =IF(10,K31="ok",0) -> FALSE | F31: Dia 29 | G31: =G30+I31 -> 2899.64 | H31: HBO | I31: -17.45 | J31: Dia 29 | L31: =IF(A31=B31,"➜ Hoje","") | M31: =M2 -> Dia 31 | N31: =N2+N30 -> 2899.64 | O31: Valor sobra dia 31 - Final do mês
A32: =TODAY() -> 45567 | B32: =B31+1 -> 45656 | C32: =A32-B32 -> -89 | D32: =C32+K32 -> -89 | E32: =IF(10,K32="ok",0) -> FALSE | F32: Dia 30 | G32: =G31+I32 -> 2899.64 | L32: =IF(A32=B32,"➜ Hoje","") | N32: =N30*2 -> 0
A33: =TODAY() -> 45567 | B33: 45596 | C33: =A33-B33 -> -29 | D33: =C33+K33 -> -29 | E33: =IF(10,K33="ok",0) -> FALSE | F33: Dia 31 | G33: =G32+I33 -> 2899.64 | L33: =IF(A33=B33,"➜ Hoje","") | N33: =N30-N32 -> 0
M34: Pendencias para pagar
M36: {=F2:K33} -> 0 | N36: Saldo Prévio | O36: Descrição Conta | P36: Valor | Q36: Data vencimento | R36: Pago?
M37: Dia 1 | N37: 25.05 | O37: 0 | P37: 0 | Q37: 0 | R37: 0
M38: Dia 2 | N38: -2.94 | O38: Nível 6 Mercado Livre - Automatico | P38: -27.99 | Q38: Dia 1 | R38: 0
M39: Dia 3 | N39: -2.94 | O39: 0 | P39: 0 | Q39: 0 | R39: 0
M40: Dia 4 | N40: -37.94 | O40: Granulado Madeira (10kg) | P40: -35 | Q40: Dia 5 | R40: 0
M41: Dia 5 | N41: 1362.06 | O41: Pagamento Recebido Bellocopo | P41: 1400 | Q41: Dia 5 | R41: 0
M42: Dia 6 | N42: 1351.59 | O42: Fatura Cartão Mercado Livre | P42: -10.47 | Q42: Dia 5 | R42: 0
M43: Dia 7 | N43: 750.99 | O43: Parcela Moto | P43: -600.6 | Q43: Dia 6 | R43: 0
M44: Dia 8 | N44: 592.99 | O44: Ração Gatos Golden Castrados | P44: -158 | Q44: Dia 6 | R44: 0
M45: Dia 9 | N45: 553.99 | O45: Microsoft | P45: -39 | Q45: Dia 6 | R45: 0
M46: Dia 10 | N46: 553.99 | O46: 0 | P46: 0 | Q46: 0 | R46: 0
M47: Dia 11 | N47: 553.99 | O47: 0 | P47: 0 | Q47: 0 | R47: 0
M48: Dia 12 | N48: 523.09 | O48: Netflix - Automatico | P48: -30.9 | Q48: Dia 9 | R48: 0
M49: Dia 13 | N49: 383.09 | O49: Dízimo (1/2 parte) | P49: -140 | Q49: Dia 9 | R49: 0
M50: Dia 14 | N50: 355.31 | O50: Anticoncepcional | P50: -27.78 | Q50: Dia 10 | R50: 0
M51: Dia 15 | N51: 338.82 | O51: SimplyPiano | P51: -16.49 | Q51: Dia 12 | R51: 0
M52: Dia 16 | N52: 299.12 | O52: Curso Aryanne Ativando a Libido | P52: -39.7 | Q52: Dia 15 | R52: 0
M53: Dia 17 | N53: 299.12 | O53: 0 | P53: 0 | Q53: 0 | R53: 0
M54: Dia 18 | N54: 2299.12 | O54: Acréscimo 13 Salario | P54: 2000 | Q54: 0 | R54: 0
M55: Dia 19 | N55: 2240.48 | O55: Fatura Cartão Nubank | P55: -58.64 | Q55: Dia 12 | R55: 0
M56: Dia 20 | N56: 3440.48 | O56: Pagamento Recebido Bellocopo | P56: 1200 | Q56: Dia 20 | R56: 0
M57: Dia 21 | N57: 3440.48 | O57: 0 | P57: 0 | Q57: 0 | R57: 0
M58: Dia 22 | N58: 3340.58 | O58: Internet Atranet | P58: -99.9 | Q58: Dia 20 | R58: 0
M59: Dia 23 | N59: 3329.59 | O59: PicsArt Photo | P59: -10.99 | Q59: Dia 21 | R59: 0
M60: Dia 24 | N60: 3329.59 | O60: 0 | P60: 0 | Q60: 0 | R60: 0
M61: Dia 25 | N61: 3209.59 | O61: Dízimo (2/2 parte) | P61: -120 | Q61: Dia 24 | R61: 0
M62: Dia 26 | N62: 3089.59 | O62: Energia Elétrica (1/4 pagamento) | P62: -120 | Q62: Dia 20 | R62: 0
M63: Dia 27 | N63: 3044.59 | O63: Internet Celular Vivo | P63: -45 | Q63: Dia 27 | R63: 0
M64: Dia 28 | N64: 2917.09 | O64: Cílios | P64: -127.5 | Q64: Dia 28 | R64: 0
M65: Dia 29 | N65: 2899.64 | O65: HBO | P65: -17.45 | Q65: Dia 29 | R65: 0
M66: Dia 30 | N66: 2899.64 | O66: 0 | P66: 0 | Q66: 0 | R66: 0
M67: Dia 31 | N67: 2899.64 | O67: 0 | P67: 0 | Q67: 0 | R67: 0

Sheet Janeiro 2025
A1: Planejamento Mensal Káic e Gabi | I1: Mês: | J1: Janeiro | M1: Resumo Finalização do Mês | S1: 0
A2: Data hoje formula | B2: Data formula | C2: Formula pgto ok | G2: Saldo Prévio | H2: Descrição Conta | I2: Valor | J2: Data vencimento | K2: Pago? | M2: =F33 -> Dia 31 | N2: =G33 -> 4433.47 | O2: Valor sobra dia 31 - Final do mês
A3: =TODAY() -> 45567 | B3: 45658 | C3: =A3-B3 -> -91 | D3: =C3+K3 -> -91 | E3: =IF(10,K3="ok",0) -> FALSE | F3: Dia 1 | G3: ='Dezembro 2024'!G33+'Dezembro 2024'!I3 -> 2899.64 | L3: =IF(A3=B3,"➜ Hoje","")
A4: =TODAY() -> 45567 | B4: =B3+1 -> 45659 | C4: =A4-B4 -> -92 | D4: =C4+K4 -> -92 | E4: =IF(10,K4="ok",0) -> FALSE | F4: Dia 2 | G4: =G3+I4 -> 2871.65 | H4: Nível 6 Mercado Livre - Automatico | I4: -27.99 | J4: Dia 1 | L4: =IF(A4=B4,"➜ Hoje","") | M4: 0.2 | N4: =IF($N$2*M4<=0,"Em vermelho",$N$2*M4) -> 886.694 | O4: Comemoraçao dia 20
A5: =TODAY() -> 45567 | B5: =B4+1 -> 45660 | C5: =A5-B5 -> -93 | D5: =C5+K5 -> -93 | E5: =IF(10,K5="ok",0) -> FALSE | F5: Dia 3 | G5: =G4+I5 -> 2871.65 | L5: =IF(A5=B5,"➜ Hoje","") | M5: 0.1 | N5: =IF($N$2*M5<=0,"Em vermelho",$N$2*M5) -> 443.347 | O5: Reforma Casa
A6: =TODAY() -> 45567 | B6: =B5+1 -> 45661 | C6: =A6-B6 -> -94 | D6: =C6+K6 -> -94 | E6: =IF(10,K6="ok",0) -> FALSE | F6: Dia 4 | G6: =G5+I6 -> 2836.65 | H6: Granulado Madeira (10kg) | I6: -35 | J6: Dia 5 | L6: =IF(A6=B6,"➜ Hoje","") | M6: 0.4 | N6: =IF($N$2*M6<=0,"Em vermelho",$N$2*M6) -> 1773.388 | O6: Tirar Carta A+B
A7: =TODAY() -> 45567 | B7: =B6+1 -> 45662 | C7: =A7-B7 -> -95 | D7: =C7+K7 -> -95 | E7: =IF(10,K7="ok",0) -> FALSE | F7: Dia 5 | G7: =G6+I7 -> 4236.65 | H7: Pagamento Recebido Bellocopo | I7: 1400 | J7: Dia 5 | L7: =IF(A7=B7,"➜ Hoje","") | M7: 0.3 | N7: =IF($N$2*M7<=0,"Em vermelho",$N$2*M7) -> 1330.041 | O7: Novas Alianças
A8: =TODAY() -> 45567 | B8: =B7+1 -> 45663 | C8: =A8-B8 -> -96 | D8: =C8+K8 -> -96 | E8: =IF(10,K8="ok",0) -> FALSE | F8: Dia 6 | G8: =G7+I8 -> 4226.18 | H8: Fatura Cartão Mercado Livre | I8: =-50.17+39.7 -> -10.47 | J8: Dia 5 | L8: =IF(A8=B8,"➜ Hoje","")
A9: =TODAY() -> 45567 | B9: =B8+1 -> 45664 | C9: =A9-B9 -> -97 | D9: =C9+K9 -> -97 | E9: =IF(10,K9="ok",0) -> FALSE | F9: Dia 7 | G9: =G8+I9 -> 4226.18 | H9: Parcela Moto | I9: 0 | J9: Dia 6 | L9: =IF(A9=B9,"➜ Hoje","") | M9: Planejamento Aquisições / Projetos
A10: =TODAY() -> 45567 | B10: =B9+1 -> 45665 | C10: =A10-B10 -> -98 | D10: =C10+K10 -> -98 | E10: =IF(10,K10="ok",0) -> FALSE | F10: Dia 8 | G10: =G9+I10 -> 4068.18 | H10: Ração Gatos Golden Castrados | I10: -158 | J10: Dia 6 | L10: =IF(A10=B10,"➜ Hoje","")
A11: =TODAY() -> 45567 | B11: =B10+1 -> 45666 | C11: =A11-B11 -> -99 | D11: =C11+K11 -> -99 | E11: =IF(10,K11="ok",0) -> FALSE | F11: Dia 9 | G11: =G10+I11 -> 4029.18 | H11: Microsoft | I11: -39 | J11: Dia 6 | L11: =IF(A11=B11,"➜ Hoje","") | M11: Data | N11: Valor média | O11: Descrição
A12: =TODAY() -> 45567 | B12: =B11+1 -> 45667 | C12: =A12-B12 -> -100 | D12: =C12+K12 -> -100 | E12: =IF(10,K12="ok",0) -> FALSE | F12: Dia 10 | G12: =G11+I12 -> 4029.18 | L12: =IF(A12=B12,"➜ Hoje","") | M12: 45046 | N12: 400 | O12: Depurador de ar (Reforma Cozinha)
A13: =TODAY() -> 45567 | B13: =B12+1 -> 45668 | C13: =A13-B13 -> -101 | D13: =C13+K13 -> -101 | E13: =IF(10,K13="ok",0) -> FALSE | F13: Dia 11 | G13: =G12+I13 -> 4029.18 | L13: =IF(A13=B13,"➜ Hoje","") | M13: 44540 | N13: 300 | O13: Revestimento Lume 45x90 Botanico Branco Retif.Azulejo (Reforma Cozinha)
A14: =TODAY() -> 45567 | B14: =B13+1 -> 45669 | C14: =A14-B14 -> -102 | D14: =C14+K14 -> -102 | E14: =IF(10,K14="ok",0) -> FALSE | F14: Dia 12 | G14: =G13+I14 -> 3998.28 | H14: Netflix - Automatico | I14: -30.9 | J14: Dia 9 | L14: =IF(A14=B14,"➜ Hoje","")
A15: =TODAY() -> 45567 | B15: =B14+1 -> 45670 | C15: =A15-B15 -> -103 | D15: =C15+K15 -> -103 | E15: =IF(10,K15="ok",0) -> FALSE | F15: Dia 13 | G15: =G14+I15 -> 3858.28 | H15: Dízimo (1/2 parte) | I15: -140 | J15: Dia 9 | L15: =IF(A15=B15,"➜ Hoje","")
A16: =TODAY() -> 45567 | B16: =B15+1 -> 45671 | C16: =A16-B16 -> -104 | D16: =C16+K16 -> -104 | E16: =IF(10,K16="ok",0) -> FALSE | F16: Dia 14 | G16: =G15+I16 -> 3830.5 | H16: Anticoncepcional | I16: -27.78 | J16: Dia 10 | L16: =IF(A16=B16,"➜ Hoje","")
A17: =TODAY() -> 45567 | B17: =B16+1 -> 45672 | C17: =A17-B17 -> -105 | D17: =C17+K17 -> -105 | E17: =IF(10,K17="ok",0) -> FALSE | F17: Dia 15 | G17: =G16+I17 -> 3814.01 | H17: SimplyPiano | I17: -16.49 | J17: Dia 12 | L17: =IF(A17=B17,"➜ Hoje","")
A18: =TODAY() -> 45567 | B18: =B17+1 -> 45673 | C18: =A18-B18 -> -106 | D18: =C18+K18 -> -106 | E18: =IF(10,K18="ok",0) -> FALSE | F18: Dia 16 | G18: =G17+I18 -> 3774.31 | H18: Curso Aryanne Ativando a Libido | I18: -39.7 | J18: Dia 15 | L18: =IF(A18=B18,"➜ Hoje","") | M18: Planejamento Reposição Dispensa / Compras Mercado
A19: =TODAY() -> 45567 | B19: =B18+1 -> 45674 | C19: =A19-B19 -> -107 | D19: =C19+K19 -> -107 | E19: =IF(10,K19="ok",0) -> FALSE | F19: Dia 17 | G19: =G18+I19 -> 3774.31 | L19: =IF(A19=B19,"➜ Hoje","")
A20: =TODAY() -> 45567 | B20: =B19+1 -> 45675 | C20: =A20-B20 -> -108 | D20: =C20+K20 -> -108 | E20: =IF(10,K20="ok",0) -> FALSE | F20: Dia 18 | G20: =G19+I20 -> 3774.31 | L20: =IF(A20=B20,"➜ Hoje","") | M20: Dia 15 | N20: 210 | O20: Pagamento Recebido VA Bellocopo
A21: =TODAY() -> 45567 | B21: =B20+1 -> 45676 | C21: =A21-B21 -> -109 | D21: =C21+K21 -> -109 | E21: =IF(10,K21="ok",0) -> FALSE | F21: Dia 19 | G21: =G20+I21 -> 3774.31 | H21: Fatura Cartão Nubank | I21: 0 | J21: Dia 12 | L21: =IF(A21=B21,"➜ Hoje","")
A22: =TODAY() -> 45567 | B22: =B21+1 -> 45677 | C22: =A22-B22 -> -110 | D22: =C22+K22 -> -110 | E22: =IF(10,K22="ok",0) -> FALSE | F22: Dia 20 | G22: =G21+I22 -> 4974.31 | H22: Pagamento Recebido Bellocopo | I22: 1200 | J22: Dia 20 | L22: =IF(A22=B22,"➜ Hoje","") | M22: Planejamento Acerto de dividas - prorrogando para mês seguinte
A23: =TODAY() -> 45567 | B23: =B22+1 -> 45678 | C23: =A23-B23 -> -111 | D23: =C23+K23 -> -111 | E23: =IF(10,K23="ok",0) -> FALSE | F23: Dia 21 | G23: =G22+I23 -> 4974.31 | L23: =IF(A23=B23,"➜ Hoje","")
A24: =TODAY() -> 45567 | B24: =B23+1 -> 45679 | C24: =A24-B24 -> -112 | D24: =C24+K24 -> -112 | E24: =IF(10,K24="ok",0) -> FALSE | F24: Dia 22 | G24: =G23+I24 -> 4874.41 | H24: Internet Atranet | I24: -99.9 | J24: Dia 20 | L24: =IF(A24=B24,"➜ Hoje","")
A25: =TODAY() -> 45567 | B25: =B24+1 -> 45680 | C25: =A25-B25 -> -113 | D25: =C25+K25 -> -113 | E25: =IF(10,K25="ok",0) -> FALSE | F25: Dia 23 | G25: =G24+I25 -> 4863.42 | H25: PicsArt Photo | I25: -10.99 | J25: Dia 21 | L25: =IF(A25=B25,"➜ Hoje","")
A26: =TODAY() -> 45567 | B26: =B25+1 -> 45681 | C26: =A26-B26 -> -114 | D26: =C26+K26 -> -114 | E26: =IF(10,K26="ok",0) -> FALSE | F26: Dia 24 | G26: =G25+I26 -> 4863.42 | L26: =IF(A26=B26,"➜ Hoje","")
A27: =TODAY() -> 45567 | B27: =B26+1 -> 45682 | C27: =A27-B27 -> -115 | D27: =C27+K27 -> -115 | E27: =IF(10,K27="ok",0) -> FALSE | F27: Dia 25 | G27: =G26+I27 -> 4743.42 | H27: Dízimo (2/2 parte) | I27: -120 | J27: Dia 24 | L27: =IF(A27=B27,"➜ Hoje","")
A28: =TODAY() -> 45567 | B28: =B27+1 -> 45683 | C28: =A28-B28 -> -116 | D28: =C28+K28 -> -116 | E28: =IF(10,K28="ok",0) -> FALSE | F28: Dia 26 | G28: =G27+I28 -> 4623.42 | H28: Energia Elétrica (1/4 pagamento) | I28: -120 | J28: Dia 20 | L28: =IF(A28=B28,"➜ Hoje","")
A29: =TODAY() -> 45567 | B29: =B28+1 -> 45684 | C29: =A29-B29 -> -117 | D29: =C29+K29 -> -117 | E29: =IF(10,K29="ok",0) -> FALSE | F29: Dia 27 | G29: =G28+I29 -> 4578.42 | H29: Internet Celular Vivo | I29: -45 | J29: Dia 27 | L29: =IF(A29=B29,"➜ Hoje","")
A30: =TODAY() -> 45567 | B30: =B29+1 -> 45685 | C30: =A30-B30 -> -118 | D30: =C30+K30 -> -118 | E30: =IF(10,K30="ok",0) -> FALSE | F30: Dia 28 | G30: =G29+I30 -> 4450.92 | H30: Cílios | I30: -127.5 | J30: Dia 28 | L30: =IF(A30=B30,"➜ Hoje","") | M30: Prorrogar: | N30: =SUM(N24:N29) -> 0
A31: =TODAY() -> 45567 | B31: =B30+1 -> 45686 | C31: =A31-B31 -> -119 | D31: =C31+K31 -> -119 | E31: =IF(10,K31="ok",0) -> FALSE | F31: Dia 29 | G31: =G30+I31 -> 4433.47 | H31: HBO | I31: -17.45 | J31: Dia 29 | L31: =IF(A31=B31,"➜ Hoje","") | M31: =M2 -> Dia 31 | N31: =N2+N30 -> 4433.47 | O31: Valor sobra dia 31 - Final do mês
A32: =TODAY() -> 45567 | B32: =B31+1 -> 45687 | C32: =A32-B32 -> -120 | D32: =C32+K32 -> -120 | E32: =IF(10,K32="ok",0) -> FALSE | F32: Dia 30 | G32: =G31+I32 -> 4433.47 | L32: =IF(A32=B32,"➜ Hoje","") | N32: =N30*2 -> 0
A33: =TODAY() -> 45567 | B33: 45596 | C33: =A33-B33 -> -29 | D33: =C33+K33 -> -29 | E33: =IF(10,K33="ok",0) -> FALSE | F33: Dia 31 | G33: =G32+I33 -> 4433.47 | L33: =IF(A33=B33,"➜ Hoje","") | N33: =N30-N32 -> 0
M34: Pendencias para pagar
M36: {=F2:K33} -> 0 | N36: Saldo Prévio | O36: Descrição Conta | P36: Valor | Q36: Data vencimento | R36: Pago?
M37: Dia 1 | N37: 2899.64 | O37: 0 | P37: 0 | Q37: 0 | R37: 0
M38: Dia 2 | N38: 2871.65 | O38: Nível 6 Mercado Livre - Automatico | P38: -27.99 | Q38: Dia 1 | R38: 0
M39: Dia 3 | N39: 2871.65 | O39: 0 | P39: 0 | Q39: 0 | R39: 0
M40: Dia 4 | N40: 2836.65 | O40: Granulado Madeira (10kg) | P40: -35 | Q40: Dia 5 | R40: 0
M41: Dia 5 | N41: 4236.65 | O41: Pagamento Recebido Bellocopo | P41: 1400 | Q41: Dia 5 | R41: 0
M42: Dia 6 | N42: 4226.18 | O42: Fatura Cartão Mercado Livre | P42: -10.47 | Q42: Dia 5 | R42: 0
M43: Dia 7 | N43: 4226.18 | O43: Parcela Moto | P43: 0 | Q43: Dia 6 | R43: 0
M44: Dia 8 | N44: 4068.18 | O44: Ração Gatos Golden Castrados | P44: -158 | Q44: Dia 6 | R44: 0
M45: Dia 9 | N45: 4029.18 | O45: Microsoft | P45: -39 | Q45: Dia 6 | R45: 0
M46: Dia 10 | N46: 4029.18 | O46: 0 | P46: 0 | Q46: 0 | R46: 0
M47: Dia 11 | N47: 4029.18 | O47: 0 | P47: 0 | Q47: 0 | R47: 0
M48: Dia 12 | N48: 3998.28 | O48: Netflix - Automatico | P48: -30.9 | Q48: Dia 9 | R48: 0
M49: Dia 13 | N49: 3858.28 | O49: Dízimo (1/2 parte) | P49: -140 | Q49: Dia 9 | R49: 0
M50: Dia 14 | N50: 3830.5 | O50: Anticoncepcional | P50: -27.78 | Q50: Dia 10 | R50: 0
M51: Dia 15 | N51: 3814.01 | O51: SimplyPiano | P51: -16.49 | Q51: Dia 12 | R51: 0
M52: Dia 16 | N52: 3774.31 | O52: Curso Aryanne Ativando a Libido | P52: -39.7 | Q52: Dia 15 | R52: 0
M53: Dia 17 | N53: 3774.31 | O53: 0 | P53: 0 | Q53: 0 | R53: 0
M54: Dia 18 | N54: 3774.31 | O54: 0 | P54: 0 | Q54: 0 | R54: 0
M55: Dia 19 | N55: 3774.31 | O55: Fatura Cartão Nubank | P55: 0 | Q55: Dia 12 | R55: 0
M56: Dia 20 | N56: 4974.31 | O56: Pagamento Recebido Bellocopo | P56: 1200 | Q56: Dia 20 | R56: 0
M57: Dia 21 | N57: 4974.31 | O57: 0 | P57: 0 | Q57: 0 | R57: 0
M58: Dia 22 | N58: 4874.41 | O58: Internet Atranet | P58: -99.9 | Q58: Dia 20 | R58: 0
M59: Dia 23 | N59: 4863.42 | O59: PicsArt Photo | P59: -10.99 | Q59: Dia 21 | R59: 0
M60: Dia 24 | N60: 4863.42 | O60: 0 | P60: 0 | Q60: 0 | R60: 0
M61: Dia 25 | N61: 4743.42 | O61: Dízimo (2/2 parte) | P61: -120 | Q61: Dia 24 | R61: 0
M62: Dia 26 | N62: 4623.42 | O62: Energia Elétrica (1/4 pagamento) | P62: -120 | Q62: Dia 20 | R62: 0
M63: Dia 27 | N63: 4578.42 | O63: Internet Celular Vivo | P63: -45 | Q63: Dia 27 | R63: 0
M64: Dia 28 | N64: 4450.92 | O64: Cílios | P64: -127.5 | Q64: Dia 28 | R64: 0
M65: Dia 29 | N65: 4433.47 | O65: HBO | P65: -17.45 | Q65: Dia 29 | R65: 0
M66: Dia 30 | N66: 4433.47 | O66: 0 | P66: 0 | Q66: 0 | R66: 0
M67: Dia 31 | N67: 4433.47 | O67: 0 | P67: 0 | Q67: 0 | R67: 0

Sheet Fevereiro 2025
A1: Planejamento Mensal Káic e Gabi | I1: Mês: | J1: 45689 | M1: Resumo Finalização do Mês | S1: 0
A2: Data hoje formula | B2: Data formula | C2: Formula pgto ok | G2: Saldo Prévio | H2: Descrição Conta | I2: Valor | J2: Data vencimento | K2: Pago? | M2: =F33 -> Dia 31 | N2: =G33 -> 5977.77 | O2: Valor sobra dia 31 - Final do mês
A3: =TODAY() -> 45567 | B3: 45689 | C3: =A3-B3 -> -122 | D3: =C3+K3 -> -122 | E3: =IF(10,K3="ok",0) -> FALSE | F3: Dia 1 | G3: ='Janeiro 2025'!G33+'Fevereiro 2025'!I3 -> 4433.47 | L3: =IF(A3=B3,"➜ Hoje","")
A4: =TODAY() -> 45567 | B4: =B3+1 -> 45690 | C4: =A4-B4 -> -123 | D4: =C4+K4 -> -123 | E4: =IF(10,K4="ok",0) -> FALSE | F4: Dia 2 | G4: =G3+I4 -> 4405.48 | H4: Nível 6 Mercado Livre - Automatico | I4: -27.99 | J4: Dia 1 | L4: =IF(A4=B4,"➜ Hoje","") | M4: 0.2 | N4: =IF($N$2*M4<=0,"Em vermelho",$N$2*M4) -> 1195.554 | O4: Comemoraçao dia 20
A5: =TODAY() -> 45567 | B5: =B4+1 -> 45691 | C5: =A5-B5 -> -124 | D5: =C5+K5 -> -124 | E5: =IF(10,K5="ok",0) -> FALSE | F5: Dia 3 | G5: =G4+I5 -> 4405.48 | L5: =IF(A5=B5,"➜ Hoje","") | M5: 0.1 | N5: =IF($N$2*M5<=0,"Em vermelho",$N$2*M5) -> 597.777 | O5: Reforma Casa
A6: =TODAY() -> 45567 | B6: =B5+1 -> 45692 | C6: =A6-B6 -> -125 | D6: =C6+K6 -> -125 | E6: =IF(10,K6="ok",0) -> FALSE | F6: Dia 4 | G6: =G5+I6 -> 4370.48 | H6: Granulado Madeira (10kg) | I6: -35 | J6: Dia 5 | L6: =IF(A6=B6,"➜ Hoje","") | M6: 0.4 | N6: =IF($N$2*M6<=0,"Em vermelho",$N$2*M6) -> 2391.108 | O6: Tirar Carta A+B
A7: =TODAY() -> 45567 | B7: =B6+1 -> 45693 | C7: =A7-B7 -> -126 | D7: =C7+K7 -> -126 | E7: =IF(10,K7="ok",0) -> FALSE | F7: Dia 5 | G7: =G6+I7 -> 5770.48 | H7: Pagamento Recebido Bellocopo | I7: 1400 | J7: Dia 5 | L7: =IF(A7=B7,"➜ Hoje","") | M7: 0.3 | N7: =IF($N$2*M7<=0,"Em vermelho",$N$2*M7) -> 1793.331 | O7: Novas Alianças
A8: =TODAY() -> 45567 | B8: =B7+1 -> 45694 | C8: =A8-B8 -> -127 | D8: =C8+K8 -> -127 | E8: =IF(10,K8="ok",0) -> FALSE | F8: Dia 6 | G8: =G7+I8 -> 5730.78 | H8: Fatura Cartão Mercado Livre | I8: -39.7 | J8: Dia 5 | L8: =IF(A8=B8,"➜ Hoje","")
A9: =TODAY() -> 45567 | B9: =B8+1 -> 45695 | C9: =A9-B9 -> -128 | D9: =C9+K9 -> -128 | E9: =IF(10,K9="ok",0) -> FALSE | F9: Dia 7 | G9: =G8+I9 -> 5730.78 | J9: Dia 6 | L9: =IF(A9=B9,"➜ Hoje","") | M9: Planejamento Aquisições / Projetos
A10: =TODAY() -> 45567 | B10: =B9+1 -> 45696 | C10: =A10-B10 -> -129 | D10: =C10+K10 -> -129 | E10: =IF(10,K10="ok",0) -> FALSE | F10: Dia 8 | G10: =G9+I10 -> 5572.78 | H10: Ração Gatos Golden Castrados | I10: -158 | J10: Dia 6 | L10: =IF(A10=B10,"➜ Hoje","")
A11: =TODAY() -> 45567 | B11: =B10+1 -> 45697 | C11: =A11-B11 -> -130 | D11: =C11+K11 -> -130 | E11: =IF(10,K11="ok",0) -> FALSE | F11: Dia 9 | G11: =G10+I11 -> 5533.78 | H11: Microsoft | I11: -39 | J11: Dia 6 | L11: =IF(A11=B11,"➜ Hoje","") | M11: Data | N11: Valor média | O11: Descrição
A12: =TODAY() -> 45567 | B12: =B11+1 -> 45698 | C12: =A12-B12 -> -131 | D12: =C12+K12 -> -131 | E12: =IF(10,K12="ok",0) -> FALSE | F12: Dia 10 | G12: =G11+I12 -> 5533.78 | L12: =IF(A12=B12,"➜ Hoje","") | M12: 45046 | N12: 400 | O12: Depurador de ar (Reforma Cozinha)
A13: =TODAY() -> 45567 | B13: =B12+1 -> 45699 | C13: =A13-B13 -> -132 | D13: =C13+K13 -> -132 | E13: =IF(10,K13="ok",0) -> FALSE | F13: Dia 11 | G13: =G12+I13 -> 5533.78 | L13: =IF(A13=B13,"➜ Hoje","") | M13: 44540 | N13: 300 | O13: Revestimento Lume 45x90 Botanico Branco Retif.Azulejo (Reforma Cozinha)
A14: =TODAY() -> 45567 | B14: =B13+1 -> 45700 | C14: =A14-B14 -> -133 | D14: =C14+K14 -> -133 | E14: =IF(10,K14="ok",0) -> FALSE | F14: Dia 12 | G14: =G13+I14 -> 5502.88 | H14: Netflix - Automatico | I14: -30.9 | J14: Dia 9 | L14: =IF(A14=B14,"➜ Hoje","")
A15: =TODAY() -> 45567 | B15: =B14+1 -> 45701 | C15: =A15-B15 -> -134 | D15: =C15+K15 -> -134 | E15: =IF(10,K15="ok",0) -> FALSE | F15: Dia 13 | G15: =G14+I15 -> 5362.88 | H15: Dízimo (1/2 parte) | I15: -140 | J15: Dia 9 | L15: =IF(A15=B15,"➜ Hoje","")
A16: =TODAY() -> 45567 | B16: =B15+1 -> 45702 | C16: =A16-B16 -> -135 | D16: =C16+K16 -> -135 | E16: =IF(10,K16="ok",0) -> FALSE | F16: Dia 14 | G16: =G15+I16 -> 5335.1 | H16: Anticoncepcional | I16: -27.78 | J16: Dia 10 | L16: =IF(A16=B16,"➜ Hoje","")
A17: =TODAY() -> 45567 | B17: =B16+1 -> 45703 | C17: =A17-B17 -> -136 | D17: =C17+K17 -> -136 | E17: =IF(10,K17="ok",0) -> FALSE | F17: Dia 15 | G17: =G16+I17 -> 5318.61 | H17: SimplyPiano | I17: -16.49 | J17: Dia 12 | L17: =IF(A17=B17,"➜ Hoje","")
A18: =TODAY() -> 45567 | B18: =B17+1 -> 45704 | C18: =A18-B18 -> -137 | D18: =C18+K18 -> -137 | E18: =IF(10,K18="ok",0) -> FALSE | F18: Dia 16 | G18: =G17+I18 -> 5318.61 | L18: =IF(A18=B18,"➜ Hoje","") | M18: Planejamento Reposição Dispensa / Compras Mercado
A19: =TODAY() -> 45567 | B19: =B18+1 -> 45705 | C19: =A19-B19 -> -138 | D19: =C19+K19 -> -138 | E19: =IF(10,K19="ok",0) -> FALSE | F19: Dia 17 | G19: =G18+I19 -> 5318.61 | L19: =IF(A19=B19,"➜ Hoje","")
A20: =TODAY() -> 45567 | B20: =B19+1 -> 45706 | C20: =A20-B20 -> -139 | D20: =C20+K20 -> -139 | E20: =IF(10,K20="ok",0) -> FALSE | F20: Dia 18 | G20: =G19+I20 -> 5318.61 | L20: =IF(A20=B20,"➜ Hoje","") | M20: Dia 15 | N20: 210 | O20: Pagamento Recebido VA Bellocopo
A21: =TODAY() -> 45567 | B21: =B20+1 -> 45707 | C21: =A21-B21 -> -140 | D21: =C21+K21 -> -140 | E21: =IF(10,K21="ok",0) -> FALSE | F21: Dia 19 | G21: =G20+I21 -> 5318.61 | H21: Fatura Cartão Nubank | I21: 0 | J21: Dia 12 | L21: =IF(A21=B21,"➜ Hoje","")
A22: =TODAY() -> 45567 | B22: =B21+1 -> 45708 | C22: =A22-B22 -> -141 | D22: =C22+K22 -> -141 | E22: =IF(10,K22="ok",0) -> FALSE | F22: Dia 20 | G22: =G21+I22 -> 6518.61 | H22: Pagamento Recebido Bellocopo | I22: 1200 | J22: Dia 20 | L22: =IF(A22=B22,"➜ Hoje","") | M22: Planejamento Acerto de dividas - prorrogando para mês seguinte
A23: =TODAY() -> 45567 | B23: =B22+1 -> 45709 | C23: =A23-B23 -> -142 | D23: =C23+K23 -> -142 | E23: =IF(10,K23="ok",0) -> FALSE | F23: Dia 21 | G23: =G22+I23 -> 6518.61 | L23: =IF(A23=B23,"➜ Hoje","")
A24: =TODAY() -> 45567 | B24: =B23+1 -> 45710 | C24: =A24-B24 -> -143 | D24: =C24+K24 -> -143 | E24: =IF(10,K24="ok",0) -> FALSE | F24: Dia 22 | G24: =G23+I24 -> 6418.71 | H24: Internet Atranet | I24: -99.9 | J24: Dia 20 | L24: =IF(A24=B24,"➜ Hoje","")
A25: =TODAY() -> 45567 | B25: =B24+1 -> 45711 | C25: =A25-B25 -> -144 | D25: =C25+K25 -> -144 | E25: =IF(10,K25="ok",0) -> FALSE | F25: Dia 23 | G25: =G24+I25 -> 6407.72 | H25: PicsArt Photo | I25: -10.99 | J25: Dia 21 | L25: =IF(A25=B25,"➜ Hoje","")
A26: =TODAY() -> 45567 | B26: =B25+1 -> 45712 | C26: =A26-B26 -> -145 | D26: =C26+K26 -> -145 | E26: =IF(10,K26="ok",0) -> FALSE | F26: Dia 24 | G26: =G25+I26 -> 6407.72 | L26: =IF(A26=B26,"➜ Hoje","")
A27: =TODAY() -> 45567 | B27: =B26+1 -> 45713 | C27: =A27-B27 -> -146 | D27: =C27+K27 -> -146 | E27: =IF(10,K27="ok",0) -> FALSE | F27: Dia 25 | G27: =G26+I27 -> 6287.72 | H27: Dízimo (2/2 parte) | I27: -120 | J27: Dia 24 | L27: =IF(A27=B27,"➜ Hoje","")
A28: =TODAY() -> 45567 | B28: =B27+1 -> 45714 | C28: =A28-B28 -> -147 | D28: =C28+K28 -> -147 | E28: =IF(10,K28="ok",0) -> FALSE | F28: Dia 26 | G28: =G27+I28 -> 6167.72 | H28: Energia Elétrica (1/4 pagamento) | I28: -120 | J28: Dia 20 | L28: =IF(A28=B28,"➜ Hoje","")
A29: =TODAY() -> 45567 | B29: =B28+1 -> 45715 | C29: =A29-B29 -> -148 | D29: =C29+K29 -> -148 | E29: =IF(10,K29="ok",0) -> FALSE | F29: Dia 27 | G29: =G28+I29 -> 6122.72 | H29: Internet Celular Vivo | I29: -45 | J29: Dia 27 | L29: =IF(A29=B29,"➜ Hoje","")
A30: =TODAY() -> 45567 | B30: =B29+1 -> 45716 | C30: =A30-B30 -> -149 | D30: =C30+K30 -> -149 | E30: =IF(10,K30="ok",0) -> FALSE | F30: Dia 28 | G30: =G29+I30 -> 5995.22 | H30: Cílios | I30: -127.5 | J30: Dia 28 | L30: =IF(A30=B30,"➜ Hoje","") | M30: Prorrogar: | N30: =SUM(N24:N29) -> 0
A31: =TODAY() -> 45567 | B31: =B30+1 -> 45717 | C31: =A31-B31 -> -150 | D31: =C31+K31 -> -150 | E31: =IF(10,K31="ok",0) -> FALSE | F31: Dia 29 | G31: =G30+I31 -> 5977.77 | H31: HBO | I31: -17.45 | J31: Dia 29 | L31: =IF(A31=B31,"➜ Hoje","") | M31: =M2 -> Dia 31 | N31: =N2+N30 -> 5977.77 | O31: Valor sobra dia 31 - Final do mês
A32: =TODAY() -> 45567 | B32: =B31+1 -> 45718 | C32: =A32-B32 -> -151 | D32: =C32+K32 -> -151 | E32: =IF(10,K32="ok",0) -> FALSE | F32: Dia 30 | G32: =G31+I32 -> 5977.77 | L32: =IF(A32=B32,"➜ Hoje","") | N32: =N30*2 -> 0
A33: =TODAY() -> 45567 | B33: 45596 | C33: =A33-B33 -> -29 | D33: =C33+K33 -> -29 | E33: =IF(10,K33="ok",0) -> FALSE | F33: Dia 31 | G33: =G32+I33 -> 5977.77 | L33: =IF(A33=B33,"➜ Hoje","") | N33: =N30-N32 -> 0
M34: Pendencias para pagar
M36: {=F2:K33} -> 0 | N36: Saldo Prévio | O36: Descrição Conta | P36: Valor | Q36: Data vencimento | R36: Pago?
M37: Dia 1 | N37: 4433.47 | O37: 0 | P37: 0 | Q37: 0 | R37: 0
M38: Dia 2 | N38: 4405.48 | O38: Nível 6 Mercado Livre - Automatico | P38: -27.99 | Q38: Dia 1 | R38: 0
M39: Dia 3 | N39: 4405.48 | O39: 0 | P39: 0 | Q39: 0 | R39: 0
M40: Dia 4 | N40: 4370.48 | O40: Granulado Madeira (10kg) | P40: -35 | Q40: Dia 5 | R40: 0
M41: Dia 5 | N41: 5770.48 | O41: Pagamento Recebido Bellocopo | P41: 1400 | Q41: Dia 5 | R41: 0
M42: Dia 6 | N42: 5730.78 | O42: Fatura Cartão Mercado Livre | P42: -39.7 | Q42: Dia 5 | R42: 0
M43: Dia 7 | N43: 5730.78 | O43: 0 | P43: 0 | Q43: Dia 6 | R43: 0
M44: Dia 8 | N44: 5572.78 | O44: Ração Gatos Golden Castrados | P44: -158 | Q44: Dia 6 | R44: 0
M45: Dia 9 | N45: 5533.78 | O45: Microsoft | P45: -39 | Q45: Dia 6 | R45: 0
M46: Dia 10 | N46: 5533.78 | O46: 0 | P46: 0 | Q46: 0 | R46: 0
M47: Dia 11 | N47: 5533.78 | O47: 0 | P47: 0 | Q47: 0 | R47: 0
M48: Dia 12 | N48: 5502.88 | O48: Netflix - Automatico | P48: -30.9 | Q48: Dia 9 | R48: 0
M49: Dia 13 | N49: 5362.88 | O49: Dízimo (1/2 parte) | P49: -140 | Q49: Dia 9 | R49: 0
M50: Dia 14 | N50: 5335.1 | O50: Anticoncepcional | P50: -27.78 | Q50: Dia 10 | R50: 0
M51: Dia 15 | N51: 5318.61 | O51: SimplyPiano | P51: -16.49 | Q51: Dia 12 | R51: 0
M52: Dia 16 | N52: 5318.61 | O52: 0 | P52: 0 | Q52: 0 | R52: 0
M53: Dia 17 | N53: 5318.61 | O53: 0 | P53: 0 | Q53: 0 | R53: 0
M54: Dia 18 | N54: 5318.61 | O54: 0 | P54: 0 | Q54: 0 | R54: 0
M55: Dia 19 | N55: 5318.61 | O55: Fatura Cartão Nubank | P55: 0 | Q55: Dia 12 | R55: 0
M56: Dia 20 | N56: 6518.61 | O56: Pagamento Recebido Bellocopo | P56: 1200 | Q56: Dia 20 | R56: 0
M57: Dia 21 | N57: 6518.61 | O57: 0 | P57: 0 | Q57: 0 | R57: 0
M58: Dia 22 | N58: 6418.71 | O58: Internet Atranet | P58: -99.9 | Q58: Dia 20 | R58: 0
M59: Dia 23 | N59: 6407.72 | O59: PicsArt Photo | P59: -10.99 | Q59: Dia 21 | R59: 0
M60: Dia 24 | N60: 6407.72 | O60: 0 | P60: 0 | Q60: 0 | R60: 0
M61: Dia 25 | N61: 6287.72 | O61: Dízimo (2/2 parte) | P61: -120 | Q61: Dia 24 | R61: 0
M62: Dia 26 | N62: 6167.72 | O62: Energia Elétrica (1/4 pagamento) | P62: -120 | Q62: Dia 20 | R62: 0
M63: Dia 27 | N63: 6122.72 | O63: Internet Celular Vivo | P63: -45 | Q63: Dia 27 | R63: 0
M64: Dia 28 | N64: 5995.22 | O64: Cílios | P64: -127.5 | Q64: Dia 28 | R64: 0
M65: Dia 29 | N65: 5977.77 | O65: HBO | P65: -17.45 | Q65: Dia 29 | R65: 0
M66: Dia 30 | N66: 5977.77 | O66: 0 | P66: 0 | Q66: 0 | R66: 0
M67: Dia 31 | N67: 5977.77 | O67: 0 | P67: 0 | Q67: 0 | R67: 0

Sheet Março 2025
A1: Planejamento Mensal Káic e Gabi | I1: Mês: | J1: 45717 | M1: Resumo Finalização do Mês | S1: 0
A2: Data hoje formula | B2: Data formula | C2: Formula pgto ok | G2: Saldo Prévio | H2: Descrição Conta | I2: Valor | J2: Data vencimento | K2: Pago? | M2: =F33 -> Dia 31 | N2: =G33 -> 7522.07 | O2: Valor sobra dia 31 - Final do mês
A3: =TODAY() -> 45567 | B3: 45717 | C3: =A3-B3 -> -150 | D3: =C3+K3 -> -150 | E3: =IF(10,K3="ok",0) -> FALSE | F3: Dia 1 | G3: ='Fevereiro 2025'!G33+'Março 2025'!I3 -> 5977.77 | L3: =IF(A3=B3,"➜ Hoje","")
A4: =TODAY() -> 45567 | B4: =B3+1 -> 45718 | C4: =A4-B4 -> -151 | D4: =C4+K4 -> -151 | E4: =IF(10,K4="ok",0) -> FALSE | F4: Dia 2 | G4: =G3+I4 -> 5949.78 | H4: Nível 6 Mercado Livre - Automatico | I4: -27.99 | J4: Dia 1 | L4: =IF(A4=B4,"➜ Hoje","") | M4: 0.2 | N4: =IF($N$2*M4<=0,"Em vermelho",$N$2*M4) -> 1504.414 | O4: Comemoraçao dia 20
A5: =TODAY() -> 45567 | B5: =B4+1 -> 45719 | C5: =A5-B5 -> -152 | D5: =C5+K5 -> -152 | E5: =IF(10,K5="ok",0) -> FALSE | F5: Dia 3 | G5: =G4+I5 -> 5949.78 | L5: =IF(A5=B5,"➜ Hoje","") | M5: 0.1 | N5: =IF($N$2*M5<=0,"Em vermelho",$N$2*M5) -> 752.207 | O5: Reforma Casa
A6: =TODAY() -> 45567 | B6: =B5+1 -> 45720 | C6: =A6-B6 -> -153 | D6: =C6+K6 -> -153 | E6: =IF(10,K6="ok",0) -> FALSE | F6: Dia 4 | G6: =G5+I6 -> 5914.78 | H6: Granulado Madeira (10kg) | I6: -35 | J6: Dia 5 | L6: =IF(A6=B6,"➜ Hoje","") | M6: 0.4 | N6: =IF($N$2*M6<=0,"Em vermelho",$N$2*M6) -> 3008.828 | O6: Tirar Carta A+B
A7: =TODAY() -> 45567 | B7: =B6+1 -> 45721 | C7: =A7-B7 -> -154 | D7: =C7+K7 -> -154 | E7: =IF(10,K7="ok",0) -> FALSE | F7: Dia 5 | G7: =G6+I7 -> 7314.78 | H7: Pagamento Recebido Bellocopo | I7: 1400 | J7: Dia 5 | L7: =IF(A7=B7,"➜ Hoje","") | M7: 0.3 | N7: =IF($N$2*M7<=0,"Em vermelho",$N$2*M7) -> 2256.621 | O7: Novas Alianças
A8: =TODAY() -> 45567 | B8: =B7+1 -> 45722 | C8: =A8-B8 -> -155 | D8: =C8+K8 -> -155 | E8: =IF(10,K8="ok",0) -> FALSE | F8: Dia 6 | G8: =G7+I8 -> 7275.08 | H8: Fatura Cartão Mercado Livre | I8: -39.7 | J8: Dia 5 | L8: =IF(A8=B8,"➜ Hoje","")
A9: =TODAY() -> 45567 | B9: =B8+1 -> 45723 | C9: =A9-B9 -> -156 | D9: =C9+K9 -> -156 | E9: =IF(10,K9="ok",0) -> FALSE | F9: Dia 7 | G9: =G8+I9 -> 7275.08 | J9: Dia 6 | L9: =IF(A9=B9,"➜ Hoje","") | M9: Planejamento Aquisições / Projetos
A10: =TODAY() -> 45567 | B10: =B9+1 -> 45724 | C10: =A10-B10 -> -157 | D10: =C10+K10 -> -157 | E10: =IF(10,K10="ok",0) -> FALSE | F10: Dia 8 | G10: =G9+I10 -> 7117.08 | H10: Ração Gatos Golden Castrados | I10: -158 | J10: Dia 6 | L10: =IF(A10=B10,"➜ Hoje","")
A11: =TODAY() -> 45567 | B11: =B10+1 -> 45725 | C11: =A11-B11 -> -158 | D11: =C11+K11 -> -158 | E11: =IF(10,K11="ok",0) -> FALSE | F11: Dia 9 | G11: =G10+I11 -> 7078.08 | H11: Microsoft | I11: -39 | J11: Dia 6 | L11: =IF(A11=B11,"➜ Hoje","") | M11: Data | N11: Valor média | O11: Descrição
A12: =TODAY() -> 45567 | B12: =B11+1 -> 45726 | C12: =A12-B12 -> -159 | D12: =C12+K12 -> -159 | E12: =IF(10,K12="ok",0) -> FALSE | F12: Dia 10 | G12: =G11+I12 -> 7078.08 | L12: =IF(A12=B12,"➜ Hoje","") | M12: 45046 | N12: 400 | O12: Depurador de ar (Reforma Cozinha)
A13: =TODAY() -> 45567 | B13: =B12+1 -> 45727 | C13: =A13-B13 -> -160 | D13: =C13+K13 -> -160 | E13: =IF(10,K13="ok",0) -> FALSE | F13: Dia 11 | G13: =G12+I13 -> 7078.08 | L13: =IF(A13=B13,"➜ Hoje","") | M13: 44540 | N13: 300 | O13: Revestimento Lume 45x90 Botanico Branco Retif.Azulejo (Reforma Cozinha)
A14: =TODAY() -> 45567 | B14: =B13+1 -> 45728 | C14: =A14-B14 -> -161 | D14: =C14+K14 -> -161 | E14: =IF(10,K14="ok",0) -> FALSE | F14: Dia 12 | G14: =G13+I14 -> 7047.18 | H14: Netflix - Automatico | I14: -30.9 | J14: Dia 9 | L14: =IF(A14=B14,"➜ Hoje","")
A15: =TODAY() -> 45567 | B15: =B14+1 -> 45729 | C15: =A15-B15 -> -162 | D15: =C15+K15 -> -162 | E15: =IF(10,K15="ok",0) -> FALSE | F15: Dia 13 | G15: =G14+I15 -> 6907.18 | H15: Dízimo (1/2 parte) | I15: -140 | J15: Dia 9 | L15: =IF(A15=B15,"➜ Hoje","")
A16: =TODAY() -> 45567 | B16: =B15+1 -> 45730 | C16: =A16-B16 -> -163 | D16: =C16+K16 -> -163 | E16: =IF(10,K16="ok",0) -> FALSE | F16: Dia 14 | G16: =G15+I16 -> 6879.4 | H16: Anticoncepcional | I16: -27.78 | J16: Dia 10 | L16: =IF(A16=B16,"➜ Hoje","")
A17: =TODAY() -> 45567 | B17: =B16+1 -> 45731 | C17: =A17-B17 -> -164 | D17: =C17+K17 -> -164 | E17: =IF(10,K17="ok",0) -> FALSE | F17: Dia 15 | G17: =G16+I17 -> 6862.91 | H17: SimplyPiano | I17: -16.49 | J17: Dia 12 | L17: =IF(A17=B17,"➜ Hoje","")
A18: =TODAY() -> 45567 | B18: =B17+1 -> 45732 | C18: =A18-B18 -> -165 | D18: =C18+K18 -> -165 | E18: =IF(10,K18="ok",0) -> FALSE | F18: Dia 16 | G18: =G17+I18 -> 6862.91 | L18: =IF(A18=B18,"➜ Hoje","") | M18: Planejamento Reposição Dispensa / Compras Mercado
A19: =TODAY() -> 45567 | B19: =B18+1 -> 45733 | C19: =A19-B19 -> -166 | D19: =C19+K19 -> -166 | E19: =IF(10,K19="ok",0) -> FALSE | F19: Dia 17 | G19: =G18+I19 -> 6862.91 | L19: =IF(A19=B19,"➜ Hoje","")
A20: =TODAY() -> 45567 | B20: =B19+1 -> 45734 | C20: =A20-B20 -> -167 | D20: =C20+K20 -> -167 | E20: =IF(10,K20="ok",0) -> FALSE | F20: Dia 18 | G20: =G19+I20 -> 6862.91 | L20: =IF(A20=B20,"➜ Hoje","") | M20: Dia 15 | N20: 210 | O20: Pagamento Recebido VA Bellocopo
A21: =TODAY() -> 45567 | B21: =B20+1 -> 45735 | C21: =A21-B21 -> -168 | D21: =C21+K21 -> -168 | E21: =IF(10,K21="ok",0) -> FALSE | F21: Dia 19 | G21: =G20+I21 -> 6862.91 | H21: Fatura Cartão Nubank | I21: 0 | J21: Dia 12 | L21: =IF(A21=B21,"➜ Hoje","")
A22: =TODAY() -> 45567 | B22: =B21+1 -> 45736 | C22: =A22-B22 -> -169 | D22: =C22+K22 -> -169 | E22: =IF(10,K22="ok",0) -> FALSE | F22: Dia 20 | G22: =G21+I22 -> 8062.91 | H22: Pagamento Recebido Bellocopo | I22: 1200 | J22: Dia 20 | L22: =IF(A22=B22,"➜ Hoje","") | M22: Planejamento Acerto de dividas - prorrogando para mês seguinte
A23: =TODAY() -> 45567 | B23: =B22+1 -> 45737 | C23: =A23-B23 -> -170 | D23: =C23+K23 -> -170 | E23: =IF(10,K23="ok",0) -> FALSE | F23: Dia 21 | G23: =G22+I23 -> 8062.91 | L23: =IF(A23=B23,"➜ Hoje","")
A24: =TODAY() -> 45567 | B24: =B23+1 -> 45738 | C24: =A24-B24 -> -171 | D24: =C24+K24 -> -171 | E24: =IF(10,K24="ok",0) -> FALSE | F24: Dia 22 | G24: =G23+I24 -> 7963.01 | H24: Internet Atranet | I24: -99.9 | J24: Dia 20 | L24: =IF(A24=B24,"➜ Hoje","")
A25: =TODAY() -> 45567 | B25: =B24+1 -> 45739 | C25: =A25-B25 -> -172 | D25: =C25+K25 -> -172 | E25: =IF(10,K25="ok",0) -> FALSE | F25: Dia 23 | G25: =G24+I25 -> 7952.02 | H25: PicsArt Photo | I25: -10.99 | J25: Dia 21 | L25: =IF(A25=B25,"➜ Hoje","")
A26: =TODAY() -> 45567 | B26: =B25+1 -> 45740 | C26: =A26-B26 -> -173 | D26: =C26+K26 -> -173 | E26: =IF(10,K26="ok",0) -> FALSE | F26: Dia 24 | G26: =G25+I26 -> 7952.02 | L26: =IF(A26=B26,"➜ Hoje","")
A27: =TODAY() -> 45567 | B27: =B26+1 -> 45741 | C27: =A27-B27 -> -174 | D27: =C27+K27 -> -174 | E27: =IF(10,K27="ok",0) -> FALSE | F27: Dia 25 | G27: =G26+I27 -> 7832.02 | H27: Dízimo (2/2 parte) | I27: -120 | J27: Dia 24 | L27: =IF(A27=B27,"➜ Hoje","")
A28: =TODAY() -> 45567 | B28: =B27+1 -> 45742 | C28: =A28-B28 -> -175 | D28: =C28+K28 -> -175 | E28: =IF(10,K28="ok",0) -> FALSE | F28: Dia 26 | G28: =G27+I28 -> 7712.02 | H28: Energia Elétrica (1/4 pagamento) | I28: -120 | J28: Dia 20 | L28: =IF(A28=B28,"➜ Hoje","")
A29: =TODAY() -> 45567 | B29: =B28+1 -> 45743 | C29: =A29-B29 -> -176 | D29: =C29+K29 -> -176 | E29: =IF(10,K29="ok",0) -> FALSE | F29: Dia 27 | G29: =G28+I29 -> 7667.02 | H29: Internet Celular Vivo | I29: -45 | J29: Dia 27 | L29: =IF(A29=B29,"➜ Hoje","")
A30: =TODAY() -> 45567 | B30: =B29+1 -> 45744 | C30: =A30-B30 -> -177 | D30: =C30+K30 -> -177 | E30: =IF(10,K30="ok",0) -> FALSE | F30: Dia 28 | G30: =G29+I30 -> 7539.52 | H30: Cílios | I30: -127.5 | J30: Dia 28 | L30: =IF(A30=B30,"➜ Hoje","") | M30: Prorrogar: | N30: =SUM(N24:N29) -> 0
A31: =TODAY() -> 45567 | B31: =B30+1 -> 45745 | C31: =A31-B31 -> -178 | D31: =C31+K31 -> -178 | E31: =IF(10,K31="ok",0) -> FALSE | F31: Dia 29 | G31: =G30+I31 -> 7522.07 | H31: HBO | I31: -17.45 | J31: Dia 29 | L31: =IF(A31=B31,"➜ Hoje","") | M31: =M2 -> Dia 31 | N31: =N2+N30 -> 7522.07 | O31: Valor sobra dia 31 - Final do mês
A32: =TODAY() -> 45567 | B32: =B31+1 -> 45746 | C32: =A32-B32 -> -179 | D32: =C32+K32 -> -179 | E32: =IF(10,K32="ok",0) -> FALSE | F32: Dia 30 | G32: =G31+I32 -> 7522.07 | L32: =IF(A32=B32,"➜ Hoje","") | N32: =N30*2 -> 0
A33: =TODAY() -> 45567 | B33: 45596 | C33: =A33-B33 -> -29 | D33: =C33+K33 -> -29 | E33: =IF(10,K33="ok",0) -> FALSE | F33: Dia 31 | G33: =G32+I33 -> 7522.07 | L33: =IF(A33=B33,"➜ Hoje","") | N33: =N30-N32 -> 0
M34: Pendencias para pagar
M36: {=F2:K33} -> 0 | N36: Saldo Prévio | O36: Descrição Conta | P36: Valor | Q36: Data vencimento | R36: Pago?
M37: Dia 1 | N37: 5977.77 | O37: 0 | P37: 0 | Q37: 0 | R37: 0
M38: Dia 2 | N38: 5949.78 | O38: Nível 6 Mercado Livre - Automatico | P38: -27.99 | Q38: Dia 1 | R38: 0
M39: Dia 3 | N39: 5949.78 | O39: 0 | P39: 0 | Q39: 0 | R39: 0
M40: Dia 4 | N40: 5914.78 | O40: Granulado Madeira (10kg) | P40: -35 | Q40: Dia 5 | R40: 0
M41: Dia 5 | N41: 7314.78 | O41: Pagamento Recebido Bellocopo | P41: 1400 | Q41: Dia 5 | R41: 0
M42: Dia 6 | N42: 7275.08 | O42: Fatura Cartão Mercado Livre | P42: -39.7 | Q42: Dia 5 | R42: 0
M43: Dia 7 | N43: 7275.08 | O43: 0 | P43: 0 | Q43: Dia 6 | R43: 0
M44: Dia 8 | N44: 7117.08 | O44: Ração Gatos Golden Castrados | P44: -158 | Q44: Dia 6 | R44: 0
M45: Dia 9 | N45: 7078.08 | O45: Microsoft | P45: -39 | Q45: Dia 6 | R45: 0
M46: Dia 10 | N46: 7078.08 | O46: 0 | P46: 0 | Q46: 0 | R46: 0
M47: Dia 11 | N47: 7078.08 | O47: 0 | P47: 0 | Q47: 0 | R47: 0
M48: Dia 12 | N48: 7047.18 | O48: Netflix - Automatico | P48: -30.9 | Q48: Dia 9 | R48: 0
M49: Dia 13 | N49: 6907.18 | O49: Dízimo (1/2 parte) | P49: -140 | Q49: Dia 9 | R49: 0
M50: Dia 14 | N50: 6879.4 | O50: Anticoncepcional | P50: -27.78 | Q50: Dia 10 | R50: 0
M51: Dia 15 | N51: 6862.91 | O51: SimplyPiano | P51: -16.49 | Q51: Dia 12 | R51: 0
M52: Dia 16 | N52: 6862.91 | O52: 0 | P52: 0 | Q52: 0 | R52: 0
M53: Dia 17 | N53: 6862.91 | O53: 0 | P53: 0 | Q53: 0 | R53: 0
M54: Dia 18 | N54: 6862.91 | O54: 0 | P54: 0 | Q54: 0 | R54: 0
M55: Dia 19 | N55: 6862.91 | O55: Fatura Cartão Nubank | P55: 0 | Q55: Dia 12 | R55: 0
M56: Dia 20 | N56: 8062.91 | O56: Pagamento Recebido Bellocopo | P56: 1200 | Q56: Dia 20 | R56: 0
M57: Dia 21 | N57: 8062.91 | O57: 0 | P57: 0 | Q57: 0 | R57: 0
M58: Dia 22 | N58: 7963.01 | O58: Internet Atranet | P58: -99.9 | Q58: Dia 20 | R58: 0
M59: Dia 23 | N59: 7952.02 | O59: PicsArt Photo | P59: -10.99 | Q59: Dia 21 | R59: 0
M60: Dia 24 | N60: 7952.02 | O60: 0 | P60: 0 | Q60: 0 | R60: 0
M61: Dia 25 | N61: 7832.02 | O61: Dízimo (2/2 parte) | P61: -120 | Q61: Dia 24 | R61: 0
M62: Dia 26 | N62: 7712.02 | O62: Energia Elétrica (1/4 pagamento) | P62: -120 | Q62: Dia 20 | R62: 0
M63: Dia 27 | N63: 7667.02 | O63: Internet Celular Vivo | P63: -45 | Q63: Dia 27 | R63: 0
M64: Dia 28 | N64: 7539.52 | O64: Cílios | P64: -127.5 | Q64: Dia 28 | R64: 0
M65: Dia 29 | N65: 7522.07 | O65: HBO | P65: -17.45 | Q65: Dia 29 | R65: 0
M66: Dia 30 | N66: 7522.07 | O66: 0 | P66: 0 | Q66: 0 | R66: 0
M67: Dia 31 | N67: 7522.07 | O67: 0 | P67: 0 | Q67: 0 | R67: 0

Sheet Abril 2025
A1: Planejamento Mensal Káic e Gabi | I1: Mês: | J1: =B3 -> 45748 | M1: Resumo Finalização do Mês | S1: 0
A2: Data hoje formula | B2: Data formula | C2: Formula pgto ok | G2: Saldo Prévio | H2: Descrição Conta | I2: Valor | J2: Data vencimento | K2: Pago? | M2: =F33 -> Dia 31 | N2: =G33 -> 9066.37 | O2: Valor sobra dia 31 - Final do mês
A3: =TODAY() -> 45567 | B3: 45748 | C3: =A3-B3 -> -181 | D3: =C3+K3 -> -181 | E3: =IF(10,K3="ok",0) -> FALSE | F3: Dia 1 | G3: ='Março 2025'!G33+'Abril 2025'!I3 -> 7522.07 | L3: =IF(A3=B3,"➜ Hoje","")
A4: =TODAY() -> 45567 | B4: =B3+1 -> 45749 | C4: =A4-B4 -> -182 | D4: =C4+K4 -> -182 | E4: =IF(10,K4="ok",0) -> FALSE | F4: Dia 2 | G4: =G3+I4 -> 7494.08 | H4: Nível 6 Mercado Livre - Automatico | I4: -27.99 | J4: Dia 1 | L4: =IF(A4=B4,"➜ Hoje","") | M4: 0.2 | N4: =IF($N$2*M4<=0,"Em vermelho",$N$2*M4) -> 1813.274 | O4: Comemoraçao dia 20
A5: =TODAY() -> 45567 | B5: =B4+1 -> 45750 | C5: =A5-B5 -> -183 | D5: =C5+K5 -> -183 | E5: =IF(10,K5="ok",0) -> FALSE | F5: Dia 3 | G5: =G4+I5 -> 7494.08 | L5: =IF(A5=B5,"➜ Hoje","") | M5: 0.1 | N5: =IF($N$2*M5<=0,"Em vermelho",$N$2*M5) -> 906.637 | O5: Reforma Casa
A6: =TODAY() -> 45567 | B6: =B5+1 -> 45751 | C6: =A6-B6 -> -184 | D6: =C6+K6 -> -184 | E6: =IF(10,K6="ok",0) -> FALSE | F6: Dia 4 | G6: =G5+I6 -> 7459.08 | H6: Granulado Madeira (10kg) | I6: -35 | J6: Dia 5 | L6: =IF(A6=B6,"➜ Hoje","") | M6: 0.4 | N6: =IF($N$2*M6<=0,"Em vermelho",$N$2*M6) -> 3626.548 | O6: Tirar Carta A+B
A7: =TODAY() -> 45567 | B7: =B6+1 -> 45752 | C7: =A7-B7 -> -185 | D7: =C7+K7 -> -185 | E7: =IF(10,K7="ok",0) -> FALSE | F7: Dia 5 | G7: =G6+I7 -> 8859.08 | H7: Pagamento Recebido Bellocopo | I7: 1400 | J7: Dia 5 | L7: =IF(A7=B7,"➜ Hoje","") | M7: 0.3 | N7: =IF($N$2*M7<=0,"Em vermelho",$N$2*M7) -> 2719.911 | O7: Novas Alianças
A8: =TODAY() -> 45567 | B8: =B7+1 -> 45753 | C8: =A8-B8 -> -186 | D8: =C8+K8 -> -186 | E8: =IF(10,K8="ok",0) -> FALSE | F8: Dia 6 | G8: =G7+I8 -> 8819.38 | H8: Fatura Cartão Mercado Livre | I8: -39.7 | J8: Dia 5 | L8: =IF(A8=B8,"➜ Hoje","")
A9: =TODAY() -> 45567 | B9: =B8+1 -> 45754 | C9: =A9-B9 -> -187 | D9: =C9+K9 -> -187 | E9: =IF(10,K9="ok",0) -> FALSE | F9: Dia 7 | G9: =G8+I9 -> 8819.38 | J9: Dia 6 | L9: =IF(A9=B9,"➜ Hoje","") | M9: Planejamento Aquisições / Projetos
A10: =TODAY() -> 45567 | B10: =B9+1 -> 45755 | C10: =A10-B10 -> -188 | D10: =C10+K10 -> -188 | E10: =IF(10,K10="ok",0) -> FALSE | F10: Dia 8 | G10: =G9+I10 -> 8661.38 | H10: Ração Gatos Golden Castrados | I10: -158 | J10: Dia 6 | L10: =IF(A10=B10,"➜ Hoje","")
A11: =TODAY() -> 45567 | B11: =B10+1 -> 45756 | C11: =A11-B11 -> -189 | D11: =C11+K11 -> -189 | E11: =IF(10,K11="ok",0) -> FALSE | F11: Dia 9 | G11: =G10+I11 -> 8622.38 | H11: Microsoft | I11: -39 | J11: Dia 6 | L11: =IF(A11=B11,"➜ Hoje","") | M11: Data | N11: Valor média | O11: Descrição
A12: =TODAY() -> 45567 | B12: =B11+1 -> 45757 | C12: =A12-B12 -> -190 | D12: =C12+K12 -> -190 | E12: =IF(10,K12="ok",0) -> FALSE | F12: Dia 10 | G12: =G11+I12 -> 8622.38 | L12: =IF(A12=B12,"➜ Hoje","") | M12: 45046 | N12: 400 | O12: Depurador de ar (Reforma Cozinha)
A13: =TODAY() -> 45567 | B13: =B12+1 -> 45758 | C13: =A13-B13 -> -191 | D13: =C13+K13 -> -191 | E13: =IF(10,K13="ok",0) -> FALSE | F13: Dia 11 | G13: =G12+I13 -> 8622.38 | L13: =IF(A13=B13,"➜ Hoje","") | M13: 44540 | N13: 300 | O13: Revestimento Lume 45x90 Botanico Branco Retif.Azulejo (Reforma Cozinha)
A14: =TODAY() -> 45567 | B14: =B13+1 -> 45759 | C14: =A14-B14 -> -192 | D14: =C14+K14 -> -192 | E14: =IF(10,K14="ok",0) -> FALSE | F14: Dia 12 | G14: =G13+I14 -> 8591.48 | H14: Netflix - Automatico | I14: -30.9 | J14: Dia 9 | L14: =IF(A14=B14,"➜ Hoje","")
A15: =TODAY() -> 45567 | B15: =B14+1 -> 45760 | C15: =A15-B15 -> -193 | D15: =C15+K15 -> -193 | E15: =IF(10,K15="ok",0) -> FALSE | F15: Dia 13 | G15: =G14+I15 -> 8451.48 | H15: Dízimo (1/2 parte) | I15: -140 | J15: Dia 9 | L15: =IF(A15=B15,"➜ Hoje","")
A16: =TODAY() -> 45567 | B16: =B15+1 -> 45761 | C16: =A16-B16 -> -194 | D16: =C16+K16 -> -194 | E16: =IF(10,K16="ok",0) -> FALSE | F16: Dia 14 | G16: =G15+I16 -> 8423.7 | H16: Anticoncepcional | I16: -27.78 | J16: Dia 10 | L16: =IF(A16=B16,"➜ Hoje","")
A17: =TODAY() -> 45567 | B17: =B16+1 -> 45762 | C17: =A17-B17 -> -195 | D17: =C17+K17 -> -195 | E17: =IF(10,K17="ok",0) -> FALSE | F17: Dia 15 | G17: =G16+I17 -> 8407.21 | H17: SimplyPiano | I17: -16.49 | J17: Dia 12 | L17: =IF(A17=B17,"➜ Hoje","")
A18: =TODAY() -> 45567 | B18: =B17+1 -> 45763 | C18: =A18-B18 -> -196 | D18: =C18+K18 -> -196 | E18: =IF(10,K18="ok",0) -> FALSE | F18: Dia 16 | G18: =G17+I18 -> 8407.21 | L18: =IF(A18=B18,"➜ Hoje","") | M18: Planejamento Reposição Dispensa / Compras Mercado
A19: =TODAY() -> 45567 | B19: =B18+1 -> 45764 | C19: =A19-B19 -> -197 | D19: =C19+K19 -> -197 | E19: =IF(10,K19="ok",0) -> FALSE | F19: Dia 17 | G19: =G18+I19 -> 8407.21 | L19: =IF(A19=B19,"➜ Hoje","")
A20: =TODAY() -> 45567 | B20: =B19+1 -> 45765 | C20: =A20-B20 -> -198 | D20: =C20+K20 -> -198 | E20: =IF(10,K20="ok",0) -> FALSE | F20: Dia 18 | G20: =G19+I20 -> 8407.21 | L20: =IF(A20=B20,"➜ Hoje","") | M20: Dia 15 | N20: 210 | O20: Pagamento Recebido VA Bellocopo
A21: =TODAY() -> 45567 | B21: =B20+1 -> 45766 | C21: =A21-B21 -> -199 | D21: =C21+K21 -> -199 | E21: =IF(10,K21="ok",0) -> FALSE | F21: Dia 19 | G21: =G20+I21 -> 8407.21 | H21: Fatura Cartão Nubank | I21: 0 | J21: Dia 12 | L21: =IF(A21=B21,"➜ Hoje","")
A22: =TODAY() -> 45567 | B22: =B21+1 -> 45767 | C22: =A22-B22 -> -200 | D22: =C22+K22 -> -200 | E22: =IF(10,K22="ok",0) -> FALSE | F22: Dia 20 | G22: =G21+I22 -> 9607.21 | H22: Pagamento Recebido Bellocopo | I22: 1200 | J22: Dia 20 | L22: =IF(A22=B22,"➜ Hoje","") | M22: Planejamento Acerto de dividas - prorrogando para mês seguinte
A23: =TODAY() -> 45567 | B23: =B22+1 -> 45768 | C23: =A23-B23 -> -201 | D23: =C23+K23 -> -201 | E23: =IF(10,K23="ok",0) -> FALSE | F23: Dia 21 | G23: =G22+I23 -> 9607.21 | L23: =IF(A23=B23,"➜ Hoje","")
A24: =TODAY() -> 45567 | B24: =B23+1 -> 45769 | C24: =A24-B24 -> -202 | D24: =C24+K24 -> -202 | E24: =IF(10,K24="ok",0) -> FALSE | F24: Dia 22 | G24: =G23+I24 -> 9507.31 | H24: Internet Atranet | I24: -99.9 | J24: Dia 20 | L24: =IF(A24=B24,"➜ Hoje","")
A25: =TODAY() -> 45567 | B25: =B24+1 -> 45770 | C25: =A25-B25 -> -203 | D25: =C25+K25 -> -203 | E25: =IF(10,K25="ok",0) -> FALSE | F25: Dia 23 | G25: =G24+I25 -> 9496.32 | H25: PicsArt Photo | I25: -10.99 | J25: Dia 21 | L25: =IF(A25=B25,"➜ Hoje","")
A26: =TODAY() -> 45567 | B26: =B25+1 -> 45771 | C26: =A26-B26 -> -204 | D26: =C26+K26 -> -204 | E26: =IF(10,K26="ok",0) -> FALSE | F26: Dia 24 | G26: =G25+I26 -> 9496.32 | L26: =IF(A26=B26,"➜ Hoje","")
A27: =TODAY() -> 45567 | B27: =B26+1 -> 45772 | C27: =A27-B27 -> -205 | D27: =C27+K27 -> -205 | E27: =IF(10,K27="ok",0) -> FALSE | F27: Dia 25 | G27: =G26+I27 -> 9376.32 | H27: Dízimo (2/2 parte) | I27: -120 | J27: Dia 24 | L27: =IF(A27=B27,"➜ Hoje","")
A28: =TODAY() -> 45567 | B28: =B27+1 -> 45773 | C28: =A28-B28 -> -206 | D28: =C28+K28 -> -206 | E28: =IF(10,K28="ok",0) -> FALSE | F28: Dia 26 | G28: =G27+I28 -> 9256.32 | H28: Energia Elétrica (1/4 pagamento) | I28: -120 | J28: Dia 20 | L28: =IF(A28=B28,"➜ Hoje","")
A29: =TODAY() -> 45567 | B29: =B28+1 -> 45774 | C29: =A29-B29 -> -207 | D29: =C29+K29 -> -207 | E29: =IF(10,K29="ok",0) -> FALSE | F29: Dia 27 | G29: =G28+I29 -> 9211.32 | H29: Internet Celular Vivo | I29: -45 | J29: Dia 27 | L29: =IF(A29=B29,"➜ Hoje","")
A30: =TODAY() -> 45567 | B30: =B29+1 -> 45775 | C30: =A30-B30 -> -208 | D30: =C30+K30 -> -208 | E30: =IF(10,K30="ok",0) -> FALSE | F30: Dia 28 | G30: =G29+I30 -> 9083.82 | H30: Cílios | I30: -127.5 | J30: Dia 28 | L30: =IF(A30=B30,"➜ Hoje","") | M30: Prorrogar: | N30: =SUM(N24:N29) -> 0
A31: =TODAY() -> 45567 | B31: =B30+1 -> 45776 | C31: =A31-B31 -> -209 | D31: =C31+K31 -> -209 | E31: =IF(10,K31="ok",0) -> FALSE | F31: Dia 29 | G31: =G30+I31 -> 9066.37 | H31: HBO | I31: -17.45 | J31: Dia 29 | L31: =IF(A31=B31,"➜ Hoje","") | M31: =M2 -> Dia 31 | N31: =N2+N30 -> 9066.37 | O31: Valor sobra dia 31 - Final do mês
A32: =TODAY() -> 45567 | B32: =B31+1 -> 45777 | C32: =A32-B32 -> -210 | D32: =C32+K32 -> -210 | E32: =IF(10,K32="ok",0) -> FALSE | F32: Dia 30 | G32: =G31+I32 -> 9066.37 | L32: =IF(A32=B32,"➜ Hoje","") | N32: =N30*2 -> 0
A33: =TODAY() -> 45567 | B33: 45596 | C33: =A33-B33 -> -29 | D33: =C33+K33 -> -29 | E33: =IF(10,K33="ok",0) -> FALSE | F33: Dia 31 | G33: =G32+I33 -> 9066.37 | L33: =IF(A33=B33,"➜ Hoje","") | N33: =N30-N32 -> 0
M34: Pendencias para pagar
M36: {=F2:K33} -> 0 | N36: Saldo Prévio | O36: Descrição Conta | P36: Valor | Q36: Data vencimento | R36: Pago?
M37: Dia 1 | N37: 7522.07 | O37: 0 | P37: 0 | Q37: 0 | R37: 0
M38: Dia 2 | N38: 7494.08 | O38: Nível 6 Mercado Livre - Automatico | P38: -27.99 | Q38: Dia 1 | R38: 0
M39: Dia 3 | N39: 7494.08 | O39: 0 | P39: 0 | Q39: 0 | R39: 0
M40: Dia 4 | N40: 7459.08 | O40: Granulado Madeira (10kg) | P40: -35 | Q40: Dia 5 | R40: 0
M41: Dia 5 | N41: 8859.08 | O41: Pagamento Recebido Bellocopo | P41: 1400 | Q41: Dia 5 | R41: 0
M42: Dia 6 | N42: 8819.38 | O42: Fatura Cartão Mercado Livre | P42: -39.7 | Q42: Dia 5 | R42: 0
M43: Dia 7 | N43: 8819.38 | O43: 0 | P43: 0 | Q43: Dia 6 | R43: 0
M44: Dia 8 | N44: 8661.38 | O44: Ração Gatos Golden Castrados | P44: -158 | Q44: Dia 6 | R44: 0
M45: Dia 9 | N45: 8622.38 | O45: Microsoft | P45: -39 | Q45: Dia 6 | R45: 0
M46: Dia 10 | N46: 8622.38 | O46: 0 | P46: 0 | Q46: 0 | R46: 0
M47: Dia 11 | N47: 8622.38 | O47: 0 | P47: 0 | Q47: 0 | R47: 0
M48: Dia 12 | N48: 8591.48 | O48: Netflix - Automatico | P48: -30.9 | Q48: Dia 9 | R48: 0
M49: Dia 13 | N49: 8451.48 | O49: Dízimo (1/2 parte) | P49: -140 | Q49: Dia 9 | R49: 0
M50: Dia 14 | N50: 8423.7 | O50: Anticoncepcional | P50: -27.78 | Q50: Dia 10 | R50: 0
M51: Dia 15 | N51: 8407.21 | O51: SimplyPiano | P51: -16.49 | Q51: Dia 12 | R51: 0
M52: Dia 16 | N52: 8407.21 | O52: 0 | P52: 0 | Q52: 0 | R52: 0
M53: Dia 17 | N53: 8407.21 | O53: 0 | P53: 0 | Q53: 0 | R53: 0
M54: Dia 18 | N54: 8407.21 | O54: 0 | P54: 0 | Q54: 0 | R54: 0
M55: Dia 19 | N55: 8407.21 | O55: Fatura Cartão Nubank | P55: 0 | Q55: Dia 12 | R55: 0
M56: Dia 20 | N56: 9607.21 | O56: Pagamento Recebido Bellocopo | P56: 1200 | Q56: Dia 20 | R56: 0
M57: Dia 21 | N57: 9607.21 | O57: 0 | P57: 0 | Q57: 0 | R57: 0
M58: Dia 22 | N58: 9507.31 | O58: Internet Atranet | P58: -99.9 | Q58: Dia 20 | R58: 0
M59: Dia 23 | N59: 9496.32 | O59: PicsArt Photo | P59: -10.99 | Q59: Dia 21 | R59: 0
M60: Dia 24 | N60: 9496.32 | O60: 0 | P60: 0 | Q60: 0 | R60: 0
M61: Dia 25 | N61: 9376.32 | O61: Dízimo (2/2 parte) | P61: -120 | Q61: Dia 24 | R61: 0
M62: Dia 26 | N62: 9256.32 | O62: Energia Elétrica (1/4 pagamento) | P62: -120 | Q62: Dia 20 | R62: 0
M63: Dia 27 | N63: 9211.32 | O63: Internet Celular Vivo | P63: -45 | Q63: Dia 27 | R63: 0
M64: Dia 28 | N64: 9083.82 | O64: Cílios | P64: -127.5 | Q64: Dia 28 | R64: 0
M65: Dia 29 | N65: 9066.37 | O65: HBO | P65: -17.45 | Q65: Dia 29 | R65: 0
M66: Dia 30 | N66: 9066.37 | O66: 0 | P66: 0 | Q66: 0 | R66: 0
M67: Dia 31 | N67: 9066.37 | O67: 0 | P67: 0 | Q67: 0 | R67: 0

Sheet Maio 2025
A1: Planejamento Mensal Káic e Gabi | I1: Mês: | J1: =B3 -> 45778 | M1: Resumo Finalização do Mês | S1: 0
A2: Data hoje formula | B2: Data formula | C2: Formula pgto ok | G2: Saldo Prévio | H2: Descrição Conta | I2: Valor | J2: Data vencimento | K2: Pago? | M2: =F33 -> Dia 31 | N2: =G33 -> 10610.67 | O2: Valor sobra dia 31 - Final do mês
A3: =TODAY() -> 45567 | B3: 45778 | C3: =A3-B3 -> -211 | D3: =C3+K3 -> -211 | E3: =IF(10,K3="ok",0) -> FALSE | F3: Dia 1 | G3: ='Abril 2025'!G33+'Maio 2025'!I3 -> 9066.37 | L3: =IF(A3=B3,"➜ Hoje","")
A4: =TODAY() -> 45567 | B4: =B3+1 -> 45779 | C4: =A4-B4 -> -212 | D4: =C4+K4 -> -212 | E4: =IF(10,K4="ok",0) -> FALSE | F4: Dia 2 | G4: =G3+I4 -> 9038.38 | H4: Nível 6 Mercado Livre - Automatico | I4: -27.99 | J4: Dia 1 | L4: =IF(A4=B4,"➜ Hoje","") | M4: 0.2 | N4: =IF($N$2*M4<=0,"Em vermelho",$N$2*M4) -> 2122.134 | O4: Comemoraçao dia 20
A5: =TODAY() -> 45567 | B5: =B4+1 -> 45780 | C5: =A5-B5 -> -213 | D5: =C5+K5 -> -213 | E5: =IF(10,K5="ok",0) -> FALSE | F5: Dia 3 | G5: =G4+I5 -> 9038.38 | L5: =IF(A5=B5,"➜ Hoje","") | M5: 0.1 | N5: =IF($N$2*M5<=0,"Em vermelho",$N$2*M5) -> 1061.067 | O5: Reforma Casa
A6: =TODAY() -> 45567 | B6: =B5+1 -> 45781 | C6: =A6-B6 -> -214 | D6: =C6+K6 -> -214 | E6: =IF(10,K6="ok",0) -> FALSE | F6: Dia 4 | G6: =G5+I6 -> 9003.38 | H6: Granulado Madeira (10kg) | I6: -35 | J6: Dia 5 | L6: =IF(A6=B6,"➜ Hoje","") | M6: 0.4 | N6: =IF($N$2*M6<=0,"Em vermelho",$N$2*M6) -> 4244.268 | O6: Tirar Carta A+B
A7: =TODAY() -> 45567 | B7: =B6+1 -> 45782 | C7: =A7-B7 -> -215 | D7: =C7+K7 -> -215 | E7: =IF(10,K7="ok",0) -> FALSE | F7: Dia 5 | G7: =G6+I7 -> 10403.38 | H7: Pagamento Recebido Bellocopo | I7: 1400 | J7: Dia 5 | L7: =IF(A7=B7,"➜ Hoje","") | M7: 0.3 | N7: =IF($N$2*M7<=0,"Em vermelho",$N$2*M7) -> 3183.201 | O7: Novas Alianças
A8: =TODAY() -> 45567 | B8: =B7+1 -> 45783 | C8: =A8-B8 -> -216 | D8: =C8+K8 -> -216 | E8: =IF(10,K8="ok",0) -> FALSE | F8: Dia 6 | G8: =G7+I8 -> 10363.68 | H8: Fatura Cartão Mercado Livre | I8: -39.7 | J8: Dia 5 | L8: =IF(A8=B8,"➜ Hoje","")
A9: =TODAY() -> 45567 | B9: =B8+1 -> 45784 | C9: =A9-B9 -> -217 | D9: =C9+K9 -> -217 | E9: =IF(10,K9="ok",0) -> FALSE | F9: Dia 7 | G9: =G8+I9 -> 10363.68 | J9: Dia 6 | L9: =IF(A9=B9,"➜ Hoje","") | M9: Planejamento Aquisições / Projetos
A10: =TODAY() -> 45567 | B10: =B9+1 -> 45785 | C10: =A10-B10 -> -218 | D10: =C10+K10 -> -218 | E10: =IF(10,K10="ok",0) -> FALSE | F10: Dia 8 | G10: =G9+I10 -> 10205.68 | H10: Ração Gatos Golden Castrados | I10: -158 | J10: Dia 6 | L10: =IF(A10=B10,"➜ Hoje","")
A11: =TODAY() -> 45567 | B11: =B10+1 -> 45786 | C11: =A11-B11 -> -219 | D11: =C11+K11 -> -219 | E11: =IF(10,K11="ok",0) -> FALSE | F11: Dia 9 | G11: =G10+I11 -> 10166.68 | H11: Microsoft | I11: -39 | J11: Dia 6 | L11: =IF(A11=B11,"➜ Hoje","") | M11: Data | N11: Valor média | O11: Descrição
A12: =TODAY() -> 45567 | B12: =B11+1 -> 45787 | C12: =A12-B12 -> -220 | D12: =C12+K12 -> -220 | E12: =IF(10,K12="ok",0) -> FALSE | F12: Dia 10 | G12: =G11+I12 -> 10166.68 | L12: =IF(A12=B12,"➜ Hoje","") | M12: 45046 | N12: 400 | O12: Depurador de ar (Reforma Cozinha)
A13: =TODAY() -> 45567 | B13: =B12+1 -> 45788 | C13: =A13-B13 -> -221 | D13: =C13+K13 -> -221 | E13: =IF(10,K13="ok",0) -> FALSE | F13: Dia 11 | G13: =G12+I13 -> 10166.68 | L13: =IF(A13=B13,"➜ Hoje","") | M13: 44540 | N13: 300 | O13: Revestimento Lume 45x90 Botanico Branco Retif.Azulejo (Reforma Cozinha)
A14: =TODAY() -> 45567 | B14: =B13+1 -> 45789 | C14: =A14-B14 -> -222 | D14: =C14+K14 -> -222 | E14: =IF(10,K14="ok",0) -> FALSE | F14: Dia 12 | G14: =G13+I14 -> 10135.78 | H14: Netflix - Automatico | I14: -30.9 | J14: Dia 9 | L14: =IF(A14=B14,"➜ Hoje","")
A15: =TODAY() -> 45567 | B15: =B14+1 -> 45790 | C15: =A15-B15 -> -223 | D15: =C15+K15 -> -223 | E15: =IF(10,K15="ok",0) -> FALSE | F15: Dia 13 | G15: =G14+I15 -> 9995.78 | H15: Dízimo (1/2 parte) | I15: -140 | J15: Dia 9 | L15: =IF(A15=B15,"➜ Hoje","")
A16: =TODAY() -> 45567 | B16: =B15+1 -> 45791 | C16: =A16-B16 -> -224 | D16: =C16+K16 -> -224 | E16: =IF(10,K16="ok",0) -> FALSE | F16: Dia 14 | G16: =G15+I16 -> 9968 | H16: Anticoncepcional | I16: -27.78 | J16: Dia 10 | L16: =IF(A16=B16,"➜ Hoje","")
A17: =TODAY() -> 45567 | B17: =B16+1 -> 45792 | C17: =A17-B17 -> -225 | D17: =C17+K17 -> -225 | E17: =IF(10,K17="ok",0) -> FALSE | F17: Dia 15 | G17: =G16+I17 -> 9951.51 | H17: SimplyPiano | I17: -16.49 | J17: Dia 12 | L17: =IF(A17=B17,"➜ Hoje","")
A18: =TODAY() -> 45567 | B18: =B17+1 -> 45793 | C18: =A18-B18 -> -226 | D18: =C18+K18 -> -226 | E18: =IF(10,K18="ok",0) -> FALSE | F18: Dia 16 | G18: =G17+I18 -> 9951.51 | L18: =IF(A18=B18,"➜ Hoje","") | M18: Planejamento Reposição Dispensa / Compras Mercado
A19: =TODAY() -> 45567 | B19: =B18+1 -> 45794 | C19: =A19-B19 -> -227 | D19: =C19+K19 -> -227 | E19: =IF(10,K19="ok",0) -> FALSE | F19: Dia 17 | G19: =G18+I19 -> 9951.51 | L19: =IF(A19=B19,"➜ Hoje","")
A20: =TODAY() -> 45567 | B20: =B19+1 -> 45795 | C20: =A20-B20 -> -228 | D20: =C20+K20 -> -228 | E20: =IF(10,K20="ok",0) -> FALSE | F20: Dia 18 | G20: =G19+I20 -> 9951.51 | L20: =IF(A20=B20,"➜ Hoje","") | M20: Dia 15 | N20: 210 | O20: Pagamento Recebido VA Bellocopo
A21: =TODAY() -> 45567 | B21: =B20+1 -> 45796 | C21: =A21-B21 -> -229 | D21: =C21+K21 -> -229 | E21: =IF(10,K21="ok",0) -> FALSE | F21: Dia 19 | G21: =G20+I21 -> 9951.51 | H21: Fatura Cartão Nubank | I21: 0 | J21: Dia 12 | L21: =IF(A21=B21,"➜ Hoje","")
A22: =TODAY() -> 45567 | B22: =B21+1 -> 45797 | C22: =A22-B22 -> -230 | D22: =C22+K22 -> -230 | E22: =IF(10,K22="ok",0) -> FALSE | F22: Dia 20 | G22: =G21+I22 -> 11151.51 | H22: Pagamento Recebido Bellocopo | I22: 1200 | J22: Dia 20 | L22: =IF(A22=B22,"➜ Hoje","") | M22: Planejamento Acerto de dividas - prorrogando para mês seguinte
A23: =TODAY() -> 45567 | B23: =B22+1 -> 45798 | C23: =A23-B23 -> -231 | D23: =C23+K23 -> -231 | E23: =IF(10,K23="ok",0) -> FALSE | F23: Dia 21 | G23: =G22+I23 -> 11151.51 | L23: =IF(A23=B23,"➜ Hoje","")
A24: =TODAY() -> 45567 | B24: =B23+1 -> 45799 | C24: =A24-B24 -> -232 | D24: =C24+K24 -> -232 | E24: =IF(10,K24="ok",0) -> FALSE | F24: Dia 22 | G24: =G23+I24 -> 11051.61 | H24: Internet Atranet | I24: -99.9 | J24: Dia 20 | L24: =IF(A24=B24,"➜ Hoje","")
A25: =TODAY() -> 45567 | B25: =B24+1 -> 45800 | C25: =A25-B25 -> -233 | D25: =C25+K25 -> -233 | E25: =IF(10,K25="ok",0) -> FALSE | F25: Dia 23 | G25: =G24+I25 -> 11040.62 | H25: PicsArt Photo | I25: -10.99 | J25: Dia 21 | L25: =IF(A25=B25,"➜ Hoje","")
A26: =TODAY() -> 45567 | B26: =B25+1 -> 45801 | C26: =A26-B26 -> -234 | D26: =C26+K26 -> -234 | E26: =IF(10,K26="ok",0) -> FALSE | F26: Dia 24 | G26: =G25+I26 -> 11040.62 | L26: =IF(A26=B26,"➜ Hoje","")
A27: =TODAY() -> 45567 | B27: =B26+1 -> 45802 | C27: =A27-B27 -> -235 | D27: =C27+K27 -> -235 | E27: =IF(10,K27="ok",0) -> FALSE | F27: Dia 25 | G27: =G26+I27 -> 10920.62 | H27: Dízimo (2/2 parte) | I27: -120 | J27: Dia 24 | L27: =IF(A27=B27,"➜ Hoje","")
A28: =TODAY() -> 45567 | B28: =B27+1 -> 45803 | C28: =A28-B28 -> -236 | D28: =C28+K28 -> -236 | E28: =IF(10,K28="ok",0) -> FALSE | F28: Dia 26 | G28: =G27+I28 -> 10800.62 | H28: Energia Elétrica (1/4 pagamento) | I28: -120 | J28: Dia 20 | L28: =IF(A28=B28,"➜ Hoje","")
A29: =TODAY() -> 45567 | B29: =B28+1 -> 45804 | C29: =A29-B29 -> -237 | D29: =C29+K29 -> -237 | E29: =IF(10,K29="ok",0) -> FALSE | F29: Dia 27 | G29: =G28+I29 -> 10755.62 | H29: Internet Celular Vivo | I29: -45 | J29: Dia 27 | L29: =IF(A29=B29,"➜ Hoje","")
A30: =TODAY() -> 45567 | B30: =B29+1 -> 45805 | C30: =A30-B30 -> -238 | D30: =C30+K30 -> -238 | E30: =IF(10,K30="ok",0) -> FALSE | F30: Dia 28 | G30: =G29+I30 -> 10628.12 | H30: Cílios | I30: -127.5 | J30: Dia 28 | L30: =IF(A30=B30,"➜ Hoje","") | M30: Prorrogar: | N30: =SUM(N24:N29) -> 0
A31: =TODAY() -> 45567 | B31: =B30+1 -> 45806 | C31: =A31-B31 -> -239 | D31: =C31+K31 -> -239 | E31: =IF(10,K31="ok",0) -> FALSE | F31: Dia 29 | G31: =G30+I31 -> 10610.67 | H31: HBO | I31: -17.45 | J31: Dia 29 | L31: =IF(A31=B31,"➜ Hoje","") | M31: =M2 -> Dia 31 | N31: =N2+N30 -> 10610.67 | O31: Valor sobra dia 31 - Final do mês
A32: =TODAY() -> 45567 | B32: =B31+1 -> 45807 | C32: =A32-B32 -> -240 | D32: =C32+K32 -> -240 | E32: =IF(10,K32="ok",0) -> FALSE | F32: Dia 30 | G32: =G31+I32 -> 10610.67 | L32: =IF(A32=B32,"➜ Hoje","") | N32: =N30*2 -> 0
A33: =TODAY() -> 45567 | B33: 45596 | C33: =A33-B33 -> -29 | D33: =C33+K33 -> -29 | E33: =IF(10,K33="ok",0) -> FALSE | F33: Dia 31 | G33: =G32+I33 -> 10610.67 | L33: =IF(A33=B33,"➜ Hoje","") | N33: =N30-N32 -> 0
M34: Pendencias para pagar
M36: {=F2:K33} -> 0 | N36: Saldo Prévio | O36: Descrição Conta | P36: Valor | Q36: Data vencimento | R36: Pago?
M37: Dia 1 | N37: 9066.37 | O37: 0 | P37: 0 | Q37: 0 | R37: 0
M38: Dia 2 | N38: 9038.38 | O38: Nível 6 Mercado Livre - Automatico | P38: -27.99 | Q38: Dia 1 | R38: 0
M39: Dia 3 | N39: 9038.38 | O39: 0 | P39: 0 | Q39: 0 | R39: 0
M40: Dia 4 | N40: 9003.38 | O40: Granulado Madeira (10kg) | P40: -35 | Q40: Dia 5 | R40: 0
M41: Dia 5 | N41: 10403.38 | O41: Pagamento Recebido Bellocopo | P41: 1400 | Q41: Dia 5 | R41: 0
M42: Dia 6 | N42: 10363.68 | O42: Fatura Cartão Mercado Livre | P42: -39.7 | Q42: Dia 5 | R42: 0
M43: Dia 7 | N43: 10363.68 | O43: 0 | P43: 0 | Q43: Dia 6 | R43: 0
M44: Dia 8 | N44: 10205.68 | O44: Ração Gatos Golden Castrados | P44: -158 | Q44: Dia 6 | R44: 0
M45: Dia 9 | N45: 10166.68 | O45: Microsoft | P45: -39 | Q45: Dia 6 | R45: 0
M46: Dia 10 | N46: 10166.68 | O46: 0 | P46: 0 | Q46: 0 | R46: 0
M47: Dia 11 | N47: 10166.68 | O47: 0 | P47: 0 | Q47: 0 | R47: 0
M48: Dia 12 | N48: 10135.78 | O48: Netflix - Automatico | P48: -30.9 | Q48: Dia 9 | R48: 0
M49: Dia 13 | N49: 9995.78 | O49: Dízimo (1/2 parte) | P49: -140 | Q49: Dia 9 | R49: 0
M50: Dia 14 | N50: 9968 | O50: Anticoncepcional | P50: -27.78 | Q50: Dia 10 | R50: 0
M51: Dia 15 | N51: 9951.51 | O51: SimplyPiano | P51: -16.49 | Q51: Dia 12 | R51: 0
M52: Dia 16 | N52: 9951.51 | O52: 0 | P52: 0 | Q52: 0 | R52: 0
M53: Dia 17 | N53: 9951.51 | O53: 0 | P53: 0 | Q53: 0 | R53: 0
M54: Dia 18 | N54: 9951.51 | O54: 0 | P54: 0 | Q54: 0 | R54: 0
M55: Dia 19 | N55: 9951.51 | O55: Fatura Cartão Nubank | P55: 0 | Q55: Dia 12 | R55: 0
M56: Dia 20 | N56: 11151.51 | O56: Pagamento Recebido Bellocopo | P56: 1200 | Q56: Dia 20 | R56: 0
M57: Dia 21 | N57: 11151.51 | O57: 0 | P57: 0 | Q57: 0 | R57: 0
M58: Dia 22 | N58: 11051.61 | O58: Internet Atranet | P58: -99.9 | Q58: Dia 20 | R58: 0
M59: Dia 23 | N59: 11040.62 | O59: PicsArt Photo | P59: -10.99 | Q59: Dia 21 | R59: 0
M60: Dia 24 | N60: 11040.62 | O60: 0 | P60: 0 | Q60: 0 | R60: 0
M61: Dia 25 | N61: 10920.62 | O61: Dízimo (2/2 parte) | P61: -120 | Q61: Dia 24 | R61: 0
M62: Dia 26 | N62: 10800.62 | O62: Energia Elétrica (1/4 pagamento) | P62: -120 | Q62: Dia 20 | R62: 0
M63: Dia 27 | N63: 10755.62 | O63: Internet Celular Vivo | P63: -45 | Q63: Dia 27 | R63: 0
M64: Dia 28 | N64: 10628.12 | O64: Cílios | P64: -127.5 | Q64: Dia 28 | R64: 0
M65: Dia 29 | N65: 10610.67 | O65: HBO | P65: -17.45 | Q65: Dia 29 | R65: 0
M66: Dia 30 | N66: 10610.67 | O66: 0 | P66: 0 | Q66: 0 | R66: 0
M67: Dia 31 | N67: 10610.67 | O67: 0 | P67: 0 | Q67: 0 | R67: 0

Sheet Junho 2025
A1: Planejamento Mensal Káic e Gabi | I1: Mês: | J1: =B3 -> 45809 | M1: Resumo Finalização do Mês | S1: 0
A2: Data hoje formula | B2: Data formula | C2: Formula pgto ok | G2: Saldo Prévio | H2: Descrição Conta | I2: Valor | J2: Data vencimento | K2: Pago? | M2: =F33 -> Dia 31 | N2: =G33 -> 12154.97 | O2: Valor sobra dia 31 - Final do mês
A3: =TODAY() -> 45567 | B3: 45809 | C3: =A3-B3 -> -242 | D3: =C3+K3 -> -242 | E3: =IF(10,K3="ok",0) -> FALSE | F3: Dia 1 | G3: ='Maio 2025'!G33+'Junho 2025'!I3 -> 10610.67 | L3: =IF(A3=B3,"➜ Hoje","")
A4: =TODAY() -> 45567 | B4: =B3+1 -> 45810 | C4: =A4-B4 -> -243 | D4: =C4+K4 -> -243 | E4: =IF(10,K4="ok",0) -> FALSE | F4: Dia 2 | G4: =G3+I4 -> 10582.68 | H4: Nível 6 Mercado Livre - Automatico | I4: -27.99 | J4: Dia 1 | L4: =IF(A4=B4,"➜ Hoje","") | M4: 0.2 | N4: =IF($N$2*M4<=0,"Em vermelho",$N$2*M4) -> 2430.994 | O4: Comemoraçao dia 20
A5: =TODAY() -> 45567 | B5: =B4+1 -> 45811 | C5: =A5-B5 -> -244 | D5: =C5+K5 -> -244 | E5: =IF(10,K5="ok",0) -> FALSE | F5: Dia 3 | G5: =G4+I5 -> 10582.68 | L5: =IF(A5=B5,"➜ Hoje","") | M5: 0.1 | N5: =IF($N$2*M5<=0,"Em vermelho",$N$2*M5) -> 1215.497 | O5: Reforma Casa
A6: =TODAY() -> 45567 | B6: =B5+1 -> 45812 | C6: =A6-B6 -> -245 | D6: =C6+K6 -> -245 | E6: =IF(10,K6="ok",0) -> FALSE | F6: Dia 4 | G6: =G5+I6 -> 10547.68 | H6: Granulado Madeira (10kg) | I6: -35 | J6: Dia 5 | L6: =IF(A6=B6,"➜ Hoje","") | M6: 0.4 | N6: =IF($N$2*M6<=0,"Em vermelho",$N$2*M6) -> 4861.988 | O6: Tirar Carta A+B
A7: =TODAY() -> 45567 | B7: =B6+1 -> 45813 | C7: =A7-B7 -> -246 | D7: =C7+K7 -> -246 | E7: =IF(10,K7="ok",0) -> FALSE | F7: Dia 5 | G7: =G6+I7 -> 11947.68 | H7: Pagamento Recebido Bellocopo | I7: 1400 | J7: Dia 5 | L7: =IF(A7=B7,"➜ Hoje","") | M7: 0.3 | N7: =IF($N$2*M7<=0,"Em vermelho",$N$2*M7) -> 3646.491 | O7: Novas Alianças
A8: =TODAY() -> 45567 | B8: =B7+1 -> 45814 | C8: =A8-B8 -> -247 | D8: =C8+K8 -> -247 | E8: =IF(10,K8="ok",0) -> FALSE | F8: Dia 6 | G8: =G7+I8 -> 11907.98 | H8: Fatura Cartão Mercado Livre | I8: -39.7 | J8: Dia 5 | L8: =IF(A8=B8,"➜ Hoje","")
A9: =TODAY() -> 45567 | B9: =B8+1 -> 45815 | C9: =A9-B9 -> -248 | D9: =C9+K9 -> -248 | E9: =IF(10,K9="ok",0) -> FALSE | F9: Dia 7 | G9: =G8+I9 -> 11907.98 | J9: Dia 6 | L9: =IF(A9=B9,"➜ Hoje","") | M9: Planejamento Aquisições / Projetos
A10: =TODAY() -> 45567 | B10: =B9+1 -> 45816 | C10: =A10-B10 -> -249 | D10: =C10+K10 -> -249 | E10: =IF(10,K10="ok",0) -> FALSE | F10: Dia 8 | G10: =G9+I10 -> 11749.98 | H10: Ração Gatos Golden Castrados | I10: -158 | J10: Dia 6 | L10: =IF(A10=B10,"➜ Hoje","")
A11: =TODAY() -> 45567 | B11: =B10+1 -> 45817 | C11: =A11-B11 -> -250 | D11: =C11+K11 -> -250 | E11: =IF(10,K11="ok",0) -> FALSE | F11: Dia 9 | G11: =G10+I11 -> 11710.98 | H11: Microsoft | I11: -39 | J11: Dia 6 | L11: =IF(A11=B11,"➜ Hoje","") | M11: Data | N11: Valor média | O11: Descrição
A12: =TODAY() -> 45567 | B12: =B11+1 -> 45818 | C12: =A12-B12 -> -251 | D12: =C12+K12 -> -251 | E12: =IF(10,K12="ok",0) -> FALSE | F12: Dia 10 | G12: =G11+I12 -> 11710.98 | L12: =IF(A12=B12,"➜ Hoje","") | M12: 45046 | N12: 400 | O12: Depurador de ar (Reforma Cozinha)
A13: =TODAY() -> 45567 | B13: =B12+1 -> 45819 | C13: =A13-B13 -> -252 | D13: =C13+K13 -> -252 | E13: =IF(10,K13="ok",0) -> FALSE | F13: Dia 11 | G13: =G12+I13 -> 11710.98 | L13: =IF(A13=B13,"➜ Hoje","") | M13: 44540 | N13: 300 | O13: Revestimento Lume 45x90 Botanico Branco Retif.Azulejo (Reforma Cozinha)
A14: =TODAY() -> 45567 | B14: =B13+1 -> 45820 | C14: =A14-B14 -> -253 | D14: =C14+K14 -> -253 | E14: =IF(10,K14="ok",0) -> FALSE | F14: Dia 12 | G14: =G13+I14 -> 11680.08 | H14: Netflix - Automatico | I14: -30.9 | J14: Dia 9 | L14: =IF(A14=B14,"➜ Hoje","")
A15: =TODAY() -> 45567 | B15: =B14+1 -> 45821 | C15: =A15-B15 -> -254 | D15: =C15+K15 -> -254 | E15: =IF(10,K15="ok",0) -> FALSE | F15: Dia 13 | G15: =G14+I15 -> 11540.08 | H15: Dízimo (1/2 parte) | I15: -140 | J15: Dia 9 | L15: =IF(A15=B15,"➜ Hoje","")
A16: =TODAY() -> 45567 | B16: =B15+1 -> 45822 | C16: =A16-B16 -> -255 | D16: =C16+K16 -> -255 | E16: =IF(10,K16="ok",0) -> FALSE | F16: Dia 14 | G16: =G15+I16 -> 11512.3 | H16: Anticoncepcional | I16: -27.78 | J16: Dia 10 | L16: =IF(A16=B16,"➜ Hoje","")
A17: =TODAY() -> 45567 | B17: =B16+1 -> 45823 | C17: =A17-B17 -> -256 | D17: =C17+K17 -> -256 | E17: =IF(10,K17="ok",0) -> FALSE | F17: Dia 15 | G17: =G16+I17 -> 11495.81 | H17: SimplyPiano | I17: -16.49 | J17: Dia 12 | L17: =IF(A17=B17,"➜ Hoje","")
A18: =TODAY() -> 45567 | B18: =B17+1 -> 45824 | C18: =A18-B18 -> -257 | D18: =C18+K18 -> -257 | E18: =IF(10,K18="ok",0) -> FALSE | F18: Dia 16 | G18: =G17+I18 -> 11495.81 | L18: =IF(A18=B18,"➜ Hoje","") | M18: Planejamento Reposição Dispensa / Compras Mercado
A19: =TODAY() -> 45567 | B19: =B18+1 -> 45825 | C19: =A19-B19 -> -258 | D19: =C19+K19 -> -258 | E19: =IF(10,K19="ok",0) -> FALSE | F19: Dia 17 | G19: =G18+I19 -> 11495.81 | L19: =IF(A19=B19,"➜ Hoje","")
A20: =TODAY() -> 45567 | B20: =B19+1 -> 45826 | C20: =A20-B20 -> -259 | D20: =C20+K20 -> -259 | E20: =IF(10,K20="ok",0) -> FALSE | F20: Dia 18 | G20: =G19+I20 -> 11495.81 | L20: =IF(A20=B20,"➜ Hoje","") | M20: Dia 15 | N20: 210 | O20: Pagamento Recebido VA Bellocopo
A21: =TODAY() -> 45567 | B21: =B20+1 -> 45827 | C21: =A21-B21 -> -260 | D21: =C21+K21 -> -260 | E21: =IF(10,K21="ok",0) -> FALSE | F21: Dia 19 | G21: =G20+I21 -> 11495.81 | H21: Fatura Cartão Nubank | I21: 0 | J21: Dia 12 | L21: =IF(A21=B21,"➜ Hoje","")
A22: =TODAY() -> 45567 | B22: =B21+1 -> 45828 | C22: =A22-B22 -> -261 | D22: =C22+K22 -> -261 | E22: =IF(10,K22="ok",0) -> FALSE | F22: Dia 20 | G22: =G21+I22 -> 12695.81 | H22: Pagamento Recebido Bellocopo | I22: 1200 | J22: Dia 20 | L22: =IF(A22=B22,"➜ Hoje","") | M22: Planejamento Acerto de dividas - prorrogando para mês seguinte
A23: =TODAY() -> 45567 | B23: =B22+1 -> 45829 | C23: =A23-B23 -> -262 | D23: =C23+K23 -> -262 | E23: =IF(10,K23="ok",0) -> FALSE | F23: Dia 21 | G23: =G22+I23 -> 12695.81 | L23: =IF(A23=B23,"➜ Hoje","")
A24: =TODAY() -> 45567 | B24: =B23+1 -> 45830 | C24: =A24-B24 -> -263 | D24: =C24+K24 -> -263 | E24: =IF(10,K24="ok",0) -> FALSE | F24: Dia 22 | G24: =G23+I24 -> 12595.91 | H24: Internet Atranet | I24: -99.9 | J24: Dia 20 | L24: =IF(A24=B24,"➜ Hoje","")
A25: =TODAY() -> 45567 | B25: =B24+1 -> 45831 | C25: =A25-B25 -> -264 | D25: =C25+K25 -> -264 | E25: =IF(10,K25="ok",0) -> FALSE | F25: Dia 23 | G25: =G24+I25 -> 12584.92 | H25: PicsArt Photo | I25: -10.99 | J25: Dia 21 | L25: =IF(A25=B25,"➜ Hoje","")
A26: =TODAY() -> 45567 | B26: =B25+1 -> 45832 | C26: =A26-B26 -> -265 | D26: =C26+K26 -> -265 | E26: =IF(10,K26="ok",0) -> FALSE | F26: Dia 24 | G26: =G25+I26 -> 12584.92 | L26: =IF(A26=B26,"➜ Hoje","")
A27: =TODAY() -> 45567 | B27: =B26+1 -> 45833 | C27: =A27-B27 -> -266 | D27: =C27+K27 -> -266 | E27: =IF(10,K27="ok",0) -> FALSE | F27: Dia 25 | G27: =G26+I27 -> 12464.92 | H27: Dízimo (2/2 parte) | I27: -120 | J27: Dia 24 | L27: =IF(A27=B27,"➜ Hoje","")
A28: =TODAY() -> 45567 | B28: =B27+1 -> 45834 | C28: =A28-B28 -> -267 | D28: =C28+K28 -> -267 | E28: =IF(10,K28="ok",0) -> FALSE | F28: Dia 26 | G28: =G27+I28 -> 12344.92 | H28: Energia Elétrica (1/4 pagamento) | I28: -120 | J28: Dia 20 | L28: =IF(A28=B28,"➜ Hoje","")
A29: =TODAY() -> 45567 | B29: =B28+1 -> 45835 | C29: =A29-B29 -> -268 | D29: =C29+K29 -> -268 | E29: =IF(10,K29="ok",0) -> FALSE | F29: Dia 27 | G29: =G28+I29 -> 12299.92 | H29: Internet Celular Vivo | I29: -45 | J29: Dia 27 | L29: =IF(A29=B29,"➜ Hoje","")
A30: =TODAY() -> 45567 | B30: =B29+1 -> 45836 | C30: =A30-B30 -> -269 | D30: =C30+K30 -> -269 | E30: =IF(10,K30="ok",0) -> FALSE | F30: Dia 28 | G30: =G29+I30 -> 12172.42 | H30: Cílios | I30: -127.5 | J30: Dia 28 | L30: =IF(A30=B30,"➜ Hoje","") | M30: Prorrogar: | N30: =SUM(N24:N29) -> 0
A31: =TODAY() -> 45567 | B31: =B30+1 -> 45837 | C31: =A31-B31 -> -270 | D31: =C31+K31 -> -270 | E31: =IF(10,K31="ok",0) -> FALSE | F31: Dia 29 | G31: =G30+I31 -> 12154.97 | H31: HBO | I31: -17.45 | J31: Dia 29 | L31: =IF(A31=B31,"➜ Hoje","") | M31: =M2 -> Dia 31 | N31: =N2+N30 -> 12154.97 | O31: Valor sobra dia 31 - Final do mês
A32: =TODAY() -> 45567 | B32: =B31+1 -> 45838 | C32: =A32-B32 -> -271 | D32: =C32+K32 -> -271 | E32: =IF(10,K32="ok",0) -> FALSE | F32: Dia 30 | G32: =G31+I32 -> 12154.97 | L32: =IF(A32=B32,"➜ Hoje","") | N32: =N30*2 -> 0
A33: =TODAY() -> 45567 | B33: 45596 | C33: =A33-B33 -> -29 | D33: =C33+K33 -> -29 | E33: =IF(10,K33="ok",0) -> FALSE | F33: Dia 31 | G33: =G32+I33 -> 12154.97 | L33: =IF(A33=B33,"➜ Hoje","") | N33: =N30-N32 -> 0
M34: Pendencias para pagar
M36: {=F2:K33} -> 0 | N36: Saldo Prévio | O36: Descrição Conta | P36: Valor | Q36: Data vencimento | R36: Pago?
M37: Dia 1 | N37: 10610.67 | O37: 0 | P37: 0 | Q37: 0 | R37: 0
M38: Dia 2 | N38: 10582.68 | O38: Nível 6 Mercado Livre - Automatico | P38: -27.99 | Q38: Dia 1 | R38: 0
M39: Dia 3 | N39: 10582.68 | O39: 0 | P39: 0 | Q39: 0 | R39: 0
M40: Dia 4 | N40: 10547.68 | O40: Granulado Madeira (10kg) | P40: -35 | Q40: Dia 5 | R40: 0
M41: Dia 5 | N41: 11947.68 | O41: Pagamento Recebido Bellocopo | P41: 1400 | Q41: Dia 5 | R41: 0
M42: Dia 6 | N42: 11907.98 | O42: Fatura Cartão Mercado Livre | P42: -39.7 | Q42: Dia 5 | R42: 0
M43: Dia 7 | N43: 11907.98 | O43: 0 | P43: 0 | Q43: Dia 6 | R43: 0
M44: Dia 8 | N44: 11749.98 | O44: Ração Gatos Golden Castrados | P44: -158 | Q44: Dia 6 | R44: 0
M45: Dia 9 | N45: 11710.98 | O45: Microsoft | P45: -39 | Q45: Dia 6 | R45: 0
M46: Dia 10 | N46: 11710.98 | O46: 0 | P46: 0 | Q46: 0 | R46: 0
M47: Dia 11 | N47: 11710.98 | O47: 0 | P47: 0 | Q47: 0 | R47: 0
M48: Dia 12 | N48: 11680.08 | O48: Netflix - Automatico | P48: -30.9 | Q48: Dia 9 | R48: 0
M49: Dia 13 | N49: 11540.08 | O49: Dízimo (1/2 parte) | P49: -140 | Q49: Dia 9 | R49: 0
M50: Dia 14 | N50: 11512.3 | O50: Anticoncepcional | P50: -27.78 | Q50: Dia 10 | R50: 0
M51: Dia 15 | N51: 11495.81 | O51: SimplyPiano | P51: -16.49 | Q51: Dia 12 | R51: 0
M52: Dia 16 | N52: 11495.81 | O52: 0 | P52: 0 | Q52: 0 | R52: 0
M53: Dia 17 | N53: 11495.81 | O53: 0 | P53: 0 | Q53: 0 | R53: 0
M54: Dia 18 | N54: 11495.81 | O54: 0 | P54: 0 | Q54: 0 | R54: 0
M55: Dia 19 | N55: 11495.81 | O55: Fatura Cartão Nubank | P55: 0 | Q55: Dia 12 | R55: 0
M56: Dia 20 | N56: 12695.81 | O56: Pagamento Recebido Bellocopo | P56: 1200 | Q56: Dia 20 | R56: 0
M57: Dia 21 | N57: 12695.81 | O57: 0 | P57: 0 | Q57: 0 | R57: 0
M58: Dia 22 | N58: 12595.91 | O58: Internet Atranet | P58: -99.9 | Q58: Dia 20 | R58: 0
M59: Dia 23 | N59: 12584.92 | O59: PicsArt Photo | P59: -10.99 | Q59: Dia 21 | R59: 0
M60: Dia 24 | N60: 12584.92 | O60: 0 | P60: 0 | Q60: 0 | R60: 0
M61: Dia 25 | N61: 12464.92 | O61: Dízimo (2/2 parte) | P61: -120 | Q61: Dia 24 | R61: 0
M62: Dia 26 | N62: 12344.92 | O62: Energia Elétrica (1/4 pagamento) | P62: -120 | Q62: Dia 20 | R62: 0
M63: Dia 27 | N63: 12299.92 | O63: Internet Celular Vivo | P63: -45 | Q63: Dia 27 | R63: 0
M64: Dia 28 | N64: 12172.42 | O64: Cílios | P64: -127.5 | Q64: Dia 28 | R64: 0
M65: Dia 29 | N65: 12154.97 | O65: HBO | P65: -17.45 | Q65: Dia 29 | R65: 0
M66: Dia 30 | N66: 12154.97 | O66: 0 | P66: 0 | Q66: 0 | R66: 0
M67: Dia 31 | N67: 12154.97 | O67: 0 | P67: 0 | Q67: 0 | R67: 0

Sheet Julho 2025
A1: Planejamento Mensal Káic e Gabi | I1: Mês: | J1: =B3 -> 45809 | M1: Resumo Finalização do Mês | S1: 0
A2: Data hoje formula | B2: Data formula | C2: Formula pgto ok | G2: Saldo Prévio | H2: Descrição Conta | I2: Valor | J2: Data vencimento | K2: Pago? | M2: =F33 -> Dia 31 | N2: =G33 -> 13738.97 | O2: Valor sobra dia 31 - Final do mês
A3: =TODAY() -> 45567 | B3: 45809 | C3: =A3-B3 -> -242 | D3: =C3+K3 -> -242 | E3: =IF(10,K3="ok",0) -> FALSE | F3: Dia 1 | G3: ='Junho 2025'!G33+'Julho 2025'!I3 -> 12154.97 | L3: =IF(A3=B3,"➜ Hoje","")
A4: =TODAY() -> 45567 | B4: =B3+1 -> 45810 | C4: =A4-B4 -> -243 | D4: =C4+K4 -> -243 | E4: =IF(10,K4="ok",0) -> FALSE | F4: Dia 2 | G4: =G3+I4 -> 12126.98 | H4: Nível 6 Mercado Livre - Automatico | I4: -27.99 | J4: Dia 1 | L4: =IF(A4=B4,"➜ Hoje","") | M4: 0.2 | N4: =IF($N$2*M4<=0,"Em vermelho",$N$2*M4) -> 2747.794 | O4: Comemoraçao dia 20
A5: =TODAY() -> 45567 | B5: =B4+1 -> 45811 | C5: =A5-B5 -> -244 | D5: =C5+K5 -> -244 | E5: =IF(10,K5="ok",0) -> FALSE | F5: Dia 3 | G5: =G4+I5 -> 12126.98 | L5: =IF(A5=B5,"➜ Hoje","") | M5: 0.1 | N5: =IF($N$2*M5<=0,"Em vermelho",$N$2*M5) -> 1373.897 | O5: Reforma Casa
A6: =TODAY() -> 45567 | B6: =B5+1 -> 45812 | C6: =A6-B6 -> -245 | D6: =C6+K6 -> -245 | E6: =IF(10,K6="ok",0) -> FALSE | F6: Dia 4 | G6: =G5+I6 -> 12091.98 | H6: Granulado Madeira (10kg) | I6: -35 | J6: Dia 5 | L6: =IF(A6=B6,"➜ Hoje","") | M6: 0.4 | N6: =IF($N$2*M6<=0,"Em vermelho",$N$2*M6) -> 5495.588 | O6: Tirar Carta A+B
A7: =TODAY() -> 45567 | B7: =B6+1 -> 45813 | C7: =A7-B7 -> -246 | D7: =C7+K7 -> -246 | E7: =IF(10,K7="ok",0) -> FALSE | F7: Dia 5 | G7: =G6+I7 -> 13491.98 | H7: Pagamento Recebido Bellocopo | I7: 1400 | J7: Dia 5 | L7: =IF(A7=B7,"➜ Hoje","") | M7: 0.3 | N7: =IF($N$2*M7<=0,"Em vermelho",$N$2*M7) -> 4121.691 | O7: Novas Alianças
A8: =TODAY() -> 45567 | B8: =B7+1 -> 45814 | C8: =A8-B8 -> -247 | D8: =C8+K8 -> -247 | E8: =IF(10,K8="ok",0) -> FALSE | F8: Dia 6 | G8: =G7+I8 -> 13491.98 | H8: Fatura Cartão Mercado Livre | I8: 0 | J8: Dia 5 | L8: =IF(A8=B8,"➜ Hoje","")
A9: =TODAY() -> 45567 | B9: =B8+1 -> 45815 | C9: =A9-B9 -> -248 | D9: =C9+K9 -> -248 | E9: =IF(10,K9="ok",0) -> FALSE | F9: Dia 7 | G9: =G8+I9 -> 13491.98 | J9: Dia 6 | L9: =IF(A9=B9,"➜ Hoje","") | M9: Planejamento Aquisições / Projetos
A10: =TODAY() -> 45567 | B10: =B9+1 -> 45816 | C10: =A10-B10 -> -249 | D10: =C10+K10 -> -249 | E10: =IF(10,K10="ok",0) -> FALSE | F10: Dia 8 | G10: =G9+I10 -> 13333.98 | H10: Ração Gatos Golden Castrados | I10: -158 | J10: Dia 6 | L10: =IF(A10=B10,"➜ Hoje","")
A11: =TODAY() -> 45567 | B11: =B10+1 -> 45817 | C11: =A11-B11 -> -250 | D11: =C11+K11 -> -250 | E11: =IF(10,K11="ok",0) -> FALSE | F11: Dia 9 | G11: =G10+I11 -> 13294.98 | H11: Microsoft | I11: -39 | J11: Dia 6 | L11: =IF(A11=B11,"➜ Hoje","") | M11: Data | N11: Valor média | O11: Descrição
A12: =TODAY() -> 45567 | B12: =B11+1 -> 45818 | C12: =A12-B12 -> -251 | D12: =C12+K12 -> -251 | E12: =IF(10,K12="ok",0) -> FALSE | F12: Dia 10 | G12: =G11+I12 -> 13294.98 | L12: =IF(A12=B12,"➜ Hoje","") | M12: 45046 | N12: 400 | O12: Depurador de ar (Reforma Cozinha)
A13: =TODAY() -> 45567 | B13: =B12+1 -> 45819 | C13: =A13-B13 -> -252 | D13: =C13+K13 -> -252 | E13: =IF(10,K13="ok",0) -> FALSE | F13: Dia 11 | G13: =G12+I13 -> 13294.98 | L13: =IF(A13=B13,"➜ Hoje","") | M13: 44540 | N13: 300 | O13: Revestimento Lume 45x90 Botanico Branco Retif.Azulejo (Reforma Cozinha)
A14: =TODAY() -> 45567 | B14: =B13+1 -> 45820 | C14: =A14-B14 -> -253 | D14: =C14+K14 -> -253 | E14: =IF(10,K14="ok",0) -> FALSE | F14: Dia 12 | G14: =G13+I14 -> 13264.08 | H14: Netflix - Automatico | I14: -30.9 | J14: Dia 9 | L14: =IF(A14=B14,"➜ Hoje","")
A15: =TODAY() -> 45567 | B15: =B14+1 -> 45821 | C15: =A15-B15 -> -254 | D15: =C15+K15 -> -254 | E15: =IF(10,K15="ok",0) -> FALSE | F15: Dia 13 | G15: =G14+I15 -> 13124.08 | H15: Dízimo (1/2 parte) | I15: -140 | J15: Dia 9 | L15: =IF(A15=B15,"➜ Hoje","")
A16: =TODAY() -> 45567 | B16: =B15+1 -> 45822 | C16: =A16-B16 -> -255 | D16: =C16+K16 -> -255 | E16: =IF(10,K16="ok",0) -> FALSE | F16: Dia 14 | G16: =G15+I16 -> 13096.3 | H16: Anticoncepcional | I16: -27.78 | J16: Dia 10 | L16: =IF(A16=B16,"➜ Hoje","")
A17: =TODAY() -> 45567 | B17: =B16+1 -> 45823 | C17: =A17-B17 -> -256 | D17: =C17+K17 -> -256 | E17: =IF(10,K17="ok",0) -> FALSE | F17: Dia 15 | G17: =G16+I17 -> 13079.81 | H17: SimplyPiano | I17: -16.49 | J17: Dia 12 | L17: =IF(A17=B17,"➜ Hoje","")
A18: =TODAY() -> 45567 | B18: =B17+1 -> 45824 | C18: =A18-B18 -> -257 | D18: =C18+K18 -> -257 | E18: =IF(10,K18="ok",0) -> FALSE | F18: Dia 16 | G18: =G17+I18 -> 13079.81 | L18: =IF(A18=B18,"➜ Hoje","") | M18: Planejamento Reposição Dispensa / Compras Mercado
A19: =TODAY() -> 45567 | B19: =B18+1 -> 45825 | C19: =A19-B19 -> -258 | D19: =C19+K19 -> -258 | E19: =IF(10,K19="ok",0) -> FALSE | F19: Dia 17 | G19: =G18+I19 -> 13079.81 | L19: =IF(A19=B19,"➜ Hoje","")
A20: =TODAY() -> 45567 | B20: =B19+1 -> 45826 | C20: =A20-B20 -> -259 | D20: =C20+K20 -> -259 | E20: =IF(10,K20="ok",0) -> FALSE | F20: Dia 18 | G20: =G19+I20 -> 13079.81 | L20: =IF(A20=B20,"➜ Hoje","") | M20: Dia 15 | N20: 210 | O20: Pagamento Recebido VA Bellocopo
A21: =TODAY() -> 45567 | B21: =B20+1 -> 45827 | C21: =A21-B21 -> -260 | D21: =C21+K21 -> -260 | E21: =IF(10,K21="ok",0) -> FALSE | F21: Dia 19 | G21: =G20+I21 -> 13079.81 | H21: Fatura Cartão Nubank | I21: 0 | J21: Dia 12 | L21: =IF(A21=B21,"➜ Hoje","")
A22: =TODAY() -> 45567 | B22: =B21+1 -> 45828 | C22: =A22-B22 -> -261 | D22: =C22+K22 -> -261 | E22: =IF(10,K22="ok",0) -> FALSE | F22: Dia 20 | G22: =G21+I22 -> 14279.81 | H22: Pagamento Recebido Bellocopo | I22: 1200 | J22: Dia 20 | L22: =IF(A22=B22,"➜ Hoje","") | M22: Planejamento Acerto de dividas - prorrogando para mês seguinte
A23: =TODAY() -> 45567 | B23: =B22+1 -> 45829 | C23: =A23-B23 -> -262 | D23: =C23+K23 -> -262 | E23: =IF(10,K23="ok",0) -> FALSE | F23: Dia 21 | G23: =G22+I23 -> 14279.81 | L23: =IF(A23=B23,"➜ Hoje","")
A24: =TODAY() -> 45567 | B24: =B23+1 -> 45830 | C24: =A24-B24 -> -263 | D24: =C24+K24 -> -263 | E24: =IF(10,K24="ok",0) -> FALSE | F24: Dia 22 | G24: =G23+I24 -> 14179.91 | H24: Internet Atranet | I24: -99.9 | J24: Dia 20 | L24: =IF(A24=B24,"➜ Hoje","")
A25: =TODAY() -> 45567 | B25: =B24+1 -> 45831 | C25: =A25-B25 -> -264 | D25: =C25+K25 -> -264 | E25: =IF(10,K25="ok",0) -> FALSE | F25: Dia 23 | G25: =G24+I25 -> 14168.92 | H25: PicsArt Photo | I25: -10.99 | J25: Dia 21 | L25: =IF(A25=B25,"➜ Hoje","")
A26: =TODAY() -> 45567 | B26: =B25+1 -> 45832 | C26: =A26-B26 -> -265 | D26: =C26+K26 -> -265 | E26: =IF(10,K26="ok",0) -> FALSE | F26: Dia 24 | G26: =G25+I26 -> 14168.92 | L26: =IF(A26=B26,"➜ Hoje","")
A27: =TODAY() -> 45567 | B27: =B26+1 -> 45833 | C27: =A27-B27 -> -266 | D27: =C27+K27 -> -266 | E27: =IF(10,K27="ok",0) -> FALSE | F27: Dia 25 | G27: =G26+I27 -> 14048.92 | H27: Dízimo (2/2 parte) | I27: -120 | J27: Dia 24 | L27: =IF(A27=B27,"➜ Hoje","")
A28: =TODAY() -> 45567 | B28: =B27+1 -> 45834 | C28: =A28-B28 -> -267 | D28: =C28+K28 -> -267 | E28: =IF(10,K28="ok",0) -> FALSE | F28: Dia 26 | G28: =G27+I28 -> 13928.92 | H28: Energia Elétrica (1/4 pagamento) | I28: -120 | J28: Dia 20 | L28: =IF(A28=B28,"➜ Hoje","")
A29: =TODAY() -> 45567 | B29: =B28+1 -> 45835 | C29: =A29-B29 -> -268 | D29: =C29+K29 -> -268 | E29: =IF(10,K29="ok",0) -> FALSE | F29: Dia 27 | G29: =G28+I29 -> 13883.92 | H29: Internet Celular Vivo | I29: -45 | J29: Dia 27 | L29: =IF(A29=B29,"➜ Hoje","")
A30: =TODAY() -> 45567 | B30: =B29+1 -> 45836 | C30: =A30-B30 -> -269 | D30: =C30+K30 -> -269 | E30: =IF(10,K30="ok",0) -> FALSE | F30: Dia 28 | G30: =G29+I30 -> 13756.42 | H30: Cílios | I30: -127.5 | J30: Dia 28 | L30: =IF(A30=B30,"➜ Hoje","") | M30: Prorrogar: | N30: =SUM(N24:N29) -> 0
A31: =TODAY() -> 45567 | B31: =B30+1 -> 45837 | C31: =A31-B31 -> -270 | D31: =C31+K31 -> -270 | E31: =IF(10,K31="ok",0) -> FALSE | F31: Dia 29 | G31: =G30+I31 -> 13738.97 | H31: HBO | I31: -17.45 | J31: Dia 29 | L31: =IF(A31=B31,"➜ Hoje","") | M31: =M2 -> Dia 31 | N31: =N2+N30 -> 13738.97 | O31: Valor sobra dia 31 - Final do mês
A32: =TODAY() -> 45567 | B32: =B31+1 -> 45838 | C32: =A32-B32 -> -271 | D32: =C32+K32 -> -271 | E32: =IF(10,K32="ok",0) -> FALSE | F32: Dia 30 | G32: =G31+I32 -> 13738.97 | L32: =IF(A32=B32,"➜ Hoje","") | N32: =N30*2 -> 0
A33: =TODAY() -> 45567 | B33: 45596 | C33: =A33-B33 -> -29 | D33: =C33+K33 -> -29 | E33: =IF(10,K33="ok",0) -> FALSE | F33: Dia 31 | G33: =G32+I33 -> 13738.97 | L33: =IF(A33=B33,"➜ Hoje","") | N33: =N30-N32 -> 0
M34: Pendencias para pagar
M36: {=F2:K33} -> 0 | N36: Saldo Prévio | O36: Descrição Conta | P36: Valor | Q36: Data vencimento | R36: Pago?
M37: Dia 1 | N37: 12154.97 | O37: 0 | P37: 0 | Q37: 0 | R37: 0
M38: Dia 2 | N38: 12126.98 | O38: Nível 6 Mercado Livre - Automatico | P38: -27.99 | Q38: Dia 1 | R38: 0
M39: Dia 3 | N39: 12126.98 | O39: 0 | P39: 0 | Q39: 0 | R39: 0
M40: Dia 4 | N40: 12091.98 | O40: Granulado Madeira (10kg) | P40: -35 | Q40: Dia 5 | R40: 0
M41: Dia 5 | N41: 13491.98 | O41: Pagamento Recebido Bellocopo | P41: 1400 | Q41: Dia 5 | R41: 0
M42: Dia 6 | N42: 13491.98 | O42: Fatura Cartão Mercado Livre | P42: 0 | Q42: Dia 5 | R42: 0
M43: Dia 7 | N43: 13491.98 | O43: 0 | P43: 0 | Q43: Dia 6 | R43: 0
M44: Dia 8 | N44: 13333.98 | O44: Ração Gatos Golden Castrados | P44: -158 | Q44: Dia 6 | R44: 0
M45: Dia 9 | N45: 13294.98 | O45: Microsoft | P45: -39 | Q45: Dia 6 | R45: 0
M46: Dia 10 | N46: 13294.98 | O46: 0 | P46: 0 | Q46: 0 | R46: 0
M47: Dia 11 | N47: 13294.98 | O47: 0 | P47: 0 | Q47: 0 | R47: 0
M48: Dia 12 | N48: 13264.08 | O48: Netflix - Automatico | P48: -30.9 | Q48: Dia 9 | R48: 0
M49: Dia 13 | N49: 13124.08 | O49: Dízimo (1/2 parte) | P49: -140 | Q49: Dia 9 | R49: 0
M50: Dia 14 | N50: 13096.3 | O50: Anticoncepcional | P50: -27.78 | Q50: Dia 10 | R50: 0
M51: Dia 15 | N51: 13079.81 | O51: SimplyPiano | P51: -16.49 | Q51: Dia 12 | R51: 0
M52: Dia 16 | N52: 13079.81 | O52: 0 | P52: 0 | Q52: 0 | R52: 0
M53: Dia 17 | N53: 13079.81 | O53: 0 | P53: 0 | Q53: 0 | R53: 0
M54: Dia 18 | N54: 13079.81 | O54: 0 | P54: 0 | Q54: 0 | R54: 0
M55: Dia 19 | N55: 13079.81 | O55: Fatura Cartão Nubank | P55: 0 | Q55: Dia 12 | R55: 0
M56: Dia 20 | N56: 14279.81 | O56: Pagamento Recebido Bellocopo | P56: 1200 | Q56: Dia 20 | R56: 0
M57: Dia 21 | N57: 14279.81 | O57: 0 | P57: 0 | Q57: 0 | R57: 0
M58: Dia 22 | N58: 14179.91 | O58: Internet Atranet | P58: -99.9 | Q58: Dia 20 | R58: 0
M59: Dia 23 | N59: 14168.92 | O59: PicsArt Photo | P59: -10.99 | Q59: Dia 21 | R59: 0
M60: Dia 24 | N60: 14168.92 | O60: 0 | P60: 0 | Q60: 0 | R60: 0
M61: Dia 25 | N61: 14048.92 | O61: Dízimo (2/2 parte) | P61: -120 | Q61: Dia 24 | R61: 0
M62: Dia 26 | N62: 13928.92 | O62: Energia Elétrica (1/4 pagamento) | P62: -120 | Q62: Dia 20 | R62: 0
M63: Dia 27 | N63: 13883.92 | O63: Internet Celular Vivo | P63: -45 | Q63: Dia 27 | R63: 0
M64: Dia 28 | N64: 13756.42 | O64: Cílios | P64: -127.5 | Q64: Dia 28 | R64: 0
M65: Dia 29 | N65: 13738.97 | O65: HBO | P65: -17.45 | Q65: Dia 29 | R65: 0
M66: Dia 30 | N66: 13738.97 | O66: 0 | P66: 0 | Q66: 0 | R66: 0
M67: Dia 31 | N67: 13738.97 | O67: 0 | P67: 0 | Q67: 0 | R67: 0
